Workbook

Sheet GDP, CFC, NDP, NNI
A1: Gross Domestic Product, Factor Shares, Real Gross Domestic Product, Non-Financial Assets 1896-2023 (nuevos soles)
A2: Year | B2: Labor income (current soles) | C2: Profit income (current soles) | D2: Mixed income (current soles) | E2: T_production (current soles) | F2: Gross Domestic Product (current soles) | G2: CFC (current soles) | H2: Net Foreign Income | I2: Net Domestic Product | J2: Net National Income | K2: Gross Domestic Product (constant soles, 2007) | L2: Non-Financial Assets (soles) (Castillo-García 2026) | M2: Non-Financial Assets (soles) - Spliced WID and Castillo-García (2026)
A3: 1896 | L3: 0.88902316 | M3: 0.89455562
A4: 1897 | L4: 0.88622487 | M4: 0.89173993
A5: 1898 | L5: 0.92951344 | M5: 0.93529788
A6: 1899 | L6: 0.92056365 | M6: 0.9262924
A7: 1900 | L7: 1.0118176 | M7: 1.0181142
A8: 1901 | L8: 1.0188153 | M8: 1.0251555
A9: 1902 | L9: 1.0471995 | M9: 1.0537163
A10: 1903 | L10: 1.1241359 | M10: 1.1311315
A11: 1904 | L11: 1.2512964 | M11: 1.2590833
A12: 1905 | L12: 1.3334012 | M12: 1.3416991
A13: 1906 | L13: 1.3970663 | M13: 1.4057604
A14: 1907 | L14: 1.464504 | M14: 1.4736178
... A48: 1941 | L48: 6.6865575 | M48: 6.7281685
A49: 1942 | B49: 0.958 | C49: 0.78193652 | D49: 1.0660635 | E49: 0.154 | F49: 2.96 | G49: 0.263 | H49: -0.02 | I49: 2.7 | J49: 2.68 | K49: 2.623139e+10 | L49: 8.8686319 | M49: 8.9238221
A50: 1943 | B50: 1.1305307 | C50: 0.82295661 | D50: 1.1243037 | E50: 0.18991668 | F50: 3.2677077 | G50: 0.26178691 | H50: 0 | I50: 3.01 | J50: 3.01 | K50: 2.6936653e+10 | L50: 9.7682202 | M50: 9.8290087
A51: 1944 | B51: 1.4771622 | C51: 0.72132916 | D51: 1.4575608 | E51: 0.21514625 | F51: 3.8711984 | G51: 0.28864931 | H51: 0.06 | I51: 3.58 | J51: 3.64 | K51: 2.9141655e+10 | L51: 11.045127 | M51: 11.113862
A52: 1945 | B52: 1.7874428 | C52: 0.86053316 | D52: 1.6301646 | E52: 0.24408497 | F52: 4.5222256 | G52: 0.25637149 | H52: 0 | I52: 4.27 | J52: 4.26 | K52: 3.0538584e+10 | L52: 12.811184 | M52: 12.890909
A53: 1946 | B53: 2.0332642 | C53: 1.2401414 | D53: 1.8834099 | E53: 0.26631195 | F53: 5.4231275 | G53: 0.32613637 | H53: 0 | I53: 5.1 | J53: 5.1 | K53: 3.2494986e+10 | L53: 15.290451 | M53: 15.385605
A54: 1947 | B54: 2.6448508 | C54: 1.6461839 | D54: 2.4099043 | E54: 0.34238115 | F54: 7.0433202 | G54: 0.25659716 | H54: 0 | I54: 6.79 | J54: 6.78 | K54: 3.3554218e+10 | L54: 20.208526 | M54: 20.334285
A55: 1948 | B55: 3.1963572 | C55: 2.2595183 | D55: 3.1066892 | E55: 0.39474946 | F55: 8.9573141 | G55: 0.40617481 | H55: -0.16 | I55: 8.55 | J55: 8.39 | K55: 3.4837693e+10 | L55: 25.672473 | M55: 25.832235
A56: 1949 | B56: 4.3376049 | C56: 3.8487538 | D56: 3.8519279 | E56: 0.65161074 | F56: 12.689897 | G56: 0.70561919 | H56: -0.05 | I56: 11.98 | J56: 11.94 | K56: 3.7699141e+10 | L56: 34.947514 | M56: 35.164995
A57: 1950 | B57: 5.518 | C57: 4.537 | D57: 5.075 | E57: 0.73 | F57: 15.86 | G57: 0.652 | H57: -0.32 | I57: 15.21 | J57: 14.89 | K57: 40920000000 | L57: 42.790867 | M57: 43.057158
A58: 1951 | B58: 6.639 | C58: 5.801 | D58: 6.369 | E58: 1.12 | F58: 19.929 | G58: 0.843 | H58: -0.21 | I58: 19.09 | J58: 18.88 | K58: 44711000000 | L58: 52.962359 | M58: 53.291948
A59: 1952 | B59: 7.29 | C59: 5.952 | D59: 6.584 | E59: 1.336 | F59: 21.162 | G59: 0.962 | H59: -0.16 | I59: 20.2 | J59: 20.04 | K59: 47347000000 | L59: 57.187979 | M59: 57.543865
A60: 1953 | B60: 8.257 | C60: 5.813 | D60: 7.182 | E60: 1.6 | F60: 22.852 | G60: 0.996 | H60: -0.2 | I60: 21.86 | J60: 21.65 | K60: 50085000000 | L60: 62.679921 | M60: 63.069983
... A129: 2022 | B129: 2.6898654e+11 | C129: 3.9606524e+11 | D129: 1.8788049e+11 | E129: 8.3690031e+10 | F129: 9.3662231e+11 | G129: 7.5645182e+10 | H129: -7.161419e+10 | I129: 8.6097713e+11 | J129: 7.8936294e+11 | K129: 5.6770881e+11 | L129: 4.0023602e+12 | M129: 4.1571484e+12
A130: 2023 | L130: 4.5597298e+12 | M130: 4.4219403e+12

Sheet Comparison Wage Share
B1: Wage Share = [ceugo + ceuco + ceuhn]/market-price GDP | H1: WID (2025) data
A2: Year | B2: Castillo-García (2026) | C2: Dietrich et al (2025) | D2: INE (1981) | E2: INEI (2013) | F2: INEI (2025) | H2: Year | I2: Labor Share in Total Economy (% GDP factor price) (WID) | J2: GDP factor price (gvato) (billion soles) | K2: ceugo + ceuco + ceuhn +0.6*gmxhn (billion soles) | L2: Gross Mixed Income (gmxhn) (billion soles) | M2: ceugo + ceuco + ceuhn (billion soles) | N2: GDP market price | O2: Wage Share on market price GDP
A3: 1942 | B3: =100*'GDP, CFC, NDP, NNI'!B49/'GDP, CFC, NDP, NNI'!F49 -> 32.364865
A4: 1943 | B4: =100*'GDP, CFC, NDP, NNI'!B50/'GDP, CFC, NDP, NNI'!F50 -> 34.597057
A5: 1944 | B5: =100*'GDP, CFC, NDP, NNI'!B51/'GDP, CFC, NDP, NNI'!F51 -> 38.15775
A6: 1945 | B6: =100*'GDP, CFC, NDP, NNI'!B52/'GDP, CFC, NDP, NNI'!F52 -> 39.525733
A7: 1946 | B7: =100*'GDP, CFC, NDP, NNI'!B53/'GDP, CFC, NDP, NNI'!F53 -> 37.492466
A8: 1947 | B8: =100*'GDP, CFC, NDP, NNI'!B54/'GDP, CFC, NDP, NNI'!F54 -> 37.551194
A9: 1948 | B9: =100*'GDP, CFC, NDP, NNI'!B55/'GDP, CFC, NDP, NNI'!F55 -> 35.684327
A10: 1949 | B10: =100*'GDP, CFC, NDP, NNI'!B56/'GDP, CFC, NDP, NNI'!F56 -> 34.18156
A11: 1950 | B11: =100*'GDP, CFC, NDP, NNI'!B57/'GDP, CFC, NDP, NNI'!F57 -> 34.791929
A12: 1951 | B12: =100*'GDP, CFC, NDP, NNI'!B58/'GDP, CFC, NDP, NNI'!F58 -> 33.313262
A13: 1952 | B13: =100*'GDP, CFC, NDP, NNI'!B59/'GDP, CFC, NDP, NNI'!F59 -> 34.44854
A14: 1953 | B14: =100*'GDP, CFC, NDP, NNI'!B60/'GDP, CFC, NDP, NNI'!F60 -> 36.132505
... A30: 1969 | B30: =100*'GDP, CFC, NDP, NNI'!B76/'GDP, CFC, NDP, NNI'!F76 -> 37.570088
A31: 1970 | B31: =100*'GDP, CFC, NDP, NNI'!B77/'GDP, CFC, NDP, NNI'!F77 -> 36.784206 | C31: =O31 -> 36.032824 | D31: 34.820924 | H31: 1970 | I31: 0.5638 | J31: 207.4469 | K31: =I31*J31 -> 116.95856 | L31: 58.9654 | M31: =K31-0.6*L31 -> 81.579322 | N31: 226.4028 | O31: =M31*100/N31 -> 36.032824 | X31: 1991 | Y31: 8.023 | Z31: 14.065 | AA31: 1.952 | AB31: 2.646 | AC31: 1.819 | AD31: 288 | AE31: 539 | AF31: 26.686 | AG31: =Y31/AF31*100 -> 30.064453
A32: 1971 | B32: =100*'GDP, CFC, NDP, NNI'!B78/'GDP, CFC, NDP, NNI'!F78 -> 38.63516 | C32: =O32 -> 37.188652 | D32: 36.137687 | H32: 1971 | I32: 0.5708 | J32: 231.6198 | K32: =I32*J32 -> 132.20858 | L32: 63.8969 | M32: =K32-0.6*L32 -> 93.870442 | N32: 252.4169 | O32: =M32*100/N32 -> 37.188652 | X32: 1992 | Y32: 11.889 | Z32: 25.353 | AA32: 2.931 | AB32: 4.781 | AC32: 3.461 | AD32: 612 | AE32: 708 | AF32: 44.953 | AG32: =Y32/AF32*100 -> 26.447623
A33: 1972 | B33: =100*'GDP, CFC, NDP, NNI'!B79/'GDP, CFC, NDP, NNI'!F79 -> 39.820421 | C33: =O33 -> 39.617326 | D33: 38.224716 | H33: 1972 | I33: 0.5896 | J33: 256.1823 | K33: =I33*J33 -> 151.04508 | L33: 67.1526 | M33: =K33-0.6*L33 -> 110.75352 | N33: 279.5583 | O33: =M33*100/N33 -> 39.617326 | X33: 1993 | Y33: 17.311 | Z33: 40.451 | AA33: 4.336 | AB33: 7.164 | AC33: 5.187 | AD33: 1.171 | AE33: 806 | AF33: 69.262 | AG33: =Y33/AF33*100 -> 24.993503
A34: 1973 | B34: =100*'GDP, CFC, NDP, NNI'!B80/'GDP, CFC, NDP, NNI'!F80 -> 38.545798 | C34: =O34 -> 39.85113 | D34: 38.545798 | H34: 1973 | I34: 0.5884 | J34: 307.9799 | K34: =I34*J34 -> 181.21537 | L34: 80.0885 | M34: =K34-0.6*L34 -> 133.16227 | N34: 334.1493 | O34: =M34*100/N34 -> 39.85113 | X34: 1994 | Y34: 24.766 | Z34: 57.302 | AA34: 5.773 | AB34: 10.738 | AC34: 7.889 | AD34: 1.715 | AE34: 1.134 | AF34: 98.577 | AG34: =Y34/AF34*100 -> 25.123508
A35: 1974 | B35: =100*'GDP, CFC, NDP, NNI'!B81/'GDP, CFC, NDP, NNI'!F81 -> 36.834338 | C35: =O35 -> 37.98381 | D35: 36.495512 | H35: 1974 | I35: 0.5656 | J35: 395.5605 | K35: =I35*J35 -> 223.72902 | L35: 105.8866 | M35: =K35-0.6*L35 -> 160.19706 | N35: 421.7509 | O35: =M35*100/N35 -> 37.98381 | X35: 1995 | Y35: 30.436 | Z35: 69.616 | AA35: 7.531 | AB35: 13.345 | AC35: 9.734 | AD35: 2.26 | AE35: 1.351 | AF35: 120.928 | AG35: =Y35/AF35*100 -> 25.168695
A36: 1975 | B36: =100*'GDP, CFC, NDP, NNI'!B82/'GDP, CFC, NDP, NNI'!F82 -> 37.353461 | C36: =O36 -> 37.414247 | D36: 36.669419 | H36: 1975 | I36: 0.5613 | J36: 498.6301 | K36: =I36*J36 -> 279.88108 | L36: 131.9791 | M36: =K36-0.6*L36 -> 200.69362 | N36: 536.4096 | O36: =M36*100/N36 -> 37.414247 | X36: 1996 | Y36: 34.149 | Z36: 79.474 | AA36: 8.92 | AB36: 14.537 | AC36: 10.695 | AD36: 2.318 | AE36: 1.524 | AF36: 137.081 | AG36: =Y36/AF36*100 -> 24.911549
A37: 1976 | B37: =100*'GDP, CFC, NDP, NNI'!B83/'GDP, CFC, NDP, NNI'!F83 -> 38.049664 | C37: =O37 -> 37.379648 | D37: 46.600501 | H37: 1976 | I37: 0.5591 | J37: 661.6145 | K37: =I37*J37 -> 369.90867 | L37: 176.2392 | M37: =K37-0.6*L37 -> 264.16515 | N37: 706.7085 | O37: =M37*100/N37 -> 37.379648 | X37: 1997 | Y37: 38.064 | Z37: 92.711 | AA37: 10.301 | AB37: 16.457 | AC37: 12.367 | AD37: 2.591 | AE37: 1.499 | AF37: 157.533 | AG37: =Y37/AF37*100 -> 24.162556
A38: 1977 | B38: =100*'GDP, CFC, NDP, NNI'!B84/'GDP, CFC, NDP, NNI'!F84 -> 36.832365 | C38: =O38 -> 36.95689 | D38: 36.732328 | H38: 1977 | I38: 0.5497 | J38: 919.3373 | K38: =I38*J38 -> 505.35971 | L38: 250.1195 | M38: =K38-0.6*L38 -> 355.28801 | N38: 961.358 | O38: =M38*100/N38 -> 36.95689 | X38: 1998 | Y38: 40.781 | Z38: 96.859 | AA38: 11.493 | AB38: 17.149 | AC38: 12.836 | AD38: 2.959 | AE38: 1.354 | AF38: 166.282 | AG38: =Y38/AF38*100 -> 24.525204
A39: 1978 | B39: =100*'GDP, CFC, NDP, NNI'!B85/'GDP, CFC, NDP, NNI'!F85 -> 32.572752 | C39: =O39 -> 31.557788 | D39: 31.348472 | H39: 1978 | I39: 0.5253 | J39: 1397.5193 | K39: =I39*J39 -> 734.11689 | L39: 416.6816 | M39: =K39-0.6*L39 -> 484.10793 | N39: 1534.0363 | O39: =M39*100/N39 -> 31.557788 | X39: 1999 | Y39: 43.346 | Z39: 102.132 | AA39: 11.975 | AB39: 16.967 | AC39: 12.819 | AD39: 2.875 | AE39: 1.273 | AF39: 174.422 | AG39: =Y39/AF39*100 -> 24.851223
A40: 1979 | B40: =100*'GDP, CFC, NDP, NNI'!B86/'GDP, CFC, NDP, NNI'!F86 -> 28.108883 | C40: =O40 -> 26.284398 | D40: 27.261926 | H40: 1979 | I40: 0.4902 | J40: 2524.5726 | K40: =I40*J40 -> 1237.5455 | L40: 831.3312 | M40: =K40-0.6*L40 -> 738.74677 | N40: 2810.5904 | O40: =M40*100/N40 -> 26.284398 | X40: 2000 | Y40: 45.41 | Z40: 110.107 | AA40: 13.063 | AB40: 17.651 | AC40: 13.281 | AD40: 2.96 | AE40: 1.41 | AF40: 186.141 | AG40: =Y40/AF40*100 -> 24.395485
A41: 1980 | B41: =100*'GDP, CFC, NDP, NNI'!B87/'GDP, CFC, NDP, NNI'!F87 -> 30.544315 | C41: =O41 -> 27.854564 | D41: 30.135866 | H41: 1980 | I41: 0.4971 | J41: 4350.3754 | K41: =I41*J41 -> 2162.5716 | L41: 1372.9638 | M41: =K41-0.6*L41 -> 1338.7933 | N41: 4806.3698 | O41: =M41*100/N41 -> 27.854564 | X41: 2001 | Y41: 47.551 | Z41: 110.348 | AA41: 14.209 | AB41: 17.104 | AC41: 13.096 | AD41: 2.791 | AE41: 1.217 | AF41: 189.213 | AG41: =Y41/AF41*100 -> 25.130937
A42: 1981 | B42: =100*'GDP, CFC, NDP, NNI'!B88/'GDP, CFC, NDP, NNI'!F88 -> 32.624907 | C42: =O42 -> 29.004464 | H42: 1981 | I42: 0.504 | J42: 7760.6166 | K42: =I42*J42 -> 3911.3508 | L42: 2372.7667 | M42: =K42-0.6*L42 -> 2487.6907 | N42: 8576.9238 | O42: =M42*100/N42 -> 29.004464 | X42: 2002 | Y42: 49.918 | Z42: 117.289 | AA42: 14.789 | AB42: 17.654 | AC42: 14.399 | AD42: 2.489 | AE42: 766 | AF42: 199.65 | AG42: =Y42/AF42*100 -> 25.002755
A43: 1982 | B43: =100*'GDP, CFC, NDP, NNI'!B89/'GDP, CFC, NDP, NNI'!F89 -> 34.668474 | C43: =O43 -> 29.98966 | H43: 1982 | I43: 0.5133 | J43: 13069.781 | K43: =I43*J43 -> 6708.7185 | L43: 3966.6982 | M43: =K43-0.6*L43 -> 4328.6996 | N43: 14433.974 | O43: =M43*100/N43 -> 29.98966 | X43: 2003 | Y43: 53.312 | Z43: 125.302 | AA43: 15.355 | AB43: 19.456 | AC43: 16.084 | AD43: 2.55 | AE43: 822 | AF43: 213.425 | AG43: =Y43/AF43*100 -> 24.979267
A44: 1983 | B44: =100*'GDP, CFC, NDP, NNI'!B90/'GDP, CFC, NDP, NNI'!F90 -> 36.800576 | C44: =O44 -> 30.90538 | H44: 1983 | I44: 0.5273 | J44: 23962.201 | K44: =I44*J44 -> 12635.268 | L44: 7586.2152 | M44: =K44-0.6*L44 -> 8083.5394 | N44: 26155.767 | O44: =M44*100/N44 -> 30.90538 | X44: 2004 | Y44: 56.977 | Z44: 141.828 | AA44: 16.91 | AB44: 22.187 | AC44: 18.604 | AD44: 2.744 | AE44: 839 | AF44: 237.902 | AG44: =Y44/AF44*100 -> 23.949778
A45: 1984 | B45: =100*'GDP, CFC, NDP, NNI'!B91/'GDP, CFC, NDP, NNI'!F91 -> 34.49769 | C45: =O45 -> 27.938084 | H45: 1984 | I45: 0.5038 | J45: 53459.732 | K45: =I45*J45 -> 26933.013 | L45: 17694.463 | M45: =K45-0.6*L45 -> 16316.335 | N45: 58401.767 | O45: =M45*100/N45 -> 27.938084 | X45: 2005 | Y45: 60.324 | Z45: 157.946 | AA45: 18.512 | AB45: 24.872 | AC45: 20.172 | AD45: 3.143 | AE45: 1.557 | AF45: 261.653 | AG45: =Y45/AF45*100 -> 23.054962
A46: 1985 | B46: =100*'GDP, CFC, NDP, NNI'!B92/'GDP, CFC, NDP, NNI'!F92 -> 32.532352 | C46: =O46 -> 25.727787 | H46: 1985 | I46: 0.4898 | J46: 143856.2 | K46: =I46*J46 -> 70460.768 | L46: 49054.28 | M46: =K46-0.6*L46 -> 41028.2 | N46: 159470.38 | O46: =M46*100/N46 -> 25.727787 | X46: 2006 | Y46: 66.32 | Z46: 187.167 | AA46: 20.9 | AB46: 27.869 | AC46: 23.158 | AD46: 2.847 | AE46: 1.864 | AF46: 302.255 | AG46: =Y46/AF46*100 -> 21.941738
A47: 1986 | B47: =100*'GDP, CFC, NDP, NNI'!B93/'GDP, CFC, NDP, NNI'!F93 -> 37.326401 | C47: =O47 -> 28.672947 | H47: 1986 | I47: 0.5025 | J47: 277731.36 | K47: =I47*J47 -> 139560.01 | L47: 88258.684 | M47: =K47-0.6*L47 -> 86604.798 | N47: 302043.59 | O47: =M47*100/N47 -> 28.672947 | X47: 2007 | Y47: 72.84 | Z47: 209.852 | AA47: 23.201 | AB47: 30.446 | AC47: 26.129 | AD47: 2.198 | AE47: 2.119 | AF47: 336.339 | AG47: =Y47/AF47*100 -> 21.656721
A48: 1987 | B48: =100*'GDP, CFC, NDP, NNI'!B94/'GDP, CFC, NDP, NNI'!F94 -> 41.157624 | C48: =O48 -> 30.901761 | H48: 1987 | I48: 0.511 | J48: 557367.61 | K48: =I48*J48 -> 284814.85 | L48: 166885.73 | M48: =K48-0.6*L48 -> 184683.41 | N48: 597646.88 | O48: =M48*100/N48 -> 30.901761 | X48: 2008 | Y48: 79.219 | Z48: 238.109 | AA48: 25.409 | AB48: 35.513 | AC48: 31.012 | AD48: 1.911 | AE48: 2.59 | AF48: 378.249 | AG48: =Y48/AF48*100 -> 20.943611
A49: 1988 | B49: =100*'GDP, CFC, NDP, NNI'!B95/'GDP, CFC, NDP, NNI'!F95 -> 35.039391 | C49: =O49 -> 24.993745 | H49: 1988 | I49: 0.4696 | J49: 3806233.3 | K49: =I49*J49 -> 1787407.1 | L49: 1313359.9 | M49: =K49-0.6*L49 -> 999391.18 | N49: 3998565.2 | O49: =M49*100/N49 -> 24.993745 | X49: 2009 | Y49: 85.494 | Z49: 246.544 | AA49: 26.312 | AB49: 33.43 | AC49: 29.012 | AD49: 1.493 | AE49: 2.925 | AF49: 391.78 | AG49: =Y49/AF49*100 -> 21.821941
A50: 1989 | B50: =100*'GDP, CFC, NDP, NNI'!B96/'GDP, CFC, NDP, NNI'!F96 -> 36.157093 | C50: =O50 -> 26.675205 | H50: 1989 | I50: 0.4902 | J50: 89561973 | K50: =I50*J50 -> 43903279 | L50: 31827818 | M50: =K50-0.6*L50 -> 24806588 | N50: 92994929 | O50: =M50*100/N50 -> 26.675205 | X50: 2010 | Y50: 93.908 | Z50: 281.465 | AA50: 28.611 | AB50: 40.474 | AC50: 35.605 | AD50: 1.803 | AE50: 3.066 | AF50: 444.46 | AG50: =Y50/AF50*100 -> 21.128561
A51: 1990 | B51: =100*'GDP, CFC, NDP, NNI'!B97/'GDP, CFC, NDP, NNI'!F97 -> 34.840324 | C51: =O51 -> 25.454581 | H51: 1990 | I51: 0.494 | J51: 5.0846393e+09 | K51: =I51*J51 -> 2.5118118e+09 | L51: 1.860019e+09 | M51: =K51-0.6*L51 -> 1.3958004e+09 | N51: 5.4834938e+09 | O51: =M51*100/N51 -> 25.454581 | X51: 2011 | Y51: 105.454 | Z51: 316.782 | AA51: 31.355 | AB51: 44.189 | AC51: 39.123 | AD51: 1.38 | AE51: 3.686 | AF51: 497.78 | AG51: =Y51/AF51*100 -> 21.184861
A52: 1991 | B52: =100*'GDP, CFC, NDP, NNI'!B98/'GDP, CFC, NDP, NNI'!F98 -> 30.064453 | C52: =O52 -> 21.028285 | E52: 30.064453 | H52: 1991 | I52: 0.4628 | J52: 2.4667941e+10 | K52: =I52*J52 -> 1.1416323e+10 | L52: 9.6965079e+09 | M52: =K52-0.6*L52 -> 5.5984182e+09 | N52: 2.6623276e+10 | O52: =M52*100/N52 -> 21.028285 | X52: 2012 | Y52: 116.534 | Z52: 340.142 | AA52: 33.588 | AB52: 47.743 | AC52: 42.101 | AD52: 1.529 | AE52: 4.113 | AF52: 538.006 | AG52: =Y52/AF52*100 -> 21.660353
A53: 1992 | B53: =100*'GDP, CFC, NDP, NNI'!B99/'GDP, CFC, NDP, NNI'!F99 -> 26.447623 | C53: =O53 -> 21.848216 | E53: 26.447623 | H53: 1992 | I53: 0.4732 | J53: 4.0800709e+10 | K53: =I53*J53 -> 1.9306896e+10 | L53: 1.584556e+10 | M53: =K53-0.6*L53 -> 9.7995593e+09 | N53: 4.4852903e+10 | O53: =M53*100/N53 -> 21.848216
A54: 1993 | B54: =100*'GDP, CFC, NDP, NNI'!B100/'GDP, CFC, NDP, NNI'!F100 -> 24.993503 | C54: =O54 -> 21.04361 | E54: 24.993503 | H54: 1993 | I54: 0.4653 | J54: 6.3023765e+10 | K54: =I54*J54 -> 2.9324958e+10 | L54: 2.4648968e+10 | M54: =K54-0.6*L54 -> 1.4535577e+10 | N54: 6.907359e+10 | O54: =M54*100/N54 -> 21.04361
A55: 1994 | B55: =100*'GDP, CFC, NDP, NNI'!B101/'GDP, CFC, NDP, NNI'!F101 -> 25.123508 | C55: =O55 -> 21.702282 | E55: 25.123508 | F55: 34.426196 | H55: 1994 | I55: 0.4636 | J55: 8.8570832e+10 | K55: =I55*J55 -> 4.1061438e+10 | L55: 3.2885755e+10 | M55: =K55-0.6*L55 -> 2.1329984e+10 | N55: 9.8284522e+10 | O55: =M55*100/N55 -> 21.702282
A56: 1995 | B56: =100*'GDP, CFC, NDP, NNI'!B102/'GDP, CFC, NDP, NNI'!F102 -> 25.853044 | C56: =O56 -> 22.558969 | E56: 25.168695 | F56: 34.679827 | H56: 1995 | I56: 0.4662 | J56: 1.0811381e+11 | K56: =I56*J56 -> 5.0402657e+10 | L56: 3.8687459e+10 | M56: =K56-0.6*L56 -> 2.7190182e+10 | N56: 1.2052936e+11 | O56: =M56*100/N56 -> 22.558969
A57: 1996 | B57: =100*'GDP, CFC, NDP, NNI'!B103/'GDP, CFC, NDP, NNI'!F103 -> 26.284679 | C57: =O57 -> 23.021325 | E57: 24.911549 | F57: 34.508798 | H57: 1996 | I57: 0.4652 | J57: 1.225258e+11 | K57: =I57*J57 -> 5.6999004e+10 | L57: 4.2862332e+10 | M57: =K57-0.6*L57 -> 3.1281605e+10 | N57: 1.3588099e+11 | O57: =M57*100/N57 -> 23.021325
A58: 1997 | B58: =100*'GDP, CFC, NDP, NNI'!B104/'GDP, CFC, NDP, NNI'!F104 -> 26.187607 | C58: =O58 -> 23.454415 | E58: 24.162556 | F58: 33.672251 | H58: 1997 | I58: 0.4644 | J58: 1.3931393e+11 | K58: =I58*J58 -> 6.4697389e+10 | L58: 4.7131123e+10 | M58: =K58-0.6*L58 -> 3.6418715e+10 | N58: 1.5527446e+11 | O58: =M58*100/N58 -> 23.454415
A59: 1998 | B59: =100*'GDP, CFC, NDP, NNI'!B105/'GDP, CFC, NDP, NNI'!F105 -> 27.303388 | C59: =O59 -> 24.145591 | E59: 24.525204 | F59: 34.371963 | H59: 1998 | I59: 0.4677 | J59: 1.4671695e+11 | K59: =I59*J59 -> 6.8619516e+10 | L59: 4.8748554e+10 | M59: =K59-0.6*L59 -> 3.9370384e+10 | N59: 1.6305413e+11 | O59: =M59*100/N59 -> 24.145591
A60: 1999 | B60: =100*'GDP, CFC, NDP, NNI'!B106/'GDP, CFC, NDP, NNI'!F106 -> 28.418598 | C60: =O60 -> 24.848844 | E60: 24.851223 | F60: 34.969592 | H60: 1999 | I60: 0.4709 | J60: 1.5359847e+11 | K60: =I60*J60 -> 7.232952e+10 | L60: 5.001531e+10 | M60: =K60-0.6*L60 -> 4.2320334e+10 | N60: 1.7031108e+11 | O60: =M60*100/N60 -> 24.848844
A61: 2000 | B61: =100*'GDP, CFC, NDP, NNI'!B107/'GDP, CFC, NDP, NNI'!F107 -> 28.655983 | C61: =O61 -> 25.561741 | E61: 24.395485 | F61: 34.458756 | H61: 2000 | I61: 0.4736 | J61: 1.6364783e+11 | K61: =I61*J61 -> 7.7503612e+10 | L61: 5.2023653e+10 | M61: =K61-0.6*L61 -> 4.6289421e+10 | N61: 1.8108868e+11 | O61: =M61*100/N61 -> 25.561741
A62: 2001 | B62: =100*'GDP, CFC, NDP, NNI'!B108/'GDP, CFC, NDP, NNI'!F108 -> 30.322536 | C62: =O62 -> 26.203563 | E62: 25.130937 | F62: 35.699376 | H62: 2001 | I62: 0.4751 | J62: 1.6595368e+11 | K62: =I62*J62 -> 7.8844594e+10 | L62: 5.1393525e+10 | M62: =K62-0.6*L62 -> 4.8008479e+10 | N62: 1.8321355e+11 | O62: =M62*100/N62 -> 26.203563
A63: 2002 | B63: =100*'GDP, CFC, NDP, NNI'!B109/'GDP, CFC, NDP, NNI'!F109 -> 30.988151 | C63: =O63 -> 26.917762 | E63: 25.002755 | F63: 35.453135 | H63: 2002 | I63: 0.4752 | J63: 1.7554175e+11 | K63: =I63*J63 -> 8.3417438e+10 | L63: 5.2218922e+10 | M63: =K63-0.6*L63 -> 5.2086085e+10 | N63: 1.935008e+11 | O63: =M63*100/N63 -> 26.917762
A64: 2003 | B64: =100*'GDP, CFC, NDP, NNI'!B110/'GDP, CFC, NDP, NNI'!F110 -> 31.800831 | C64: =O64 -> 27.605895 | E64: 24.979267 | F64: 35.554501 | H64: 2003 | I64: 0.4757 | J64: 1.8637893e+11 | K64: =I64*J64 -> 8.8660458e+10 | L64: 5.337968e+10 | M64: =K64-0.6*L64 -> 5.663265e+10 | N64: 2.0514695e+11 | O64: =M64*100/N64 -> 27.605895
A65: 2004 | B65: =100*'GDP, CFC, NDP, NNI'!B111/'GDP, CFC, NDP, NNI'!F111 -> 31.319242 | C65: =O65 -> 28.23561 | E65: 23.949778 | F65: 34.082085 | H65: 2004 | I65: 0.4757 | J65: 2.0798628e+11 | K65: =I65*J65 -> 9.8939072e+10 | L65: 5.7250631e+10 | M65: =K65-0.6*L65 -> 6.4588693e+10 | N65: 2.2874906e+11 | O65: =M65*100/N65 -> 28.23561
A66: 2005 | B66: =100*'GDP, CFC, NDP, NNI'!B112/'GDP, CFC, NDP, NNI'!F112 -> 30.968855 | C66: =O66 -> 29.02344 | E66: 23.054962 | F66: 32.605913 | H66: 2005 | I66: 0.4744 | J66: 2.2899854e+11 | K66: =I66*J66 -> 1.0863691e+11 | L66: 5.9418152e+10 | M66: =K66-0.6*L66 -> 7.2986015e+10 | N66: 2.5147266e+11 | O66: =M66*100/N66 -> 29.02344
... A73: 2012 | B73: =100*'GDP, CFC, NDP, NNI'!B119/'GDP, CFC, NDP, NNI'!F119 -> 30.721999 | C73: =O73 -> 30.548942 | E73: 21.660353 | F73: 30.721999 | H73: 2012 | I73: 0.4811 | J73: 4.6380588e+11 | K73: =I73*J73 -> 2.2313701e+11 | L73: 1.130766e+11 | M73: =K73-0.6*L73 -> 1.5529105e+11 | N73: 5.0833529e+11 | O73: =M73*100/N73 -> 30.548942
A74: 2013 | B74: =100*'GDP, CFC, NDP, NNI'!B120/'GDP, CFC, NDP, NNI'!F120 -> 31.20764 | C74: =O74 -> 31.046481 | F74: 31.20764 | H74: 2013 | I74: 0.4845 | J74: 4.9530993e+11 | K74: =I74*J74 -> 2.3997766e+11 | L74: 1.1890033e+11 | M74: =K74-0.6*L74 -> 1.6863746e+11 | N74: 5.4317738e+11 | O74: =M74*100/N74 -> 31.046481
A75: 2014 | B75: =100*'GDP, CFC, NDP, NNI'!B121/'GDP, CFC, NDP, NNI'!F121 -> 31.666319 | C75: =O75 -> 31.483359 | F75: 31.666319 | H75: 2014 | I75: 0.4952 | J75: 5.1581676e+11 | K75: =I75*J75 -> 2.5543246e+11 | L75: 1.2669627e+11 | M75: =K75-0.6*L75 -> 1.794147e+11 | N75: 5.6987153e+11 | O75: =M75*100/N75 -> 31.483359
A76: 2015 | B76: =100*'GDP, CFC, NDP, NNI'!B122/'GDP, CFC, NDP, NNI'!F122 -> 31.824108 | C76: =O76 -> 31.641092 | F76: 31.824108 | H76: 2015 | I76: 0.497 | J76: 5.5256305e+11 | K76: =I76*J76 -> 2.7462383e+11 | L76: 1.383455e+11 | M76: =K76-0.6*L76 -> 1.9161653e+11 | N76: 6.0559392e+11 | O76: =M76*100/N76 -> 31.641092
A77: 2016 | B77: =100*'GDP, CFC, NDP, NNI'!B123/'GDP, CFC, NDP, NNI'!F123 -> 31.524948 | C77: =O77 -> 31.351275 | F77: 31.524948 | H77: 2016 | I77: 0.4954 | J77: 5.9323633e+11 | K77: =I77*J77 -> 2.9388928e+11 | L77: 1.5064238e+11 | M77: =K77-0.6*L77 -> 2.0350385e+11 | N77: 6.4910869e+11 | O77: =M77*100/N77 -> 31.351275
A78: 2017 | B78: =100*'GDP, CFC, NDP, NNI'!B124/'GDP, CFC, NDP, NNI'!F124 -> 31.236691 | C78: =O78 -> 31.095945 | F78: 31.264599 | H78: 2017 | I78: 0.488 | J78: 6.3240565e+11 | K78: =I78*J78 -> 3.0861396e+11 | L78: 1.5760216e+11 | M78: =K78-0.6*L78 -> 2.1405266e+11 | N78: 6.8836198e+11 | O78: =M78*100/N78 -> 31.095945
A79: 2018 | B79: =100*'GDP, CFC, NDP, NNI'!B125/'GDP, CFC, NDP, NNI'!F125 -> 31.193261 | C79: =O79 -> 30.935132 | F79: 31.11027 | H79: 2018 | I79: 0.4866 | J79: 6.693445e+11 | K79: =I79*J79 -> 3.2570304e+11 | L79: 1.6520696e+11 | M79: =K79-0.6*L79 -> 2.2657886e+11 | N79: 7.3243217e+11 | O79: =M79*100/N79 -> 30.935132
A80: 2019 | B80: =100*'GDP, CFC, NDP, NNI'!B126/'GDP, CFC, NDP, NNI'!F126 -> 31.206531 | C80: =O80 -> 31.437857 | F80: 31.616543 | H80: 2019 | I80: 0.4944 | J80: 6.9325073e+11 | K80: =I80*J80 -> 3.4274316e+11 | L80: 1.7142671e+11 | M80: =K80-0.6*L80 -> 2.3988713e+11 | N80: 7.630518e+11 | O80: =M80*100/N80 -> 31.437857
A81: 2020 | B81: =100*'GDP, CFC, NDP, NNI'!B127/'GDP, CFC, NDP, NNI'!F127 -> 30.90572 | C81: =O81 -> 30.735396 | F81: 30.90572 | H81: 2020 | I81: 0.4732 | J81: 6.4597239e+11 | K81: =I81*J81 -> 3.0567413e+11 | L81: 1.4741719e+11 | M81: =K81-0.6*L81 -> 2.1722382e+11 | N81: 7.0675459e+11 | O81: =M81*100/N81 -> 30.735396
A82: 2021 | B82: =100*'GDP, CFC, NDP, NNI'!B128/'GDP, CFC, NDP, NNI'!F128 -> 28.222068 | C82: =O82 -> 28.071617 | F82: 28.225249 | H82: 2021 | I82: 0.4399 | J82: 7.9543869e+11 | K82: =I82*J82 -> 3.4991348e+11 | L82: 1.7280398e+11 | M82: =K82-0.6*L82 -> 2.4623109e+11 | N82: 8.7715322e+11 | O82: =M82*100/N82 -> 28.071617
A83: 2022 | B83: =100*'GDP, CFC, NDP, NNI'!B129/'GDP, CFC, NDP, NNI'!F129 -> 28.718785 | C83: =O83 -> 28.552252 | F83: 28.661151 | H83: 2022 | I83: 0.4487 | J83: 8.5809676e+11 | K83: =I83*J83 -> 3.8502801e+11 | L83: 1.9250716e+11 | M83: =K83-0.6*L83 -> 2.6952372e+11 | N83: 9.4396659e+11 | O83: =M83*100/N83 -> 28.552252
A84: 2023 | C84: =O84 -> 28.534274 | F84: 28.334569 | H84: 2023 | I84: 0.4458 | J84: 9.1128031e+11 | K84: =I84*J84 -> 4.0624876e+11 | L84: 2.0062555e+11 | M84: =K84-0.6*L84 -> 2.8587343e+11 | N84: 1.0018598e+12 | O84: =M84*100/N84 -> 28.534274
H85: 2024 | I85: 0.446 | J85: 987370422272 | K85: =I85*J85 -> 4.4036721e+11 | L85: 217570827451 | M85: =K85-0.6*L85 -> 3.0982471e+11 | N85: 1085790420992 | O85: =M85*100/N85 -> 28.534486

Sheet Comparison Mixed Income Share
A1: Gross Mixed Income Share
A2: Year | B2: Castillo-García (2026) | C2: Dietrich et al (2025) | D2: INEI (2025)
A3: 1970 | B3: ='GDP, CFC, NDP, NNI'!D77/'GDP, CFC, NDP, NNI'!F77*100 -> 22.439455 | C3: ='Comparison Wage Share'!L31/'Comparison Wage Share'!N31*100 -> 26.044466
A4: 1971 | B4: ='GDP, CFC, NDP, NNI'!D78/'GDP, CFC, NDP, NNI'!F78*100 -> 21.438444 | C4: ='Comparison Wage Share'!L32/'Comparison Wage Share'!N32*100 -> 25.314034
A5: 1972 | B5: ='GDP, CFC, NDP, NNI'!D79/'GDP, CFC, NDP, NNI'!F79*100 -> 20.857539 | C5: ='Comparison Wage Share'!L33/'Comparison Wage Share'!N33*100 -> 24.020965
A6: 1973 | B6: ='GDP, CFC, NDP, NNI'!D80/'GDP, CFC, NDP, NNI'!F80*100 -> 19.994378 | C6: ='Comparison Wage Share'!L34/'Comparison Wage Share'!N34*100 -> 23.967879
A7: 1974 | B7: ='GDP, CFC, NDP, NNI'!D81/'GDP, CFC, NDP, NNI'!F81*100 -> 20.237239 | C7: ='Comparison Wage Share'!L35/'Comparison Wage Share'!N35*100 -> 25.106431
A8: 1975 | B8: ='GDP, CFC, NDP, NNI'!D82/'GDP, CFC, NDP, NNI'!F82*100 -> 20.531147 | C8: ='Comparison Wage Share'!L36/'Comparison Wage Share'!N36*100 -> 24.604164
A9: 1976 | B9: ='GDP, CFC, NDP, NNI'!D83/'GDP, CFC, NDP, NNI'!F83*100 -> 21.096693 | C9: ='Comparison Wage Share'!L37/'Comparison Wage Share'!N37*100 -> 24.938033
A10: 1977 | B10: ='GDP, CFC, NDP, NNI'!D84/'GDP, CFC, NDP, NNI'!F84*100 -> 20.379247 | C10: ='Comparison Wage Share'!L38/'Comparison Wage Share'!N38*100 -> 26.017311
A11: 1978 | B11: ='GDP, CFC, NDP, NNI'!D85/'GDP, CFC, NDP, NNI'!F85*100 -> 19.979371 | C11: ='Comparison Wage Share'!L39/'Comparison Wage Share'!N39*100 -> 27.162434
A12: 1979 | B12: ='GDP, CFC, NDP, NNI'!D86/'GDP, CFC, NDP, NNI'!F86*100 -> 19.384945 | C12: ='Comparison Wage Share'!L40/'Comparison Wage Share'!N40*100 -> 29.578526
A13: 1980 | B13: ='GDP, CFC, NDP, NNI'!D87/'GDP, CFC, NDP, NNI'!F87*100 -> 19.39732 | C13: ='Comparison Wage Share'!L41/'Comparison Wage Share'!N41*100 -> 28.565505
A14: 1981 | B14: ='GDP, CFC, NDP, NNI'!D88/'GDP, CFC, NDP, NNI'!F88*100 -> 19.918159 | C14: ='Comparison Wage Share'!L42/'Comparison Wage Share'!N42*100 -> 27.664542
... A39: 2006 | B39: ='GDP, CFC, NDP, NNI'!D113/'GDP, CFC, NDP, NNI'!F113*100 -> 20.960572 | C39: ='Comparison Wage Share'!L67/'Comparison Wage Share'!N67*100 -> 22.167158
A40: 2007 | B40: ='GDP, CFC, NDP, NNI'!D114/'GDP, CFC, NDP, NNI'!F114*100 -> 20.474956 | C40: ='Comparison Wage Share'!L68/'Comparison Wage Share'!N68*100 -> 20.984666 | D40: 20.474956
A41: 2008 | B41: ='GDP, CFC, NDP, NNI'!D115/'GDP, CFC, NDP, NNI'!F115*100 -> 20.946986 | C41: ='Comparison Wage Share'!L69/'Comparison Wage Share'!N69*100 -> 21.451519 | D41: 20.946986
A42: 2009 | B42: ='GDP, CFC, NDP, NNI'!D116/'GDP, CFC, NDP, NNI'!F116*100 -> 22.218864 | C42: ='Comparison Wage Share'!L70/'Comparison Wage Share'!N70*100 -> 22.775514 | D42: 22.218864
A43: 2010 | B43: ='GDP, CFC, NDP, NNI'!D117/'GDP, CFC, NDP, NNI'!F117*100 -> 21.699489 | C43: ='Comparison Wage Share'!L71/'Comparison Wage Share'!N71*100 -> 22.231871 | D43: 21.699489
A44: 2011 | B44: ='GDP, CFC, NDP, NNI'!D118/'GDP, CFC, NDP, NNI'!F118*100 -> 21.220846 | C44: ='Comparison Wage Share'!L72/'Comparison Wage Share'!N72*100 -> 21.78206 | D44: 21.220846
A45: 2012 | B45: ='GDP, CFC, NDP, NNI'!D119/'GDP, CFC, NDP, NNI'!F119*100 -> 21.689092 | C45: ='Comparison Wage Share'!L73/'Comparison Wage Share'!N73*100 -> 22.244491 | D45: 21.689092
A46: 2013 | B46: ='GDP, CFC, NDP, NNI'!D120/'GDP, CFC, NDP, NNI'!F120*100 -> 21.337268 | C46: ='Comparison Wage Share'!L74/'Comparison Wage Share'!N74*100 -> 21.889779 | D46: 21.337268
A47: 2014 | B47: ='GDP, CFC, NDP, NNI'!D121/'GDP, CFC, NDP, NNI'!F121*100 -> 21.706158 | C47: ='Comparison Wage Share'!L75/'Comparison Wage Share'!N75*100 -> 22.232427 | D47: 21.706158
A48: 2015 | B48: ='GDP, CFC, NDP, NNI'!D122/'GDP, CFC, NDP, NNI'!F122*100 -> 22.321216 | C48: ='Comparison Wage Share'!L76/'Comparison Wage Share'!N76*100 -> 22.844599 | D48: 22.321216
A49: 2016 | B49: ='GDP, CFC, NDP, NNI'!D123/'GDP, CFC, NDP, NNI'!F123*100 -> 22.699439 | C49: ='Comparison Wage Share'!L77/'Comparison Wage Share'!N77*100 -> 23.207574 | D49: 22.699439
A50: 2017 | B50: ='GDP, CFC, NDP, NNI'!D124/'GDP, CFC, NDP, NNI'!F124*100 -> 22.354718 | C50: ='Comparison Wage Share'!L78/'Comparison Wage Share'!N78*100 -> 22.895245 | D50: 22.354718
A51: 2018 | B51: ='GDP, CFC, NDP, NNI'!D125/'GDP, CFC, NDP, NNI'!F125*100 -> 22.05449 | C51: ='Comparison Wage Share'!L79/'Comparison Wage Share'!N79*100 -> 22.55594 | D51: 22.05449
... A55: 2022 | B55: ='GDP, CFC, NDP, NNI'!D129/'GDP, CFC, NDP, NNI'!F129*100 -> 20.059366 | C55: ='Comparison Wage Share'!L83/'Comparison Wage Share'!N83*100 -> 20.39343 | D55: 19.933327
A56: 2023 | C56: ='Comparison Wage Share'!L84/'Comparison Wage Share'!N84*100 -> 20.025311 | D56: 20.625806

Sheet Comparison Domestic Capital
A1: Year | B1: Castillo-García (2026) | C1: Castillo-García (2026) | D1: Castillo-García (2026) | E1: Castillo-García (2026) | F1: Castillo-García (2026) | G1: Castillo-García (2026) | H1: Castillo-García (2026) | I1: WID - Bauluz et al (2025) | J1: WID - Bauluz et al (2025) and Castillo-García (2026) | K1: PWT 11.0 | L1: PWT 11.0 | M1: WID - Dietrich et al (2025) | N1: WID-Castillo-García (2026) | O1: 2011=100 | P1: 2011=100 | Q1: 2011=100 | R1: 2011=100 | S1: 2011=100 | T1: K-Y | U1: K-Y | V1: Adjusted K-Y | W1: K-Y | X1: K-Y | Y1: K-Y spliced | Z1: K-Y France | AA1: K-Y USA | AB1: K-Y Mexico | AC1: K-Y Colombia
B2: Adjusted Capital Stock (soles) | C2: GDP deflator (2007=100) | D2: Capital Stock (soles) | E2: Adjusted Capital Stock (mill. soles 2007) | F2: Capital Stock (mill. soles 2007) | G2: Market Price GDP (soles 2007) | H2: Market Price GDP (soles) | I2: Domestic Capital (soles) | J2: Non-Financial Assets Spliced Series (soles) | K2: Capital stock at current PPPs (in bil. 2021US$) | L2: Output-side real GDP at current PPPs (in mil. 2021US$) | M2: Market Price GDP (nominal soles) | N2: Market Price GDP (nominal) - Spliced | O2: K - PWT 11.0 | P2: K - Bauluz et al (2025) - WID | Q2: K - Castillo-García (2026) | R2: Adjusted K - Castillo-García (2026) | S2: GDP - Dietrich et al (2025) - WID | T2: WID | U2: Castillo-García (2026) | V2: Castillo-García (2026) | W2: PWT 11.0 | X2: WID | Y2: WID-Castillo-García (2026) | Z2: WID | AA2: WID | AB2: WID | AC2: WID
A3: 1896 | C3: 6.5340592e-11 | D3: =F3*C3*10^6 -> 0.88902316 | F3: 13605.986 | H3: 0.25998177 | J3: =J4*D3/D4 -> 0.89455562 | N3: =H3/H4*N4 -> 0.23851626 | Y3: =J3/N3 -> 3.7505016 | Z3: 6.3639037 | AA3: 4.3332439 | AB3: 3.8817315 | AC3: 3.7974601
A4: 1897 | C4: 6.511642e-11 | D4: =F4*C4*10^6 -> 0.88622487 | F4: 13609.853 | H4: 0.28313582 | J4: =J5*D4/D5 -> 0.89173993 | N4: =H4/H5*N5 -> 0.25975859 | Y4: =J4/N4 -> 3.4329564 | Z4: 6.7253263 | AA4: 4.2498583 | AB4: 3.9434809 | AC4: 3.8609351
A5: 1898 | C5: 6.653861e-11 | D5: =F5*C5*10^6 -> 0.92951344 | F5: 13969.535 | H5: 0.30811303 | J5: =J6*D5/D6 -> 0.93529788 | N5: =H5/H6*N6 -> 0.28267355 | Y5: =J5/N5 -> 3.3087563 | Z5: 6.2542068 | AA5: 3.9870938 | AB5: 3.9464994 | AC5: 3.8173645
A6: 1899 | C6: 6.3811743e-11 | D6: =F6*C6*10^6 -> 0.92056365 | F6: 14426.242 | H6: 0.31175934 | J6: =J7*D6/D7 -> 0.9262924 | N6: =H6/H7*N7 -> 0.2860188 | Y6: =J6/N6 -> 3.2385718 | Z6: 6.1910665 | AA6: 3.9096201 | AB6: 3.974383 | AC6: 3.8407515
A7: 1900 | C7: 6.7725866e-11 | D7: =F7*C7*10^6 -> 1.0118176 | F7: 14939.899 | H7: 0.34858705 | J7: =J8*D7/D8 -> 1.0181142 | N7: =H7/H8*N8 -> 0.31980581 | Y7: =J7/N7 -> 3.1835389 | Z7: 6.2986959 | AA7: 4.8045043 | AB7: 3.998225 | AC7: 3.8714774
A8: 1901 | C8: 6.5561779e-11 | D8: =F8*C8*10^6 -> 1.0188153 | F8: 15539.775 | H8: 0.36207839 | J8: =J9*D8/D9 -> 1.0251555 | N8: =H8/H9*N9 -> 0.33218323 | Y8: =J8/N8 -> 3.0861145 | Z8: 6.6199668 | AA8: 3.8132331 | AB8: 4.0393883 | AC8: 3.8926307
A9: 1902 | C9: 6.3993146e-11 | D9: =F9*C9*10^6 -> 1.0471995 | F9: 16364.245 | H9: 0.372835 | J9: =J10*D9/D10 -> 1.0537163 | N9: =H9/H10*N10 -> 0.34205172 | Y9: =J9/N9 -> 3.0805761 | Z9: 6.7188259 | AA9: 3.7342098 | AB9: 4.008102 | AC9: 3.9201835
A10: 1903 | C10: 6.4766814e-11 | D10: =F10*C10*10^6 -> 1.1241359 | F10: 17356.664 | H10: 0.40291704 | J10: =J11*D10/D11 -> 1.1311315 | N10: =H10/H11*N11 -> 0.36965002 | Y10: =J10/N10 -> 3.0600065 | Z10: 6.7208581 | AA10: 3.7044365 | AB10: 4.0241047 | AC10: 3.9631199
A11: 1904 | C11: 6.7601463e-11 | D11: =F11*C11*10^6 -> 1.2512964 | F11: 18509.901 | H11: 0.43463992 | J11: =J12*D11/D12 -> 1.2590833 | N11: =H11/H12*N12 -> 0.39875369 | Y11: =J11/N11 -> 3.1575465 | Z11: 6.7543847 | AA11: 3.9301835 | AB11: 4.0545919 | AC11: 3.9928934
A12: 1905 | C12: 6.7974347e-11 | D12: =F12*C12*10^6 -> 1.3334012 | F12: 19616.242 | H12: 0.46909753 | J12: =J13*D12/D13 -> 1.3416991 | N12: =H12/H13*N13 -> 0.43036629 | Y12: =J12/N12 -> 3.1175748 | Z12: 6.6409226 | AA12: 3.6553583 | AB12: 4.0732607 | AC12: 3.9952626
A13: 1906 | C13: 6.6518734e-11 | D13: =F13*C13*10^6 -> 1.3970663 | F13: 21002.599 | H13: 0.49571558 | J13: =J14*D13/D14 -> 1.4057604 | N13: =H13/H14*N14 -> 0.45478661 | Y13: =J13/N13 -> 3.0910328 | Z13: 6.9059257 | AA13: 3.641816 | AB13: 4.0810357 | AC13: 4.0972309
A14: 1907 | C14: 6.491316e-11 | D14: =F14*C14*10^6 -> 1.464504 | F14: 22560.973 | H14: 0.51412944 | J14: =J15*D14/D15 -> 1.4736178 | N14: =H14/H15*N15 -> 0.47168012 | Y14: =J14/N14 -> 3.1241888 | Z14: 6.3740808 | AA14: 3.6236753 | AB14: 4.0870793 | AC14: 3.9216737
... A48: 1941 | C48: 8.6819957e-11 | D48: =F48*C48*10^6 -> 6.6865575 | F48: 77016.364 | H48: 2.3012065 | J48: =J49*D48/D49 -> 6.7281685 | N48: =H48/H49*N49 -> 2.1112064 | Y48: =J48/N48 -> 3.1868834 | Z48: 3.3516942 | AA48: 3.2992594 | AB48: 1.621821 | AC48: 2.8605597
A49: 1942 | B49: =E49*C49*10^6 -> 9.8947881 | C49: 1.128419e-10 | D49: =F49*C49*10^6 -> 8.8686319 | E49: 87687.177 | F49: 78593.426 | G49: 2.623139e+10 | H49: 2.96 | J49: =J50*D49/D50 -> 8.9238221 | N49: =H49/H50*N50 -> 2.7156063 | V49: =E49*10^6/G49 -> 3.3428338 | Y49: =J49/N49 -> 3.2861251 | Z49: 3.1163478 | AA49: 2.6003297 | AB49: 1.7579109 | AC49: 2.8305132
A50: 1943 | B50: =E50*C50*10^6 -> 10.898419 | C50: 1.2131083e-10 | D50: =F50*C50*10^6 -> 9.7682202 | E50: 89838.801 | F50: 80522.244 | G50: 2.6936653e+10 | H50: 3.2677077 | J50: =J51*D50/D51 -> 9.8290087 | N50: =H50/H51*N51 -> 2.997908 | V50: =E50*10^6/G50 -> 3.335188 | Y50: =J50/N50 -> 3.2786225 | Z50: 3.3983144 | AA50: 2.2752624 | AB50: 1.9223186 | AC50: 2.8118087
A51: 1944 | B51: =E51*C51*10^6 -> 12.321915 | C51: 1.3284072e-10 | D51: =F51*C51*10^6 -> 11.045127 | E51: 92757.059 | F51: 83145.64 | G51: 2.9141655e+10 | H51: 3.8711984 | J51: =J52*D51/D52 -> 11.113862 | N51: =H51/H52*N52 -> 3.5515713 | V51: =E51*10^6/G51 -> 3.1829716 | Y51: =J51/N51 -> 3.1292802 | Z51: 3.1649218 | AA51: 2.383098 | AB51: 2.1871292 | AC51: 2.7953683
A52: 1945 | B52: =E52*C52*10^6 -> 14.290199 | C52: 1.4808236e-10 | D52: =F52*C52*10^6 -> 12.811184 | E52: 96501.694 | F52: 86513.912 | G52: 3.0538584e+10 | H52: 4.5222256 | J52: =J53*D52/D53 -> 12.890909 | N52: =H52/H53*N53 -> 4.1488461 | V52: =E52*10^6/G52 -> 3.1599924 | Y52: =J52/N52 -> 3.1071071 | Z52: 2.659511 | AA52: 2.2740775 | AB52: 2.1869954 | AC52: 2.777227
A53: 1946 | B53: =E53*C53*10^6 -> 17.05729 | C53: 1.6689121e-10 | D53: =F53*C53*10^6 -> 15.290451 | E53: 102206.04 | F53: 91619.273 | G53: 3.2494986e+10 | H53: 5.4231275 | J53: =J54*D53/D54 -> 15.385605 | N53: =H53/H54*N54 -> 4.9753646 | V53: =E53*10^6/G53 -> 3.1452866 | Y53: =J53/N53 -> 3.0923573 | Z53: 2.314933 | AA53: 2.2608783 | AB53: 2.3211735 | AC53: 2.7533603
A54: 1947 | B54: =E54*C54*10^6 -> 22.54043 | C54: 2.0990864e-10 | D54: =F54*C54*10^6 -> 20.208526 | E54: 107382.1 | F54: 96272.959 | G54: 3.3554218e+10 | H54: 7.0433202 | J54: =J55*D54/D55 -> 20.334285 | N54: =H54/H55*N55 -> 6.4617854 | V54: =E54*10^6/G54 -> 3.2002564 | Y54: =J54/N54 -> 3.1468524 | Z54: 2.5030869 | AA54: 2.4055281 | AB54: 2.3124647 | AC54: 2.7210715
A55: 1948 | B55: =E55*C55*10^6 -> 28.62759 | C55: 2.5711559e-10 | D55: =F55*C55*10^6 -> 25.672473 | E55: 111341.32 | F55: 99847.981 | G55: 3.4837693e+10 | H55: 8.9573141 | J55: =J56*D55/D56 -> 25.832235 | N55: =H55/H56*N56 -> 8.2177496 | V55: =E55*10^6/G55 -> 3.1960016 | Y55: =J55/N55 -> 3.1434682 | Z55: 2.4464147 | AA55: 2.414806 | AB55: 2.1932843 | AC55: 2.6835309
A56: 1949 | B56: =E56*C56*10^6 -> 38.963508 | C56: 3.3660972e-10 | D56: =F56*C56*10^6 -> 34.947514 | E56: 115752.77 | F56: 103822.06 | G56: 3.7699141e+10 | H56: 12.689897 | J56: =J57*D56/D57 -> 35.164995 | N56: =H56/H57*N57 -> 11.64215 | V56: =E56*10^6/G56 -> 3.0704353 | Y56: =J56/N56 -> 3.0204897 | Z56: 2.2533295 | AA56: 2.5675558 | AB56: 1.9761489 | AC56: 2.6351336
A57: 1950 | B57: =E57*C57*10^6 -> 47.715967 | C57: 3.8758553e-10 | D57: =F57*C57*10^6 -> 42.790867 | E57: 123110.81 | F57: 110403.67 | G57: 40920000000 | H57: 15.86 | J57: =J58*D57/D58 -> 43.057158 | K57: 24848.271 | L57: 19284.357 | N57: =H57/H58*N58 -> 14.550512 | V57: =E57*10^6/G57 -> 3.008573 | W57: =K57/L57 -> 1.2885195 | Y57: =J57/N57 -> 2.9591507 | Z57: 2.2842126 | AA57: 2.4864618 | AB57: 1.9826625 | AC57: 2.611408
A58: 1951 | B58: =E58*C58*10^6 -> 59.081246 | C58: 4.4572924e-10 | D58: =F58*C58*10^6 -> 52.962359 | E58: 132549.63 | F58: 118821.82 | G58: 44711000000 | H58: 19.929 | J58: =J59*D58/D59 -> 53.291948 | K58: 27007.232 | L58: 20755.299 | N58: =H58/H59*N59 -> 18.283554 | V58: =E58*10^6/G58 -> 2.9645866 | W58: =K58/L58 -> 1.3012211 | Y58: =J58/N58 -> 2.9147478 | Z58: 2.3990797 | AA58: 2.396529 | AB58: 2.1113966 | AC58: 2.5724084
A59: 1952 | B59: =E59*C59*10^6 -> 63.812252 | C59: 4.4695546e-10 | D59: =F59*C59*10^6 -> 57.187979 | E59: 142770.94 | F59: 127950.06 | G59: 47347000000 | H59: 21.162 | J59: =J60*D59/D60 -> 57.543865 | K59: 29431.412 | L59: 22079.52 | N59: =H59/H60*N60 -> 19.41475 | V59: =E59*10^6/G59 -> 3.0154169 | W59: =K59/L59 -> 1.3329734 | Y59: =J59/N59 -> 2.9639251 | Z59: 2.5052685 | AA59: 2.3980843 | AB59: 2.1238791 | AC59: 2.5535491
A60: 1953 | B60: =E60*C60*10^6 -> 69.937832 | C60: 4.5626435e-10 | D60: =F60*C60*10^6 -> 62.679921 | E60: 153283.58 | F60: 137376.33 | G60: 50085000000 | H60: 22.852 | J60: =J61*D60/D61 -> 63.069983 | K60: 31808.938 | L60: 23338.242 | N60: =H60/H61*N61 -> 20.965215 | V60: =E60*10^6/G60 -> 3.0604687 | W60: =K60/L60 -> 1.3629534 | Y60: =J60/N60 -> 3.0083156 | Z60: 2.5373775 | AA60: 2.3066741 | AB60: 2.0989967 | AC60: 2.554151
A61: 1954 | B61: =E61*C61*10^6 -> 82.028896 | C61: 5.065767e-10 | D61: =F61*C61*10^6 -> 73.518625 | E61: 161927.89 | F61: 145128.32 | G61: 52762000000 | H61: 26.728 | J61: =J62*D61/D62 -> 73.976138 | K61: 33437.059 | L61: 24815.449 | N61: =H61/H62*N62 -> 24.521191 | V61: =E61*10^6/G61 -> 3.0690249 | W61: =K61/L61 -> 1.3474291 | Y61: =J61/N61 -> 3.0168248 | Z61: 2.5436964 | AA61: 2.3947608 | AB61: 2.0046043 | AC61: 2.5472277
A62: 1955 | B62: =E62*C62*10^6 -> 91.29824 | C62: 5.3009417e-10 | D62: =F62*C62*10^6 -> 81.825251 | E62: 172230.23 | F62: 154359.84 | G62: 55858000000 | H62: 29.61 | J62: =J63*D62/D63 -> 82.334457 | K62: 35587.703 | L62: 25997.061 | N62: =H62/H63*N63 -> 27.165238 | V62: =E62*10^6/G62 -> 3.0833583 | W62: =K62/L62 -> 1.3689126 | Y62: =J62/N62 -> 3.0308756 | Z62: 2.5838719 | AA62: 2.3803186 | AB62: 2.0200815 | AC62: 2.5172143
A63: 1956 | B63: =E63*C63*10^6 -> 104.93182 | C63: 5.6437658e-10 | D63: =F63*C63*10^6 -> 94.044881 | E63: 185925.19 | F63: 166634.98 | G63: 58484000000 | H63: 33.007 | J63: =J64*D63/D64 -> 94.63013 | K63: 38194.422 | L63: 26749.988 | N63: =H63/H64*N64 -> 30.281763 | V63: =E63*10^6/G63 -> 3.1790778 | W63: =K63/L63 -> 1.4278295 | Y63: =J63/N63 -> 3.1249875 | Z63: 2.6598379 | AA63: 2.4279284 | AB63: 2.0620612 | AC63: 2.4887125
A64: 1957 | B64: =E64*C64*10^6 -> 116.54585 | C64: 5.790191e-10 | D64: =F64*C64*10^6 -> 104.44618 | E64: 201281.53 | F64: 180384.69 | G64: 62371000000 | H64: 36.114 | J64: =J65*D64/D65 -> 105.09616 | K64: 41061.941 | L64: 28801.992 | N64: =H64/H65*N65 -> 33.132232 | V64: =E64*10^6/G64 -> 3.2271653 | W64: =K64/L64 -> 1.4256632 | Y64: =J64/N64 -> 3.1720217 | Z64: 2.690433 | AA64: 2.4201735 | AB64: 2.0916427 | AC64: 2.3987317
A65: 1958 | B65: =E65*C65*10^6 -> 140.34449 | C65: 6.5312936e-10 | D65: =F65*C65*10^6 -> 125.77273 | E65: 214880.08 | F65: 192569.41 | G65: 61706000000 | H65: 40.302 | J65: =J66*D65/D66 -> 126.55543 | K65: 43129.211 | L65: 28609.02 | N65: =H65/H66*N66 -> 36.974448 | V65: =E65*10^6/G65 -> 3.4823207 | W65: =K65/L65 -> 1.5075389 | Y65: =J65/N65 -> 3.4227808 | Z65: 2.839258 | AA65: 2.5233353 | AB65: 2.0831999 | AC65: 2.2925574
A66: 1959 | B66: =E66*C66*10^6 -> 167.47862 | C66: 7.4392409e-10 | D66: =F66*C66*10^6 -> 150.07747 | E66: 225128.64 | F66: 201737.61 | G66: 63653000000 | H66: 47.353 | J66: =J67*D66/D67 -> 151.01141 | K66: 44492.93 | L66: 29232.176 | N66: =H66/H67*N67 -> 43.443279 | V66: =E66*10^6/G66 -> 3.5368112 | W66: =K66/L66 -> 1.5220533 | Y66: =J66/N66 -> 3.4760592 | Z66: 2.9643218 | AA66: 2.4896597 | AB66: 2.0773508 | AC66: 2.3152582
A67: 1960 | B67: =E67*C67*10^6 -> 192.25293 | C67: 8.1361336e-10 | D67: =F67*C67*10^6 -> 172.26046 | E67: 236295.2 | F67: 211722.76 | G67: 69946000000 | H67: 56.909 | J67: =J68*D67/D68 -> 173.33245 | K67: 46282.969 | L67: 31960.348 | N67: =H67/H68*N68 -> 52.210284 | V67: =E67*10^6/G67 -> 3.3782517 | W67: =K67/L67 -> 1.4481372 | Y67: =J67/N67 -> 3.3198911 | Z67: 2.8920586 | AA67: 2.874893 | AB67: 2.1021874 | AC67: 2.3452869
A68: 1961 | B68: =E68*C68*10^6 -> 214.58339 | C68: 8.5083572e-10 | D68: =F68*C68*10^6 -> 192.21394 | E68: 252203.08 | F68: 225911.94 | G68: 75085000000 | H68: 63.885 | J68: =J69*D68/D69 -> 193.41011 | K68: 48275.07 | L68: 34245.875 | N68: =H68/H69*N69 -> 58.610307 | V68: =E68*10^6/G68 -> 3.3589009 | W68: =K68/L68 -> 1.4096609 | Y68: =J68/N68 -> 3.2999334 | Z68: 2.9536247 | AA68: 3.2952471 | AB68: 2.0980075 | AC68: 2.3370564
... A86: 1979 | B86: =E86*C86*10^6 -> 15707.264 | C86: 2.2663115e-08 | D86: =F86*C86*10^6 -> 14000.596 | E86: 693076.13 | F86: 617770.17 | G86: 158194000000 | H86: 3585.1688 | J86: =J87*D86/D87 -> 14087.723 | K86: 100654.12 | L86: 74821.836 | N86: =H86/H87*N87 -> 3289.1578 | V86: =E86*10^6/G86 -> 4.3811784 | W86: =K86/L86 -> 1.3452506 | Y86: =J86/N86 -> 4.2830792 | Z86: 3.1409816 | AA86: 2.9916158 | AB86: 2.2280649 | AC86: 2.2426259
A87: 1980 | B87: =E87*C87*10^6 -> 22710.508 | C87: 3.1259241e-08 | D87: =F87*C87*10^6 -> 20240.112 | E87: 726521.42 | F87: 647492.11 | G87: 167596000000 | H87: 5238.9238 | I87: 20366.068 | J87: =I87 -> 20366.068 | K87: 107082.41 | L87: 82544.594 | M87: 4806.3698 | N87: =M87 -> 4806.3698 | O87: =100*K87/$K$128 -> 4.9827043 | P87: =100*I87/$I$128 -> 5.5072138e-07 | Q87: =100*D87/$D$128 -> 5.5089018e-07 | R87: =100*B87/$B$128 -> 5.4914264e-07 | S87: =100*M87/$M$128 -> 5.4795099e-07 | T87: =I87/M87 -> 4.2373077 | U87: =F87/G87*10^6 -> 3.8634103 | V87: =E87*10^6/G87 -> 4.3349568 | W87: =K87/L87 -> 1.2972674 | X87: =J87/N87 -> 4.2373077 | Y87: =X87 -> 4.2373077 | Z87: 3.1962568 | AA87: 3.2295621 | AB87: 2.2818368 | AC87: 2.2285687
A88: 1981 | B88: =E88*C88*10^6 -> 39534.564 | C88: 5.1681067e-08 | D88: =F88*C88*10^6 -> 35226.92 | E88: 764971.9 | F88: 681621.38 | G88: 176901000000 | H88: 9142.4324 | I88: 35423.567 | J88: =I88 -> 35423.567 | K88: 117148.48 | L88: 89468.992 | M88: 8576.9238 | N88: =M88 -> 8576.9238 | O88: =100*K88/$K$128 -> 5.4510936 | P88: =100*I88/$I$128 -> 9.5789309e-07 | Q88: =100*D88/$D$128 -> 9.5879728e-07 | R88: =100*B88/$B$128 -> 9.5595018e-07 | S88: =100*M88/$M$128 -> 9.7781363e-07 | T88: =I88/M88 -> 4.1301016 | U88: =F88/G88*10^6 -> 3.8531234 | V88: =E88*10^6/G88 -> 4.3242938 | W88: =K88/L88 -> 1.3093753 | X88: =J88/N88 -> 4.1301016 | Z88: 3.2085023 | AA88: 3.2268125 | AB88: 2.2977978 | AC88: 2.1898269
A89: 1982 | B89: =E89*C89*10^6 -> 68986.754 | C89: 8.613343e-08 | D89: =F89*C89*10^6 -> 61465.103 | E89: 800928.91 | F89: 713603.34 | G89: 176507000000 | H89: 15203.153 | I89: 62280.287 | J89: =I89 -> 62280.287 | K89: 127595.84 | L89: 90324.773 | M89: 14433.974 | N89: =M89 -> 14433.974 | O89: =100*K89/$K$128 -> 5.9372244 | P89: =100*I89/$I$128 -> 1.684129e-06 | Q89: =100*D89/$D$128 -> 1.6729414e-06 | R89: =100*B89/$B$128 -> 1.6681074e-06 | S89: =100*M89/$M$128 -> 1.6455476e-06 | T89: =I89/M89 -> 4.31484 | U89: =F89/G89*10^6 -> 4.042918 | V89: =E89*10^6/G89 -> 4.5376609 | W89: =K89/L89 -> 1.4126339 | X89: =J89/N89 -> 4.31484 | Z89: 3.1282055 | AA89: 3.3373441 | AB89: 2.1488665 | AC89: 2.2370704
A90: 1983 | B90: =E90*C90*10^6 -> 146447.61 | C90: 1.7863794e-07 | D90: =F90*C90*10^6 -> 130483.44 | E90: 819801.3 | F90: 730435.19 | G90: 158136000000 | H90: 28249.089 | I90: 118695.83 | J90: =I90 -> 118695.83 | K90: 133929.06 | L90: 83941.883 | M90: 26155.767 | N90: =M90 -> 26155.767 | O90: =100*K90/$K$128 -> 6.2319189 | P90: =100*I90/$I$128 -> 3.2096688e-06 | Q90: =100*D90/$D$128 -> 3.5514647e-06 | R90: =100*B90/$B$128 -> 3.5411197e-06 | S90: =100*M90/$M$128 -> 2.9818926e-06 | T90: =I90/M90 -> 4.5380367 | U90: =F90/G90*10^6 -> 4.6190316 | V90: =E90*10^6/G90 -> 5.1841535 | W90: =K90/L90 -> 1.5954975 | X90: =J90/N90 -> 4.5380367 | Z90: 3.1381366 | AA90: 3.2622432 | AB90: 2.1161232 | AC90: 2.2028161
A91: 1984 | B91: =E91*C91*10^6 -> 310826.01 | C91: 3.7241995e-07 | D91: =F91*C91*10^6 -> 276948.46 | E91: 834611.59 | F91: 743645.6 | G91: 163842000000 | H91: 61018.03 | I91: 265252.95 | J91: =I91 -> 265252.95 | K91: 141486.52 | L91: 87343.016 | M91: 58401.767 | N91: =M91 -> 58401.767 | O91: =100*K91/$K$128 -> 6.5835784 | P91: =100*I91/$I$128 -> 7.1727381e-06 | Q91: =100*D91/$D$128 -> 7.5379122e-06 | R91: =100*B91/$B$128 -> 7.5158077e-06 | S91: =100*M91/$M$128 -> 6.6581032e-06 | T91: =I91/M91 -> 4.5418652 | U91: =F91/G91*10^6 -> 4.5387971 | V91: =E91*10^6/G91 -> 5.0940027 | W91: =K91/L91 -> 1.619895 | X91: =J91/N91 -> 4.5418652 | Z91: 3.1257683 | AA91: 3.1316819 | AB91: 2.1910757 | AC91: 2.1691165
A92: 1985 | B92: =E92*C92*10^6 -> 835558.77 | C92: 9.8965028e-07 | D92: =F92*C92*10^6 -> 744508.8 | E92: 844297 | F92: 752294.84 | G92: 167219000000 | H92: 165488.33 | I92: 754035.32 | J92: =I92 -> 754035.32 | K92: 149934.38 | L92: 87949.125 | M92: 159470.38 | N92: =M92 -> 159470.38 | O92: =100*K92/$K$128 -> 6.9766699 | P92: =100*I92/$I$128 -> 2.0389963e-05 | Q92: =100*D92/$D$128 -> 2.026385e-05 | R92: =100*B92/$B$128 -> 2.0203905e-05 | S92: =100*M92/$M$128 -> 1.8180447e-05 | T92: =I92/M92 -> 4.7283723 | U92: =F92/G92*10^6 -> 4.4988598 | V92: =E92*10^6/G92 -> 5.0490495 | W92: =K92/L92 -> 1.7047853 | X92: =J92/N92 -> 4.7283723 | Z92: 3.0763147 | AA92: 3.1716669 | AB92: 2.2256218 | AC92: 2.0169428
A93: 1986 | B93: =E93*C93*10^6 -> 1431936.9 | C93: 1.6662102e-06 | D93: =F93*C93*10^6 -> 1275912.9 | E93: 859397.54 | F93: 765757.48 | G93: 182981000000 | H93: 304884.8 | I93: 1435859.8 | J93: =I93 -> 1435859.8 | K93: 162655.98 | L93: 101248.96 | M93: 302043.59 | N93: =M93 -> 302043.59 | O93: =100*K93/$K$128 -> 7.5686254 | P93: =100*I93/$I$128 -> 3.8827264e-05 | Q93: =100*D93/$D$128 -> 3.472747e-05 | R93: =100*B93/$B$128 -> 3.4624395e-05 | S93: =100*M93/$M$128 -> 3.443453e-05 | T93: =I93/M93 -> 4.7538165 | U93: =F93/G93*10^6 -> 4.1849016 | V93: =E93*10^6/G93 -> 4.696649 | W93: =K93/L93 -> 1.6064953 | X93: =J93/N93 -> 4.7538165 | Z93: 3.0833015 | AA93: 3.2951726 | AB93: 2.0891451 | AC93: 2.104744
A94: 1987 | B94: =E94*C94*10^6 -> 2728716.2 | C94: 3.0933138e-06 | D94: =F94*C94*10^6 -> 2431435.2 | E94: 882133.64 | F94: 786029.27 | G94: 200778000000 | H94: 621069.36 | I94: 2790377.1 | J94: =I94 -> 2790377.1 | K94: 181162.25 | L94: 113404.54 | M94: 597646.88 | N94: =M94 -> 597646.88 | O94: =100*K94/$K$128 -> 8.4297495 | P94: =100*I94/$I$128 -> 7.5454936e-05 | Q94: =100*D94/$D$128 -> 6.617818e-05 | R94: =100*B94/$B$128 -> 6.5980662e-05 | S94: =100*M94/$M$128 -> 6.8134832e-05 | T94: =I94/M94 -> 4.6689396 | U94: =F94/G94*10^6 -> 3.9149173 | V94: =E94*10^6/G94 -> 4.3935772 | W94: =K94/L94 -> 1.5974868 | X94: =J94/N94 -> 4.6689396 | Z94: 3.1128139 | AA94: 3.3315134 | AB94: 2.103462 | AC94: 2.1388743
A95: 1988 | B95: =E95*C95*10^6 -> 19046290 | C95: 2.1228744e-05 | D95: =F95*C95*10^6 -> 16970250 | E95: 897193.41 | F95: 799399.59 | G95: 181822000000 | H95: 3859852.8 | I95: 18923213 | J95: =I95 -> 18923213 | K95: 201197.31 | L95: 107476.73 | M95: 3998565.2 | N95: =M95 -> 3998565.2 | O95: =100*K95/$K$128 -> 9.3620108 | P95: =100*I95/$I$128 -> 0.00051170496 | Q95: =100*D95/$D$128 -> 0.00046189191 | R95: =100*B95/$B$128 -> 0.00046054142 | S95: =100*M95/$M$128 -> 0.0004558571 | T95: =I95/M95 -> 4.7325008 | U95: =F95/G95*10^6 -> 4.3966054 | V95: =E95*10^6/G95 -> 4.9344602 | W95: =K95/L95 -> 1.8720081 | X95: =J95/N95 -> 4.7325008 | Z95: 3.0799139 | AA95: 3.3086647 | AB95: 2.4141385 | AC95: 2.1209181
A96: 1989 | B96: =E96*C96*10^6 -> 5.1273829e+08 | C96: 0.00056730199 | D96: =F96*C96*10^6 -> 4.5680591e+08 | E96: 903818.96 | F96: 805225.29 | G96: 159436000000 | H96: 90448360 | I96: 4.5182863e+08 | J96: =I96 -> 4.5182863e+08 | K96: 219880.7 | L96: 89560.266 | M96: 92994929 | N96: =M96 -> 92994929 | O96: =100*K96/$K$128 -> 10.231377 | P96: =100*I96/$I$128 -> 0.012217954 | Q96: =100*D96/$D$128 -> 0.012433226 | R96: =100*B96/$B$128 -> 0.012398069 | S96: =100*M96/$M$128 -> 0.010601902 | T96: =I96/M96 -> 4.8586372 | U96: =F96/G96*10^6 -> 5.050461 | V96: =E96*10^6/G96 -> 5.6688512 | W96: =K96/L96 -> 2.4551145 | X96: =J96/N96 -> 4.8586372 | Z96: 3.1419743 | AA96: 3.3297751 | AB96: 2.5363937 | AC96: 2.18046
A97: 1990 | B97: =E97*C97*10^6 -> 3.2787627e+10 | C97: 0.036087415 | D97: =F97*C97*10^6 -> 2.9208211e+10 | E97: 908561.25 | F97: 809373.87 | G97: 151492000000 | H97: 5.4669547e+09 | I97: 2.7445841e+10 | J97: =I97 -> 2.7445841e+10 | K97: 244730.12 | L97: 90680.258 | M97: 5.4834938e+09 | N97: =M97 -> 5.4834938e+09 | O97: =100*K97/$K$128 -> 11.387657 | P97: =100*I97/$I$128 -> 0.74216641 | Q97: =100*D97/$D$128 -> 0.7949816 | R97: =100*B97/$B$128 -> 0.79280849 | S97: =100*M97/$M$128 -> 0.62514663 | T97: =I97/M97 -> 5.005174 | U97: =F97/G97*10^6 -> 5.3426839 | V97: =E97*10^6/G97 -> 5.9974207 | W97: =K97/L97 -> 2.6988248 | X97: =J97/N97 -> 5.005174 | Z97: 3.1719972 | AA97: 3.2880294 | AB97: 2.6041302 | AC97: 2.2185045
A98: 1991 | B98: =E98*C98*10^6 -> 1.5755298e+11 | C98: 0.17233007 | D98: =F98*C98*10^6 -> 1.4034278e+11 | E98: 914251.25 | F98: 814383.63 | G98: 154854000000 | H98: 26686000000 | I98: 1.2335766e+11 | J98: =I98 -> 1.2335766e+11 | K98: 276582.91 | L98: 94453.461 | M98: 2.6623276e+10 | N98: =M98 -> 2.6623276e+10 | O98: =100*K98/$K$128 -> 12.869815 | P98: =100*I98/$I$128 -> 3.3357299 | Q98: =100*D98/$D$128 -> 3.8198139 | R98: =100*B98/$B$128 -> 3.8096487 | S98: =100*M98/$M$128 -> 3.035191 | T98: =I98/M98 -> 4.6334517 | U98: =F98/G98*10^6 -> 5.2590416 | V98: =E98*10^6/G98 -> 5.9039563 | W98: =K98/L98 -> 2.9282453 | X98: =J98/N98 -> 4.6334517 | Z98: 3.144855 | AA98: 3.3208333 | AB98: 2.6616881 | AC98: 2.1522353
A99: 1992 | B99: =E99*C99*10^6 -> 2.6571131e+11 | C99: 0.29187038 | D99: =F99*C99*10^6 -> 2.3666014e+11 | E99: 910374.35 | F99: 810839.87 | G99: 154017000000 | H99: 44953000000 | I99: 2.1642519e+11 | J99: =I99 -> 2.1642519e+11 | K99: 306940.28 | L99: 97113.672 | M99: 4.4852903e+10 | N99: =M99 -> 4.4852903e+10 | O99: =100*K99/$K$128 -> 14.282389 | P99: =100*I99/$I$128 -> 5.8523804 | Q99: =100*D99/$D$128 -> 6.441355 | R99: =100*B99/$B$128 -> 6.4249291 | S99: =100*M99/$M$128 -> 5.1134627 | T99: =I99/M99 -> 4.8252214 | U99: =F99/G99*10^6 -> 5.2646128 | V99: =E99*10^6/G99 -> 5.9108693 | W99: =K99/L99 -> 3.1606289 | X99: =J99/N99 -> 4.8252214 | Z99: 3.0871017 | AA99: 3.2545277 | AB99: 2.9618111 | AC99: 2.3014611
... A129: 2022 | B129: =E129*C129*10^6 -> 4.5051818e+12 | C129: 1.6498288 | D129: =F129*C129*10^6 -> 4.0023602e+12 | E129: 2730696.6 | F129: 2425924.7 | G129: 5.6770881e+11 | H129: 9.3662231e+11 | I129: 4.1571484e+12 | J129: =I129 -> 4.1571484e+12 | K129: 2259697 | L129: 489804.91 | M129: 9.4396659e+11 | N129: =M129 -> 9.4396659e+11 | O129: =100*K129/$K$128 -> 105.14707 | P129: =100*I129/$I$128 -> 112.41397 | Q129: =100*D129/$D$128 -> 108.93522 | R129: =100*B129/$B$128 -> 108.9358 | S129: =100*M129/$M$128 -> 107.61707 | T129: =I129/M129 -> 4.4039148 | U129: =F129/G129*10^6 -> 4.2731848 | V129: =E129*10^6/G129 -> 4.8100304 | W129: =K129/L129 -> 4.6134634 | X129: =J129/N129 -> 4.4039148 | Z129: 5.528344 | AA129: 5.0347337 | AB129: 3.5372871 | AC129: 2.9430709
A130: 2023 | B130: =E130*C130*10^6 -> 5.1326255e+12 | C130: =L214*10^6/G130 -> 1.8002629 | D130: =F130*C130*10^6 -> 4.5597298e+12 | E130: 2851042.2 | F130: 2532813.2 | G130: 5.6571928e+11 | H130: =H129*M130/M129 -> 9.9406513e+11 | I130: 4.4219403e+12 | J130: =I130 -> 4.4219403e+12 | K130: 2341043.2 | L130: 483526.5 | M130: 1.0018598e+12 | N130: =M130 -> 1.0018598e+12 | O130: =100*K130/$K$128 -> 108.93223 | P130: =100*I130/$I$128 -> 119.57424 | Q130: =100*D130/$D$128 -> 124.10556 | R130: =100*B130/$B$128 -> 124.10746 | S130: =100*M130/$M$128 -> 114.2172 | T130: =I130/M130 -> 4.4137315 | U130: =F130/G130*10^6 -> 4.4771556 | V130: =E130*10^6/G130 -> 5.0396765 | W130: =K130/L130 -> 4.8416028 | X130: =J130/N130 -> 4.4137315 | Z130: 5.2432317 | AA130: 4.8210564 | AB130: 3.6668297 | AC130: 3.0671789
E133: 2599647.6
E134: 2730696.6
E135: 2851042.2
L214: 1018443.4

Sheet nwnfa
A1: country | B1: year | C1: gdpro | D1: nninc | E1: mnwnfa | F1: ynwnfa | G1: wnwnfa
A2: notes: | C2: market-price GDP in current soles | D2: soles | E2: current soles | F2: % GDP | G2: % NNI
A3: PE | B3: 1896 | C3: ='Comparison Domestic Capital'!N3 -> 0.23851626 | E3: ='Comparison Domestic Capital'!J3 -> 0.89455562 | F3: =E3/C3 -> 3.7505016
A4: PE | B4: 1897 | C4: ='Comparison Domestic Capital'!N4 -> 0.25975859 | E4: ='Comparison Domestic Capital'!J4 -> 0.89173993 | F4: =E4/C4 -> 3.4329564
A5: PE | B5: 1898 | C5: ='Comparison Domestic Capital'!N5 -> 0.28267355 | E5: ='Comparison Domestic Capital'!J5 -> 0.93529788 | F5: =E5/C5 -> 3.3087563
A6: PE | B6: 1899 | C6: ='Comparison Domestic Capital'!N6 -> 0.2860188 | E6: ='Comparison Domestic Capital'!J6 -> 0.9262924 | F6: =E6/C6 -> 3.2385718
A7: PE | B7: 1900 | C7: ='Comparison Domestic Capital'!N7 -> 0.31980581 | E7: ='Comparison Domestic Capital'!J7 -> 1.0181142 | F7: =E7/C7 -> 3.1835389
A8: PE | B8: 1901 | C8: ='Comparison Domestic Capital'!N8 -> 0.33218323 | E8: ='Comparison Domestic Capital'!J8 -> 1.0251555 | F8: =E8/C8 -> 3.0861145
A9: PE | B9: 1902 | C9: ='Comparison Domestic Capital'!N9 -> 0.34205172 | E9: ='Comparison Domestic Capital'!J9 -> 1.0537163 | F9: =E9/C9 -> 3.0805761
A10: PE | B10: 1903 | C10: ='Comparison Domestic Capital'!N10 -> 0.36965002 | E10: ='Comparison Domestic Capital'!J10 -> 1.1311315 | F10: =E10/C10 -> 3.0600065
A11: PE | B11: 1904 | C11: ='Comparison Domestic Capital'!N11 -> 0.39875369 | E11: ='Comparison Domestic Capital'!J11 -> 1.2590833 | F11: =E11/C11 -> 3.1575465
A12: PE | B12: 1905 | C12: ='Comparison Domestic Capital'!N12 -> 0.43036629 | E12: ='Comparison Domestic Capital'!J12 -> 1.3416991 | F12: =E12/C12 -> 3.1175748
A13: PE | B13: 1906 | C13: ='Comparison Domestic Capital'!N13 -> 0.45478661 | E13: ='Comparison Domestic Capital'!J13 -> 1.4057604 | F13: =E13/C13 -> 3.0910328
A14: PE | B14: 1907 | C14: ='Comparison Domestic Capital'!N14 -> 0.47168012 | E14: ='Comparison Domestic Capital'!J14 -> 1.4736178 | F14: =E14/C14 -> 3.1241888
... A48: PE | B48: 1941 | C48: ='Comparison Domestic Capital'!N48 -> 2.1112064 | E48: ='Comparison Domestic Capital'!J48 -> 6.7281685 | F48: =E48/C48 -> 3.1868834
A49: PE | B49: 1942 | C49: ='Comparison Domestic Capital'!N49 -> 2.7156063 | D49: ='GDP, CFC, NDP, NNI'!J49 -> 2.68 | E49: ='Comparison Domestic Capital'!J49 -> 8.9238221 | F49: =E49/C49 -> 3.2861251 | G49: =E49/D49 -> 3.3297844
A50: PE | B50: 1943 | C50: ='Comparison Domestic Capital'!N50 -> 2.997908 | D50: ='GDP, CFC, NDP, NNI'!J50 -> 3.01 | E50: ='Comparison Domestic Capital'!J50 -> 9.8290087 | F50: =E50/C50 -> 3.2786225 | G50: =E50/D50 -> 3.2654514
A51: PE | B51: 1944 | C51: ='Comparison Domestic Capital'!N51 -> 3.5515713 | D51: ='GDP, CFC, NDP, NNI'!J51 -> 3.64 | E51: ='Comparison Domestic Capital'!J51 -> 11.113862 | F51: =E51/C51 -> 3.1292802 | G51: =E51/D51 -> 3.0532587
A52: PE | B52: 1945 | C52: ='Comparison Domestic Capital'!N52 -> 4.1488461 | D52: ='GDP, CFC, NDP, NNI'!J52 -> 4.26 | E52: ='Comparison Domestic Capital'!J52 -> 12.890909 | F52: =E52/C52 -> 3.1071071 | G52: =E52/D52 -> 3.026035
A53: PE | B53: 1946 | C53: ='Comparison Domestic Capital'!N53 -> 4.9753646 | D53: ='GDP, CFC, NDP, NNI'!J53 -> 5.1 | E53: ='Comparison Domestic Capital'!J53 -> 15.385605 | F53: =E53/C53 -> 3.0923573 | G53: =E53/D53 -> 3.0167853
A54: PE | B54: 1947 | C54: ='Comparison Domestic Capital'!N54 -> 6.4617854 | D54: ='GDP, CFC, NDP, NNI'!J54 -> 6.78 | E54: ='Comparison Domestic Capital'!J54 -> 20.334285 | F54: =E54/C54 -> 3.1468524 | G54: =E54/D54 -> 2.9991571
A55: PE | B55: 1948 | C55: ='Comparison Domestic Capital'!N55 -> 8.2177496 | D55: ='GDP, CFC, NDP, NNI'!J55 -> 8.39 | E55: ='Comparison Domestic Capital'!J55 -> 25.832235 | F55: =E55/C55 -> 3.1434682 | G55: =E55/D55 -> 3.0789315
A56: PE | B56: 1949 | C56: ='Comparison Domestic Capital'!N56 -> 11.64215 | D56: ='GDP, CFC, NDP, NNI'!J56 -> 11.94 | E56: ='Comparison Domestic Capital'!J56 -> 35.164995 | F56: =E56/C56 -> 3.0204897 | G56: =E56/D56 -> 2.945142
A57: PE | B57: 1950 | C57: ='Comparison Domestic Capital'!N57 -> 14.550512 | D57: ='GDP, CFC, NDP, NNI'!J57 -> 14.89 | E57: ='Comparison Domestic Capital'!J57 -> 43.057158 | F57: =E57/C57 -> 2.9591507 | G57: =E57/D57 -> 2.8916829
A58: PE | B58: 1951 | C58: ='Comparison Domestic Capital'!N58 -> 18.283554 | D58: ='GDP, CFC, NDP, NNI'!J58 -> 18.88 | E58: ='Comparison Domestic Capital'!J58 -> 53.291948 | F58: =E58/C58 -> 2.9147478 | G58: =E58/D58 -> 2.8226667
A59: PE | B59: 1952 | C59: ='Comparison Domestic Capital'!N59 -> 19.41475 | D59: ='GDP, CFC, NDP, NNI'!J59 -> 20.04 | E59: ='Comparison Domestic Capital'!J59 -> 57.543865 | F59: =E59/C59 -> 2.9639251 | G59: =E59/D59 -> 2.8714504
A60: PE | B60: 1953 | C60: ='Comparison Domestic Capital'!N60 -> 20.965215 | D60: ='GDP, CFC, NDP, NNI'!J60 -> 21.65 | E60: ='Comparison Domestic Capital'!J60 -> 63.069983 | F60: =E60/C60 -> 3.0083156 | G60: =E60/D60 -> 2.9131632
... A86: PE | B86: 1979 | C86: ='Comparison Domestic Capital'!N86 -> 3289.1578 | D86: ='GDP, CFC, NDP, NNI'!J86 -> 3071.48 | E86: ='Comparison Domestic Capital'!J86 -> 14087.723 | F86: =E86/C86 -> 4.2830792 | G86: =E86/D86 -> 4.5866238
