Workbook
Name OLE_LINK1: Explanations!$A$9

Sheet SE
C5: Goverment Sector | D5: Components Goverment Sector | H5: Corporate Sector | I5: Components Corporate Sector | M5: Household Sector | N5: Components Household Sector | V5: Total Economy | AB5: Capital Shares
N6: Housing | Q6: Self-employment | V6: compen-sation of employees | W6: Mixed- income and OS | X6: Gross Operating Surplus | Y6: Mixed Income | AG6: Checks
A7: Notes | I7: residual of imputed wages paied by households | N7: Real Estate Gros Surplus | P7: Assume 1% | R7: imputed as share of total compensations of employees. 2/3 of gmxhn / (gmxhn+gsrco) | S7: Imputed labour Income / 0.7 | X7: Total profits (including selfemployment less30% of mixed income)
A8: iso | B8: year | C8: gvago | D8: ceugo | E8: gsrgo | F8: nsrgo | G8: cfcgo | H8: gvaco | I8: ceuco | J8: gsrco | K8: nsrco | L8: cfcco | M8: gvahn | N8: gsrhn | O8: nsrhn | P8: ccshn | Q8: gvmhn | R8: ceuhn | S8: gmxhn | T8: nmxhn | U8: ccmhn | V8: comhn | Y8: gmxhn | Z8: confc | AA8: ptxgo | AB8: cshare | AC8: cshare_gross | AD8: cshare_corp | AE8: chare_corp_gross | AF8: check_sector | AG8: check_total | AH8: check_chares
A9: SE | B9: 1800 | F9: 0 | Z9: =Data!CT8/Data!K8 -> 0.035728484 | AA9: =(Data!K8-Data!AN8)/Data!K8 -> 0.045805909
A10: SE | B10: 1801 | F10: 0 | Z10: =Data!CT9/Data!K9 -> 0.03496984 | AA10: =(Data!K9-Data!AN9)/Data!K9 -> 0.046004732
A11: SE | B11: 1802 | F11: 0 | Z11: =Data!CT10/Data!K10 -> 0.034302731 | AA11: =(Data!K10-Data!AN10)/Data!K10 -> 0.046199733
A12: SE | B12: 1803 | F12: 0 | Z12: =Data!CT11/Data!K11 -> 0.035350974 | AA12: =(Data!K11-Data!AN11)/Data!K11 -> 0.045993514
A13: SE | B13: 1804 | F13: 0 | Z13: =Data!CT12/Data!K12 -> 0.03833599 | AA13: =(Data!K12-Data!AN12)/Data!K12 -> 0.046011788
A14: SE | B14: 1805 | F14: 0 | Z14: =Data!CT13/Data!K13 -> 0.037317483 | AA14: =(Data!K13-Data!AN13)/Data!K13 -> 0.046253893
A15: SE | B15: 1806 | F15: 0 | Z15: =Data!CT14/Data!K14 -> 0.035959416 | AA15: =(Data!K14-Data!AN14)/Data!K14 -> 0.046085832
A16: SE | B16: 1807 | F16: 0 | Z16: =Data!CT15/Data!K15 -> 0.034426121 | AA16: =(Data!K15-Data!AN15)/Data!K15 -> 0.046297559
A17: SE | B17: 1808 | F17: 0 | Z17: =Data!CT16/Data!K16 -> 0.036619401 | AA17: =(Data!K16-Data!AN16)/Data!K16 -> 0.045799878
A18: SE | B18: 1809 | F18: 0 | Z18: =Data!CT17/Data!K17 -> 0.037981201 | AA18: =(Data!K17-Data!AN17)/Data!K17 -> 0.047242647
A19: SE | B19: 1810 | F19: 0 | Z19: =Data!CT18/Data!K18 -> 0.041272628 | AA19: =(Data!K18-Data!AN18)/Data!K18 -> 0.047619042
A20: SE | B20: 1811 | F20: 0 | Z20: =Data!CT19/Data!K19 -> 0.042842098 | AA20: =(Data!K19-Data!AN19)/Data!K19 -> 0.047371776
... A58: SE | B58: 1849 | F58: 0 | Z58: =Data!CT57/Data!K57 -> 0.040772627 | AA58: =(Data!K57-Data!AN57)/Data!K57 -> 0.047813893
A59: SE | B59: 1850 | C59: =E59+F59+D59 -> 0.058151636 | D59: =Data!HI58/Data!K58 -> 0.056546621 | E59: =Data!IC58/Data!K58 -> 0.0016050153 | F59: 0 | G59: =Data!IC58/Data!K58 -> 0.0016050153 | H59: =I59+J59 -> 0.48883867 | I59: =V59-R59-D59 -> 0.34959847 | J59: =X59-N59 -> 0.1392402 | M59: =N59+Q59 -> 0.40683818 | N59: =Data!ID58/Data!K58 -> 0.049936061 | P59: 0.01 | Q59: =R59+S59 -> 0.35690212 | R59: =(1/3)*(S59/(J59+S59))*(V59) -> 0.11000943 | S59: =(Data!HU58/0.7)/Data!K58 -> 0.24689269 | V59: =Data!HK58/Data!K58 -> 0.51615453 | W59: =X59+Y59 -> 0.43606895 | X59: =Data!IE58/Data!K58 - 0.3*Y59 -> 0.18917626 | Y59: =S59 -> 0.24689269 | Z59: =Data!CT58/Data!K58 -> 0.040845746 | AA59: =(Data!K58-Data!AN58)/Data!K58 -> 0.047776527 | AF59: =N59+Q59+H59+C59+AA59 -> 1.001605 | AG59: =V59+X59+AA59+Y59 -> 1
A60: SE | B60: 1851 | C60: =E60+F60+D60 -> 0.060043939 | D60: =Data!HI59/Data!K59 -> 0.058486391 | E60: =Data!IC59/Data!K59 -> 0.0015575481 | F60: 0 | G60: =Data!IC59/Data!K59 -> 0.0015575481 | H60: =I60+J60 -> 0.501028 | I60: =V60-R60-D60 -> 0.344537 | J60: =X60-N60 -> 0.156491 | M60: =N60+Q60 -> 0.39280507 | N60: =Data!ID59/Data!K59 -> 0.049384797 | P60: 0.01 | Q60: =R60+S60 -> 0.34342028 | R60: =(1/3)*(S60/(J60+S60))*(V60) -> 0.10214077 | S60: =(Data!HU59/Data!K59)/0.7 -> 0.2412795 | V60: =Data!HK59/Data!K59 -> 0.50516417 | W60: =X60+Y60 -> 0.4471553 | X60: =Data!IE59/Data!K59 - 0.3*Y60 -> 0.20587579 | Y60: =S60 -> 0.2412795 | Z60: =Data!CT59/Data!K59 -> 0.040437791 | AA60: =(Data!K59-Data!AN59)/Data!K59 -> 0.047680537 | AF60: =N60+Q60+H60+C60+AA60 -> 1.0015575 | AG60: =V60+X60+AA60+Y60 -> 1
A61: SE | B61: 1852 | C61: =E61+F61+D61 -> 0.057908924 | D61: =Data!HI60/Data!K60 -> 0.056349185 | E61: =Data!IC60/Data!K60 -> 0.0015597387 | F61: 0 | G61: =Data!IC60/Data!K60 -> 0.0015597387 | H61: =I61+J61 -> 0.5031434 | I61: =V61-R61-D61 -> 0.34461379 | J61: =X61-N61 -> 0.15852961 | M61: =N61+Q61 -> 0.39271858 | N61: =Data!ID60/Data!K60 -> 0.050110104 | P61: 0.01 | Q61: =R61+S61 -> 0.34260847 | R61: =(1/3)*(S61/(J61+S61))*(V61) -> 0.10103168 | S61: =(Data!HU60/Data!K60)/0.7 -> 0.2415768 | V61: =Data!HK60/Data!K60 -> 0.50199465 | W61: =X61+Y61 -> 0.45021651 | X61: =Data!IE60/Data!K60 - 0.3*Y61 -> 0.20863971 | Y61: =S61 -> 0.2415768 | Z61: =Data!CT60/Data!K60 -> 0.041063533 | AA61: =(Data!K60-Data!AN60)/Data!K60 -> 0.047788839 | AF61: =N61+Q61+H61+C61+AA61 -> 1.0015597 | AG61: =V61+X61+AA61+Y61 -> 1
A62: SE | B62: 1853 | C62: =E62+F62+D62 -> 0.06012682 | D62: =Data!HI61/Data!K61 -> 0.058526779 | E62: =Data!IC61/Data!K61 -> 0.0016000409 | F62: 0 | G62: =Data!IC61/Data!K61 -> 0.0016000409 | H62: =I62+J62 -> 0.50633905 | I62: =V62-R62-D62 -> 0.34220155 | J62: =X62-N62 -> 0.1641375 | M62: =N62+Q62 -> 0.38745784 | N62: =Data!ID61/Data!K61 -> 0.051070033 | P62: 0.01 | Q62: =R62+S62 -> 0.33638781 | R62: =(1/3)*(S62/(J62+S62))*(V62) -> 0.09846745 | S62: =(Data!HU61/Data!K61)/0.7 -> 0.23792036 | V62: =Data!HK61/Data!K61 -> 0.49919578 | W62: =X62+Y62 -> 0.45312789 | X62: =Data!IE61/Data!K61 - 0.3*Y62 -> 0.21520754 | Y62: =S62 -> 0.23792036 | Z62: =Data!CT61/Data!K61 -> 0.042419454 | AA62: =(Data!K61-Data!AN61)/Data!K61 -> 0.047676333 | AF62: =N62+Q62+H62+C62+AA62 -> 1.0016 | AG62: =V62+X62+AA62+Y62 -> 1
A63: SE | B63: 1854 | C63: =E63+F63+D63 -> 0.051563089 | D63: =Data!HI62/Data!K62 -> 0.049986988 | E63: =Data!IC62/Data!K62 -> 0.0015761005 | F63: 0 | G63: =Data!IC62/Data!K62 -> 0.0015761005 | H63: =I63+J63 -> 0.54651564 | I63: =V63-R63-D63 -> 0.33729198 | J63: =X63-N63 -> 0.20922366 | M63: =N63+Q63 -> 0.35538663 | N63: =Data!ID62/Data!K62 -> 0.051101529 | P63: 0.01 | Q63: =R63+S63 -> 0.3042851 | R63: =(1/3)*(S63/(J63+S63))*(V63) -> 0.080584794 | S63: =(Data!HU62/Data!K62)/0.7 -> 0.22370031 | V63: =Data!HK62/Data!K62 -> 0.46786376 | W63: =X63+Y63 -> 0.4840255 | X63: =Data!IE62/Data!K62 - 0.3*Y63 -> 0.26032519 | Y63: =S63 -> 0.22370031 | Z63: =Data!CT62/Data!K62 -> 0.041926581 | AA63: =(Data!K62-Data!AN62)/Data!K62 -> 0.04811074 | AF63: =N63+Q63+H63+C63+AA63 -> 1.0015761 | AG63: =V63+X63+AA63+Y63 -> 1
A64: SE | B64: 1855 | C64: =E64+F64+D64 -> 0.049113772 | D64: =Data!HI63/Data!K63 -> 0.047405755 | E64: =Data!IC63/Data!K63 -> 0.0017080172 | F64: 0 | G64: =Data!IC63/Data!K63 -> 0.0017080172 | H64: =I64+J64 -> 0.50251121 | I64: =V64-R64-D64 -> 0.35383005 | J64: =X64-N64 -> 0.14868116 | M64: =N64+Q64 -> 0.40184805 | N64: =Data!ID63/Data!K63 -> 0.054315388 | P64: 0.01 | Q64: =R64+S64 -> 0.34753266 | R64: =(1/3)*(S64/(J64+S64))*(V64) -> 0.10459611 | S64: =(Data!HU63/Data!K63)/0.7 -> 0.24293656 | V64: =Data!HK63/Data!K63 -> 0.50583191 | W64: =X64+Y64 -> 0.4459331 | X64: =Data!IE63/Data!K63 - 0.3*Y64 -> 0.20299654 | Y64: =S64 -> 0.24293656 | Z64: =Data!CT63/Data!K63 -> 0.046550427 | AA64: =(Data!K63-Data!AN63)/Data!K63 -> 0.048234985 | AF64: =N64+Q64+H64+C64+AA64 -> 1.001708 | AG64: =V64+X64+AA64+Y64 -> 1
A65: SE | B65: 1856 | C65: =E65+F65+D65 -> 0.04412007 | D65: =Data!HI64/Data!K64 -> 0.042471109 | E65: =Data!IC64/Data!K64 -> 0.001648962 | F65: 0 | G65: =Data!IC64/Data!K64 -> 0.001648962 | H65: =I65+J65 -> 0.52684628 | I65: =V65-R65-D65 -> 0.34859726 | J65: =X65-N65 -> 0.17824902 | M65: =N65+Q65 -> 0.38219432 | N65: =Data!ID64/Data!K64 -> 0.055012986 | P65: 0.01 | Q65: =R65+S65 -> 0.32718133 | R65: =(1/3)*(S65/(J65+S65))*(V65) -> 0.091589351 | S65: =(Data!HU64/Data!K64)/0.7 -> 0.23559198 | V65: =Data!HK64/Data!K64 -> 0.48265772 | W65: =X65+Y65 -> 0.46885399 | X65: =Data!IE64/Data!K64 - 0.3*Y65 -> 0.23326201 | Y65: =S65 -> 0.23559198 | Z65: =Data!CT64/Data!K64 -> 0.046832265 | AA65: =(Data!K64-Data!AN64)/Data!K64 -> 0.048488297 | AF65: =N65+Q65+H65+C65+AA65 -> 1.001649 | AG65: =V65+X65+AA65+Y65 -> 1
A66: SE | B66: 1857 | C66: =E66+F66+D66 -> 0.043212722 | D66: =Data!HI65/Data!K65 -> 0.04146051 | E66: =Data!IC65/Data!K65 -> 0.0017522117 | F66: 0 | G66: =Data!IC65/Data!K65 -> 0.0017522117 | H66: =I66+J66 -> 0.50278204 | I66: =V66-R66-D66 -> 0.34885685 | J66: =X66-N66 -> 0.15392519 | M66: =N66+Q66 -> 0.40722312 | N66: =Data!ID65/Data!K65 -> 0.062802126 | P66: 0.01 | Q66: =R66+S66 -> 0.344421 | R66: =(1/3)*(S66/(J66+S66))*(V66) -> 0.10029816 | S66: =(Data!HU65/Data!K65)/0.7 -> 0.24412284 | V66: =Data!HK65/Data!K65 -> 0.49061552 | W66: =X66+Y66 -> 0.46085016 | X66: =Data!IE65/Data!K65 - 0.3*Y66 -> 0.21672732 | Y66: =S66 -> 0.24412284 | Z66: =Data!CT65/Data!K65 -> 0.050926999 | AA66: =(Data!K65-Data!AN65)/Data!K65 -> 0.048534324 | AF66: =N66+Q66+H66+C66+AA66 -> 1.0017522 | AG66: =V66+X66+AA66+Y66 -> 1
A67: SE | B67: 1858 | C67: =E67+F67+D67 -> 0.05024047 | D67: =Data!HI66/Data!K66 -> 0.048612705 | E67: =Data!IC66/Data!K66 -> 0.001627765 | F67: 0 | G67: =Data!IC66/Data!K66 -> 0.001627765 | H67: =I67+J67 -> 0.51095248 | I67: =V67-R67-D67 -> 0.34270622 | J67: =X67-N67 -> 0.16824626 | M67: =N67+Q67 -> 0.39225698 | N67: =Data!ID66/Data!K66 -> 0.059723717 | P67: 0.01 | Q67: =R67+S67 -> 0.33253326 | R67: =(1/3)*(S67/(J67+S67))*(V67) -> 0.09488975 | S67: =(Data!HU66/Data!K66)/0.7 -> 0.23764351 | V67: =Data!HK66/Data!K66 -> 0.48620867 | W67: =X67+Y67 -> 0.46561349 | X67: =Data!IE66/Data!K66 - 0.3*Y67 -> 0.22796998 | Y67: =S67 -> 0.23764351 | Z67: =Data!CT66/Data!K66 -> 0.049153319 | AA67: =(Data!K66-Data!AN66)/Data!K66 -> 0.048177832 | AF67: =N67+Q67+H67+C67+AA67 -> 1.0016278 | AG67: =V67+X67+AA67+Y67 -> 1
A68: SE | B68: 1859 | C68: =E68+F68+D68 -> 0.051409895 | D68: =Data!HI67/Data!K67 -> 0.049765833 | E68: =Data!IC67/Data!K67 -> 0.0016440621 | F68: 0 | G68: =Data!IC67/Data!K67 -> 0.0016440621 | H68: =I68+J68 -> 0.49812247 | I68: =V68-R68-D68 -> 0.34343646 | J68: =X68-N68 -> 0.15468601 | M68: =N68+Q68 -> 0.40399319 | N68: =Data!ID67/Data!K67 -> 0.062741827 | P68: 0.01 | Q68: =R68+S68 -> 0.34125136 | R68: =(1/3)*(S68/(J68+S68))*(V68) -> 0.10017949 | S68: =(Data!HU67/Data!K67)/0.7 -> 0.24107187 | V68: =Data!HK67/Data!K67 -> 0.49338178 | W68: =X68+Y68 -> 0.4584997 | X68: =Data!IE67/Data!K67 - 0.3*Y68 -> 0.21742783 | Y68: =S68 -> 0.24107187 | Z68: =Data!CT67/Data!K67 -> 0.050368957 | AA68: =(Data!K67-Data!AN67)/Data!K67 -> 0.048118511 | AF68: =N68+Q68+H68+C68+AA68 -> 1.0016441 | AG68: =V68+X68+AA68+Y68 -> 1
A69: SE | B69: 1860 | C69: =E69+F69+D69 -> 0.05106436 | D69: =Data!HI68/Data!K68 -> 0.049440186 | E69: =Data!IC68/Data!K68 -> 0.0016241738 | F69: 0 | G69: =Data!IC68/Data!K68 -> 0.0016241738 | H69: =I69+J69 -> 0.48775363 | I69: =V69-R69-D69 -> 0.34541282 | J69: =X69-N69 -> 0.14234081 | M69: =N69+Q69 -> 0.41467014 | N69: =Data!ID68/Data!K68 -> 0.063463692 | P69: 0.01 | Q69: =R69+S69 -> 0.35120645 | R69: =(1/3)*(S69/(J69+S69))*(V69) -> 0.10561161 | S69: =(Data!HU68/Data!K68)/0.7 -> 0.24559484 | V69: =Data!HK68/Data!K68 -> 0.50046462 | W69: =X69+Y69 -> 0.45139934 | X69: =Data!IE68/Data!K68 - 0.3*Y69 -> 0.2058045 | Y69: =S69 -> 0.24559484 | Z69: =Data!CT68/Data!K68 -> 0.050335017 | AA69: =(Data!K68-Data!AN68)/Data!K68 -> 0.048136039 | AF69: =N69+Q69+H69+C69+AA69 -> 1.0016242 | AG69: =V69+X69+AA69+Y69 -> 1
A70: SE | B70: 1861 | C70: =E70+F70+D70 -> 0.050518956 | D70: =Data!HI69/Data!K69 -> 0.048900151 | E70: =Data!IC69/Data!K69 -> 0.0016188052 | F70: 0 | G70: =Data!IC69/Data!K69 -> 0.0016188052 | H70: =I70+J70 -> 0.49091234 | I70: =V70-R70-D70 -> 0.34675698 | J70: =X70-N70 -> 0.14415536 | M70: =N70+Q70 -> 0.41202381 | N70: =Data!ID69/Data!K69 -> 0.061964875 | P70: 0.01 | Q70: =R70+S70 -> 0.35005893 | R70: =(1/3)*(S70/(J70+S70))*(V70) -> 0.10507942 | S70: =(Data!HU69/Data!K69)/0.7 -> 0.24497951 | V70: =Data!HK69/Data!K69 -> 0.50073655 | W70: =X70+Y70 -> 0.45109975 | X70: =Data!IE69/Data!K69 - 0.3*Y70 -> 0.20612023 | Y70: =S70 -> 0.24497951 | Z70: =Data!CT69/Data!K69 -> 0.050253374 | AA70: =(Data!K69-Data!AN69)/Data!K69 -> 0.048163705 | AF70: =N70+Q70+H70+C70+AA70 -> 1.0016188 | AG70: =V70+X70+AA70+Y70 -> 1
A71: SE | B71: 1862 | C71: =E71+F71+D71 -> 0.051194519 | D71: =Data!HI70/Data!K70 -> 0.049478301 | E71: =Data!IC70/Data!K70 -> 0.0017162175 | F71: 0 | G71: =Data!IC70/Data!K70 -> 0.0017162175 | H71: =I71+J71 -> 0.48477802 | I71: =V71-R71-D71 -> 0.34164877 | J71: =X71-N71 -> 0.14312925 | M71: =N71+Q71 -> 0.4174708 | N71: =Data!ID70/Data!K70 -> 0.068645851 | P71: 0.01 | Q71: =R71+S71 -> 0.34882495 | R71: =(1/3)*(S71/(J71+S71))*(V71) -> 0.10416132 | S71: =(Data!HU70/Data!K70)/0.7 -> 0.24466363 | V71: =Data!HK70/Data!K70 -> 0.49528839 | W71: =X71+Y71 -> 0.45643873 | X71: =Data!IE70/Data!K70 - 0.3*Y71 -> 0.2117751 | Y71: =S71 -> 0.24466363 | Z71: =Data!CT70/Data!K70 -> 0.054241665 | AA71: =(Data!K70-Data!AN70)/Data!K70 -> 0.048272876 | AF71: =N71+Q71+H71+C71+AA71 -> 1.0017162 | AG71: =V71+X71+AA71+Y71 -> 1
... A209: SE | B209: 2000 | C209: =E209+F209+D209 -> 0.18370779 | D209: =Data!HI208/Data!K208 -> 0.16905019 | E209: =Data!IC208/Data!K208 -> 0.014657594 | F209: 0 | G209: =Data!IC208/Data!K208 -> 0.014657594 | H209: =I209+J209 -> 0.50387532 | I209: =V209-R209-D209 -> 0.36312009 | J209: =X209-N209 -> 0.14075523 | M209: =N209+Q209 -> 0.22802853 | N209: =Data!ID208/Data!K208 -> 0.09734915 | P209: 0.01 | Q209: =R209+S209 -> 0.13067938 | R209: =(1/3)*(S209/(J209+S209))*(V209) -> 0.063921686 | S209: =(Data!HU208/Data!K208)/0.7 -> 0.066757699 | V209: =Data!HK208/Data!K208 -> 0.59609197 | W209: =X209+Y209 -> 0.30486208 | X209: =Data!IE208/Data!K208 - 0.3*Y209 -> 0.23810438 | Y209: =S209 -> 0.066757699 | Z209: =Data!CT208/Data!K208 -> 0.12519403 | AA209: =(Data!K208-Data!AN208)/Data!K208 -> 0.099045951 | AF209: =N209+Q209+H209+C209+AA209 -> 1.0146576 | AG209: =V209+X209+AA209+Y209 -> 1
A210: SE | B210: 2001
A211: SE | B211: 2002
A212: SE | B212: 2003
A213: SE | B213: 2004
A214: SE | B214: 2005
A215: SE | B215: 2006
A216: SE | B216: 2007
A217: SE | B217: 2008
A218: SE | B218: 2009
A219: SE | B219: 2010
A220: SE | B220: 2011
A221: SE | B221: 2012
... A234: SE | B234: 2025

Sheet Data
A1: File name (filnamn): Historical national accounts for Sweden 1800-2000 (Historiska nationalräkenskaper för Sverige 1800-2000) Version 1.0 Last updated (senast uppdaterad): 050404
A2: Author (författare): Rodney Edvinsson | CT2: confc | HV2: Mixed income = imputed self-employed labour income / 0.7
A4: A. Annual volume growth (in percent) of aggregate production according to different estimates. | J4: B. Current values (in million SEK) of some aggregate variables. | U4: C. Estimates of GDP per capita and population | AE4: D. Nominal gross value added (in basic prices, million SEK) of different types of activities and of GDP. | AP4: E. Annual growth rates (in percent) of the volume gross value added (in basic prices and corrected for changes in the value added share in gross output) of different types of activities. | BA4: F. Nominal values (in purchasers’ prices, million SEK) of different expenditures and of GDP by expenditure. | BL4: G. Annual volume growth rates (in percent) of various expenditures and of GDP by expenditure (based on purchasers’ prices). | BT4: H. Annual changes (in percent) in the prices indices (purchasers’ prices) of various expenditures and of GDP by expenditure. | CB4: I. Nominal value of gross investment (in purchasers’ prices, million SEK) of various types of activities and total gross investment. | CL4: J. Consumption of fixed assets (in current, purchasers’ prices, million SEK) of various types of activities and total consumption of fixed assets | CV4: K. Net (capacity) stock of various types of produced assets (in current, purchasers’ prices, million SEK), aggregate economy, and the total net stock of produced assets of the aggregate economy, of the private sector and of manufacturing and handicrafts (1st of January each year) | DF4: L. Annual volume growth rates (in percent) of the net (capacity) stock of various types of produced assets (based on purchasers’ prices), aggregate economy, and of the total net stock of produced assets of the aggregate economy, of the private sector and of manufacturing and handicrafts | DQ4: M. Gross (capacity) stock of various types of produced assets (current, purchasers’ prices, million SEK), aggregate economy, and the total gross stock of produced assets of the aggregate economy, of the private sector and of manufacturing and handicrafts (1st of January each year) | EA4: N. Annual volume growth rates (in percent) of the gross (capacity) stock of various types of produced assets (purchasers’ prices, million SEK), aggregate economy, and of the total gross stock of produced assets of the aggregate economy, of the private sector and of manufacturing and handicrafts | EL4: O. Number of employed (employees and self-employed) of various types of activities | EX4: P. Number of employees of various types of activities | FJ4: Q. Number of self-employed of various types of activities, and the number of “housewives” | FU4: R. Total hours worked (in tens of thousands) of employed (employees and self-employed) of different types of activities | GG4: S. Total hours worked (in tens of thousands) of employees of different types of activities | GS4: T. Total hours worked (in tens of thousands) of self-employed of different types of activities | HC4: U. Wages and salaries (including social benefits) of employees (current factor values, million SEK) of various types of activities. | HN4: V. Imputed labour income of self-employed (including social benefits, current factor values, million SEK) of various types of activities. | HW4: W. Gross surplus (current, basic values, million SEK) of various types of activities. | IH4: X. Various ratios (in percent, based on current purchasers’ and purchasers’ proxy prices) and annual change in real wage rate (in percent) for manufacturing and handicrafts.
A5: A. Årliga volymtillväxt (i procent) av den aggregerade produktion enligt olika mått | J5: B. Olika aggregerade variabler till löpande pris (i miljoner kronor) | U5: C. Skattningar av BNP per capita och befolkning | AE5: D. Bruttoförädlingsvärdet (till löpande baspris, miljoner kronor) för olika branscher och för BNP | AP5: E. Årlig tillväxt (i procent) av volymvärdet för bruttoförädlingsvärdet (till baspris och korrigerad för förändringar i förädlingsvärdets andel av bruttoprodukten) för olika branscher | BA5: F. Löpande värde (till mottagarpriser, miljoner kronor) av olika användningar och BNP från användningssidan | BL5: G. Årliga volymtillväxt (i procent) för olika användningar och BNP från användningssidan (baserat på mottagarpriser) | BT5: H. Årliga förändring (i procent) i prisindex (mottagarpriser) för olika användingar och BNP från användningssidan | CB5: I. Löpande värde av bruttoinvesteringar (till mottagarpris, miljoner kronor) inom olika branscher och totala bruttoinvesteringar | CL5: J. Avskrivningar av fasta tillgångar (i löpander mottagarpriser, miljoner kronor) för olika branscher och totala avskrivningar av fasta tillgångar | CV5: K. Netto(kapacitets)stocken av olika typer av producerade tillgångar (till löpande mottagarpriser, miljoner kronor), hela ekonomin, och den totala nettostocken av producerade tillgångar för hela ekonomin, för privata sektorn och för industri och hantverk (första januari varje år) | DF5: L. Årliga volymtillväxt (i procent) för netto(kapacitets)stocken av olika typer av producerade tillgångar (baserat på mottagarpriser), hela ekonomin, och för den totala nettostocken av producerade tillgångar för hela ekonomin, för privata sektorn och för industri och hantverk (första januari varje år) | DQ5: M. Brutto(kapacitets)stocken av olika typer av producerade tillgångar (till löpande mottagarpriser, miljoner kronor), hela ekonomin, och den totala bruttostocken av producerade tillgångar för hela ekonomin, för privata sektorn och för industri och hantverk (första januari varje år) | EA5: N. Årlig volymtillväxt för brutto(kapacitets)stocken av olika typer av producerade tillgångar (till löpande mottagarpriser, miljoner kronor), hela ekonomin, och för den totala bruttostocken av producerade tillgångar för hela ekonomin, för privata sektorn och för industri och hantverk (första januari varje år) | EL5: O. Antal sysselsatta (anställda och företagare) inom olika branscher | EX5: P. Antal anställda inom olika branscher | FJ5: Q. Antal företagare inom olika branscher, och antalet "hemmafruar" | FU5: R. Totala antalet arbetade timmar (i 10000-tals) för sysselsatta (anställda och företagare) inom olika branscher | GG5: S. Totala antalet arbetade timmar (i 10000-tals) för anställda inom olika branscher | GS5: T. Totala antalet arbetade timmar (i 10000-tals) för företagare inom olika branscher | HC5: U. Löner (inklusive sociala avgifter) för anställda (till löpande faktorvärden, miljoner kronor) inom olika branscher | HN5: V. Tillskriven arbetsinkomst för företagare (inklusive sociala avgifter, till löpande faktorvärden, miljoner kronor) inom olika branscher | HW5: W. Bruttoöverskott (löpande basvärden, miljoner kronor) inom olika branscher | IH5: X. Olika kvoter (i procent, baserat på löpande mottagarpriser och tillskrivna mottagarpriser) och årlig förändring i reallön (i procent) inom industri och hantverk.
A6: Annual change | B6: Gross Domestic Product (GDP) by activity, Fisher index, corrected for changes in the share of value added in gross output, based on basic prices | C6: Net Domestic Product (NDP) by activity, corrected for changes in the share of value added in gross output, based on basic prices | D6: Gross Domestic Product (GDP) by activity, Laspeyre volume index, corrected for changes in the share of value added in gross output, based on basic prices | E6: Gross Domestic Product (GDP) by activity, Paasche volume index, corrected for changes in the share of value added in gross output, based on basic prices | F6: Gross Domestic Product (GDP) by activity, Fisher, uncorrected for changes in the share of value added in gross output, based on basic prices | G6: Gross Domestic Product (GDP) by expenditure, Fisher index, based on purchasers' prices | H6: Net National Product (NDP) by expenditure, Fisher index, based on purchasers' prices | J6: Year | K6: GDP by expenditure, purchasers' prices | L6: GDP by activity, basic prices | M6: NDP by expenditure, purchasers' prices | N6: NDP by activity, basic prices | O6: Consumption of fixed assets, purchasers' prices | P6: Purchasers' value less basic value of GDP | Q6: Intermediate consumption, purchasers' prices | R6: Gross Domestic Output, purchasers' prices | S6: Gross Domestic Output, basic prices | U6: Year | V6: GDP per capita by expenditure in purchasers' prices (SEK), nominal value | W6: GDP per capita by expenditure in purchasers' prices (SEK), volume value (reference year 2000) | X6: Volume growth from preceding year (%) of GDP per capita by expenditure in purchasers' prices (SEK) | Y6: GDP per capita by activity in basic prices (SEK), löpande värden | Z6: GDP per capita by activity in basic prices (SEK), volume value (reference year 2000) | AA6: Volume growth from preceding year (%) of GDP per capita by activity in basic prices (SEK), volume value (reference year 2000) | AB6: Mean population | AC6: Population growth | AE6: Year | AF6: Agriculture and ancillaries | AG6: Manufacturing and handicrafts | AH6: Building and construction | AI6: Transport and communication | AJ6: Circulation | AK6: Private reproductive services* | AL6: Government services | AM6: Real estate | AN6: GDP by activity | AP6: Annual change | AQ6: Agriculture and ancillaries | AR6: Manufacturing and handicrafts | AS6: Building and construction | AT6: Transport and communication | AU6: Circulation* | AV6: Private reproductive services* | AW6: Government services | AX6: Real estate | AY6: GDP | BA6: Year | BB6: Private final consumption | BC6: Government final consumption | BD6: Investment in buildings and structures | BE6: Investment in machinery and equipment | BF6: Changes in fixed livestock | BG6: Changes in inventory stock | BH6: Export | BI6: Import | BJ6: GDP | BL6: Annual change | BM6: Private final consumption | BN6: Government final consumption | BO6: Investment | BP6: Export | BQ6: Import | BR6: GDP | BT6: Annual change | BU6: Private final consumption | BV6: Government final consumption | BW6: Investment | BX6: Export | BY6: Import | BZ6: GDP | CB6: Year | CC6: Agriculture and ancillaries | CD6: Manufacturing and handicrafts | CE6: Building and construction | CF6: Transport and communication | CG6: Other private services, here include circulation (code CC), private reproductive services (code PR) and letting of other premises | CH6: Government services | CI6: Services of dwellings | CJ6: Total gross investment | CL6: Year | CM6: Agriculture and ancillaries | CN6: Manufacturing and handicrafts | CO6: Building and construction | CP6: Transport and communication | CQ6: Other private services, here include circulation (code CC), private reproductive services (code PR) and letting of other premises | CR6: Government services | CS6: Services of dwellings | CT6: Total consumption of fixed assets | CV6: År | CW6: Residential buildings | CX6: Non-residential structures et al. | CY6: Machinery and equipment | CZ6: Fixed livestock | DA6: Inventory stock | DB6: Total, aggregate economy | DC6: Total, private sector | DD6: Total, manufacturing and handicrafts | DF6: During year | DG6: Buildings and structures | DH6: Residential buildings | DI6: Non-residential structures et al. | DJ6: Machinery and equipment | DK6: Fixed livestock | DL6: Inventory stock | DM6: Total, aggregate economy | DN6: Total, private sector | DO6: Total, manufacturing and handicrafts | DQ6: Year | DR6: Residential buildings | DS6: Non-residential structures et al. | DT6: Machinery and equipment | DU6: Fixed livestock | DV6: Inventory stock | DW6: Total, aggregate economy | DX6: Total, private sector | DY6: Total, manufacturing and handicrafts | EA6: During year | EB6: Buildings and structures | EC6: Residential buildings | ED6: Non-residential structures et al. | EE6: Machinery and equipment | EF6: Fixed livestock | EG6: Inventory stock | EH6: Total, aggregate economy | EI6: Total, private sector | EJ6: Total, manufacturing and handicrafts | EL6: Year | EM6: Agriculture and ancillaries | EN6: Manufacturing and handicrafts | EO6: Building and construction | EP6: Transport and communication | EQ6: Circulation | ER6: Private reproductive services | ES6: Government services | ET6: Real estate | EU6: Total aggregate economy | EV6: Total private sector | EX6: Year | EY6: Agriculture and ancillaries | EZ6: Manufacturing and handicrafts | FA6: Building and construction | FB6: Transport and communication | FC6: Circulation | FD6: Private reproductive services | FE6: Government services | FF6: Real estate | FG6: Total aggregate economy | FH6: Total private sector | FJ6: Year | FK6: Agriculture and ancillaries | FL6: Manufacturing and handicrafts | FM6: Building and construction | FN6: Transport and communication | FO6: Circulation | FP6: Private reproductive services | FQ6: Real estate | FR6: Total number of self-employed | FS6: Number of “housewives” | FU6: Year | FV6: Agriculture and ancillaries | FW6: Manufacturing and handicrafts | FX6: Building and construction | FY6: Transport and communication | FZ6: Circulation | GA6: Private reproductive services | GB6: Government services | GC6: Real estate | GD6: Total aggregate economy | GE6: Total private sector | GG6: Year | GH6: Agriculture and ancillaries | GI6: Manufacturing and handicrafts | GJ6: Building and construction | GK6: Transport and communication | GL6: Circulation | GM6: Private reproductive services | GN6: Government services | GO6: Real estate | GP6: Total aggregate economy | GQ6: Private sector | GS6: Year | GT6: Agriculture and ancillaries | GU6: Manufacturing and handicrafts | GV6: Building and construction | GW6: Transport and communication | GX6: Circulation | GY6: Private reproductive services | GZ6: Real estate | HA6: Total aggregate economy | HC6: År | HD6: Agriculture and ancillaries | HE6: Manufacturing and handicrafts | HF6: Building and construction | HG6: Transport and communication | HH6: Other private services, here include circulation (code CC) and private reproductive services (code PR). | HI6: Government services | HJ6: Real estate | HK6: Total aggregate economy | HL6: Total private sector | HN6: Year | HO6: Agriculture and ancillaries | HP6: Manufacturing and handicrafts | HQ6: Building and construction | HR6: Transport and communication | HS6: Other private services, here include circulation (code CC) and private reproductive services (code PR). | HT6: Real estate | HU6: Total aggregate economy | HW6: Year | HX6: Agriculture and ancillaries | HY6: Manufacturing and handicrafts | HZ6: Building and construction | IA6: Transport and communication | IB6: Other private services, here include circulation (code CC) and private reproductive services | IC6: Government services | ID6: Real estate | IE6: Total aggregate economy | IF6: Total private sector | IH6: Year | II6: Net stock of produced assets/Gross value added | IJ6: Gross surplus/Labour income* | IK6: Gross surplus/Net stock of produced assets | IL6: Net stock of produced assets/Net value added | IM6: Net surplus/Labour income* | IN6: Net surplus/Net stock of produced assets | IO6: Change in annual real wage rate from previous year
A7: Årlig förändring | B7: Bruttonationalprodukt (BNP) från produktionssidan, Fischerindex, korrigerad för förändringar i förädlingsvärdets andel av bruttoprodukten, baserat på baspriser | C7: Nettonationalprodukt (NNP) från produktionssidan, Fisherindex, korrigerad för förändringar i förädlingsvärdets andel av bruttoprodukten, baserat på baspriser | D7: Bruttonationalprodukt (BNP) från produktionssidan, Laspeyres volymindex, korrigerad för förändringar i förädlingsvärdets andel av bruttoprodukten, baserat på baspriser | E7: Bruttonationalprodukt (BNP) från produktionssidan, Paasches volymindex, korrigerad för förändringar i förädlingsvärdets andel av bruttoprodukten, baserat på baspriser | F7: Bruttonationalprodukt (BNP) från produktionssidan, Fisherindex, okorrigerad för förändringar i förädlingsvärdets andel av bruttoprodukten, baserat på baspriser | G7: Bruttonationalprodukt (BNP) från användningssidan, Fisherindex, baserat på mottagarpriser | H7: Nettonationalprodukten (NNP) från användningssidan, Fisherindex, baserat på mottagarpriser | J7: År | K7: BNP från användningssidan, mottagarpris | L7: BNP från produktionssidan, mottagarpris | M7: NNP från användningssidan, mottagarpris | N7: NNP från produktionssidan, baspris | O7: Avskrivningar av fasta tillgångar, mottagarpris | P7: BNP till mottagarpris minus BNP till baspris | Q7: Insatsförbrukning, mottagarpris | R7: Bruttonationalproduktionsvärde, mottagarpris | S7: Bruttonationalproduktionsvärde, baspris | U7: År | V7: BNP per capita från användningssidan till mottagarpris (kronor), löpande värden | W7: BNP per capita från användningssidan till mottagarpris (kronor), volymvärde (referensår 2000) | X7: Volymtillväxt från föregående år (%) för BNP per capita från användningssidan till mottagarpris (kronor) | Y7: BNP per capita från produktionssidan till baspris (kronor), löpande värden | Z7: BNP per capita från produktionssidan till baspris (kronor), volymvärde (referensår 2000) | AA7: Volymtillväxt från föregående år (%) för BNP per capita från produktionssidan till baspris (kronor) | AB7: Medelfolkmängd | AC7: Befolkningstillväxt | AE7: År | AF7: Jordbruk med binäringar | AG7: Industri och hantverk | AH7: Byggnadsindustri | AI7: Transporter och kommunikationer | AJ7: Cirkulation | AK7: Privata reproduktiva tjänster | AL7: Offentliga tjänster | AM7: Fastighetsförvaltning | AN7: BNP från produktionssidan | AP7: Årlig förändring | AQ7: Jordbruk med binäringar | AR7: Industri och hantverk | AS7: Byggnadsindustri | AT7: Transporter och kommunikationer | AU7: Cirkulation | AV7: Privata reproduktiva tjänster | AW7: Offentliga tjänster | AX7: Fastighetsförvaltning | AY7: BNP | BA7: År | BB7: Privat konsumtion | BC7: Offentlig konsumtion | BD7: Investingar i byggnader och anläggningar | BE7: Investeringar i maskiner, transportmedel och inventarier | BF7: Förändring i fast djurstock | BG7: Lagerförändring | BH7: Export | BI7: Import | BJ7: BNP | BL7: Årlig förändring | BM7: Privat konsumtion | BN7: Offentlig konsumtion | BO7: Investeringar | BP7: Export | BQ7: Import | BR7: BNP | BT7: Årlig förändring | BU7: Privat konsumtion | BV7: Offentlig konsumtion | BW7: Investeringar | BX7: Export | BY7: Import | BZ7: BNP | CB7: År | CC7: Jordbruk med binäringar | CD7: Industri och hantverk | CE7: Byggnadsindustri | CF7: Transporter och kommunikationer | CG7: Övriga privata tjänster, här inkluderat cirkulation, privata reproduktiva tjänster och annan förvaltningsförvaltning | CH7: Offentliga tjänster | CI7: Bostadsförvaltning | CJ7: Totala bruttoinvesteringar | CL7: År | CM7: Jordbruk med binäringar | CN7: Industri och hantverk | CO7: Byggnadsindustri | CP7: Transporter och kommunikationer | CQ7: Övriga privata tjänster, här inkluderat cirkulation, privata reproduktiva tjänster och annan förvaltningsförvaltning | CR7: Offentliga tjänster | CS7: Bostadsförvaltning | CT7: Avskrivningar av fasta tillgångar, totalt | CV7: Year | CW7: Bostäder | CX7: Byggnader och anläggningar utom bostäder | CY7: Maskiner, transportmedel och inventarier | CZ7: Fast djurstock | DA7: Lagerstock | DB7: Totalt, hela ekonomin | DC7: Totalt, privat sektor | DD7: Totalt, industri och hantverk | DF7: Under loppet av år | DG7: Byggnader och anläggningar | DH7: Bostäder | DI7: Byggnader och anläggningar utom bostäder | DJ7: Maskiner, transportmedel och inventarier | DK7: Fast djurstock | DL7: Lagerstock | DM7: Totalt, hela ekonomin | DN7: Totalt, privat sektor | DO7: Totalt, industri och hantverk | DQ7: År | DR7: Bostäder | DS7: Byggnader och anläggningar utom bostäder | DT7: Maskiner, transportmedel och inventarier | DU7: Fast djurstock | DV7: Lagerstock | DW7: Totalt, hela ekonomin | DX7: Totalt, privat sektor | DY7: Totalt, industri och hantverk | EA7: Under loppet av år | EB7: Byggnader och anläggningar | EC7: Bostäder | ED7: Byggnader och anläggningar utom bostäder | EE7: Maskiner, transportmedel och inventarier | EF7: Fast djurstock | EG7: Lagerstock | EH7: Totalt, hela ekonomin | EI7: Totalt, privat sektor | EJ7: Totalt, industri och hantverk | EL7: År | EM7: Jordbruk med binäringar | EN7: Industri och hantverk | EO7: Byggnadsindustri | EP7: Transporter och kommunikationer | EQ7: Cirkulation | ER7: Privata reproduktiva tjänster | ES7: Offentliga tjänster | ET7: Fastighetsförvaltning | EU7: Totalt hela ekonomin | EV7: Totalt privat sektor | EX7: År | EY7: Jordbruk med binäringar | EZ7: Industri och hantverk | FA7: Byggnadsindustri | FB7: Transporter och kommunikationer | FC7: Cirkulation | FD7: Privata reproduktiva tjänster | FE7: Offentliga tjänster | FF7: Fastighetsförvaltning | FG7: Totalt hela ekonomin | FH7: Totalt privat sektor | FJ7: År | FK7: Jordbruk med binäringar | FL7: Industri och hantverk | FM7: Byggnadsindustri | FN7: Transporter och kommunikationer | FO7: Cirkulation | FP7: Privata reproduktiva tjänster | FQ7: Fastighetsförvaltning | FR7: Totalt antal företagare | FS7: Antal "hemmafruar" | FU7: År | FV7: Jordbruk med binäringar | FW7: Industri och hantverk | FX7: Byggnadsindustri | FY7: Transporter och kommunikationer | FZ7: Cirkulation | GA7: Privata reproduktiva tjänster | GB7: Offentliga tjänster | GC7: Fastighetsförvaltning | GD7: Totalt hela ekonomin | GE7: Totalt privat sektor | GG7: År | GH7: Jordbruk med binäringar | GI7: Industri och hantverk | GJ7: Byggnadsindustri | GK7: Transporter och kommunikationer | GL7: Cirkulation | GM7: Privata reproduktiva tjänster | GN7: Offentliga tjänster | GO7: Fastighetsförvaltning | GP7: Totalt hela ekonomin | GQ7: Totalt privat sektor | GS7: År | GT7: Jordbruk med binäringar | GU7: Industri och hantverk | GV7: Byggnadsindustri | GW7: Transporter och kommunikationer | GX7: Cirkulation | GY7: Privata reproduktiva tjänster | GZ7: Fastighetsförvaltning | HA7: Totalt hela ekonomin | HC7: Year | HD7: Jordbruk med binäringar | HE7: Industri och hantverk | HF7: Byggnadsindustri | HG7: Transporter och kommunikationer | HH7: Övriga privata tjänster, här inkluderat cirkulation och privata reproduktiva tjänster | HI7: Privata reproduktiva tjänster | HJ7: Fastighetsförvaltning | HK7: Totalt hela ekonomin | HL7: Totalt privat sektor | HN7: År | HO7: Jordbruk med binäringar | HP7: Industri och hantverk | HQ7: Byggnadsindustri | HR7: Transporter och kommunikationer | HS7: Övriga privata tjänster, här inkluderat cirkulation och privata reproduktiva tjänster | HT7: Fastighetsförvaltning | HU7: Totalt hela ekonomin | HW7: År | HX7: Jordbruk med binäringar | HY7: Industri och hantverk | HZ7: Byggnadsindustri | IA7: Transporter och kommunikationer | IB7: Övriga privata tjänster, här inkluderat cirkulation och privata reproduktiva tjänster | IC7: Offentliga tjänster | ID7: Fastighetsförvaltning | IE7: Totalt hela ekonomin | IF7: Totalt privat sektor | IH7: År | II7: Nettostock av producerade tillgångar/Bruttoförädlingsvärde | IJ7: Bruttoöverskott/Arbetsinkomst | IK7: Bruttoöverskott/Nettostock av producerade tillgångar | IL7: Nettostock av producerade tillgångar/nettoförädlingsvärde | IM7: Nettöverskott/Arbetsinkomst | IN7: Nettoöverskott/Nettostock av producerad tillgångar | IO7: Förändring av reallöne från föregående år
J8: 1800 | K8: 115.34355 | L8: 110.06013 | M8: 111.2225 | N8: 105.93908 | O8: 4.1210501 | P8: 5.283416 | Q8: 74.955499 | R8: 190.29905 | S8: 185.01563 | U8: 1800 | V8: 49.037642 | W8: 8598.1762 | Y8: 46.791428 | Z8: 7957.7299 | AB8: 2352143 | AE8: 1800 | AF8: 51.555396 | AG8: 12.085592 | AH8: 5.4648712 | AI8: 6.5083959 | AJ8: 4.0596346 | AK8: 14.438785 | AL8: 11.188284 | AM8: 4.759172 | AN8: 110.06013 | BA8: 1800 | BB8: 96.132772 | BC8: 13.271726 | BD8: 4.5935748 | BE8: 0.68449705 | BF8: 0.1197527 | BG8: 0.10492535 | BH8: 14.856538 | BI8: 14.42024 | BJ8: 115.34355 | CB8: 1800 | CC8: 2.1398109 | CD8: 1.0130101 | CE8: 0.017290177 | CF8: 0.63140524 | CG8: 0.30451597 | CH8: 0.19584581 | CI8: 1.2008717 | CJ8: 5.50275 | CL8: 1800 | CM8: 1.9275201 | CN8: 0.37002897 | CO8: 0.014241118 | CP8: 0.53382658 | CQ8: 0.097090435 | CR8: 0.13898309 | CS8: 1.0393598 | CT8: 4.1210501 | CV8: 1800 | CW8: 32.758354 | CX8: 56.115489 | CY8: 5.4337142 | CZ8: 17.39597 | DA8: 15.682366 | DB8: 127.38589 | DC8: 123.51326 | DD8: 18.613266 | DF8: 1800 | DG8: 1.3444966 | DH8: 0.49304034 | DI8: 1.8415483 | DJ8: -0.6861379 | DK8: 7.5105692 | DL8: 0.66906581 | DM8: 2.0120594 | DN8: 2.0288535 | DO8: 0.54484913 | DQ8: 1800 | DR8: 74.535614 | DS8: 131.26897 | DT8: 11.756553 | DU8: 17.39597 | DV8: 15.682366 | DW8: 250.63947 | DX8: 241.84453 | DY8: 28.239217 | EA8: 1800 | EB8: 0.93453894 | EC8: 0.55666312 | ED8: 1.1491 | EE8: -0.078224647 | EF8: 7.5105692 | EG8: 0.66906581 | EH8: 1.3265804 | EI8: 1.3384896 | EJ8: 0.62252243
A9: 1800-1801 | B9: -4.4491681 | C9: -4.4335349 | D9: -3.8903594 | E9: -5.0047277 | F9: -4.4543026 | G9: -7.2386294 | H9: -7.5304379 | J9: 1801 | K9: 118.16873 | L9: 112.73241 | M9: 114.03639 | N9: 108.60007 | O9: 4.1323416 | P9: 5.4363206 | Q9: 79.320786 | R9: 197.48951 | S9: 192.05319 | U9: 1801 | V9: 50.260518 | W9: 7979.2416 | X9: -7.1984407 | Y9: 47.948296 | Z9: 7606.9714 | AA9: -4.4077708 | AB9: 2351124.4 | AC9: -0.043306069 | AE9: 1801 | AF9: 52.345831 | AG9: 12.777799 | AH9: 5.4206768 | AI9: 6.958832 | AJ9: 5.0812015 | AK9: 14.204542 | AL9: 10.999162 | AM9: 4.9443638 | AN9: 112.73241 | AP9: 1800-1801 | AQ9: -9.9971455 | AR9: 2.4438345 | AS9: -0.1617398 | AT9: -1.9966428 | AU9: -2.4152357 | AV9: 0.33584003 | AW9: 2.8294944 | AX9: 0.40497629 | AY9: -4.4491681 | BA9: 1801 | BB9: 99.153551 | BC9: 12.586415 | BD9: 4.6332199 | BE9: 0.74393477 | BF9: -0.30646626 | BG9: 0.15100382 | BH9: 19.653271 | BI9: 18.446201 | BJ9: 118.16873 | BL9: 1800-1801 | BM9: -9.320104 | BN9: -1.3922634 | BO9: -4.8820506 | BP9: 32.542291 | BQ9: 24.489116 | BR9: -7.2386294 | BT9: 1800-1801 | BU9: 13.743292 | BV9: -3.8246777 | BW9: -0.23711215 | BX9: -0.1925976 | BY9: 2.7550244 | BZ9: 10.443995 | CB9: 1801 | CC9: 1.8577282 | CD9: 0.93476082 | CE9: 0.016674194 | CF9: 0.69684498 | CG9: 0.28420025 | CH9: 0.16353982 | CI9: 1.2679439 | CJ9: 5.2216922 | CL9: 1801 | CM9: 1.9202824 | CN9: 0.37386969 | CO9: 0.012115157 | CP9: 0.54165006 | CQ9: 0.10221098 | CR9: 0.13609164 | CS9: 1.0461217 | CT9: 4.1323416 | CV9: 1801 | CW9: 32.919866 | CX9: 57.148883 | CY9: 5.1304917 | CZ9: 18.702506 | DA9: 17.23174 | DB9: 131.13349 | DC9: 127.2326 | DD9: 19.641014 | DF9: 1801 | DG9: 1.3231269 | DH9: 0.6738249 | DI9: 1.6971488 | DJ9: 1.0255197 | DK9: 1.618629 | DL9: 0.87631205 | DM9: 1.2948809 | DN9: 1.3130513 | DO9: 0.35534152 | DQ9: 1801 | DR9: 74.950526 | DS9: 132.77738 | DT9: 11.167818 | DU9: 18.702506 | DV9: 17.23174 | DW9: 254.82997 | DX9: 246.00939 | DY9: 29.227788 | EA9: 1801 | EB9: 0.936933 | EC9: 0.63691845 | ED9: 1.106286 | EE9: 0.73706048 | EF9: 1.618629 | EG9: 0.87631205 | EH9: 0.97400773 | EI9: 0.9852661 | EJ9: 0.54432545
A10: 1801-1802 | B10: 3.8116577 | C10: 3.8350712 | D10: 3.8207195 | E10: 3.8025968 | F10: 3.6531445 | G10: 4.215858 | H10: 4.3608909 | J10: 1802 | K10: 121.16509 | L10: 115.5673 | M10: 117.0088 | N10: 111.411 | O10: 4.1562936 | P10: 5.5977949 | Q10: 79.517196 | R10: 200.68229 | S10: 195.08449 | U10: 1802 | V10: 51.263632 | W10: 8271.8545 | X10: 3.6671765 | Y10: 48.895266 | Z10: 7855.347 | AA10: 3.2651042 | AB10: 2363568.2 | AC10: 0.52927222 | AE10: 1802 | AF10: 54.244934 | AG10: 13.231086 | AH10: 4.2322086 | AI10: 8.3508132 | AJ10: 6.0039647 | AK10: 13.718799 | AL10: 10.812283 | AM10: 4.9732088 | AN10: 115.5673 | AP10: 1801-1802 | AQ10: 4.4764961 | AR10: 8.9970555 | AS10: -16.975263 | AT10: 13.134129 | AU10: 4.3902316 | AV10: 0.5993191 | AW10: 3.8626133 | AX10: 0.583392 | AY10: 3.8116577 | BA10: 1802 | BB10: 96.614661 | BC10: 12.593731 | BD10: 3.6872652 | BE10: 0.66018231 | BF10: 0.26340701 | BG10: 0.46432797 | BH10: 20.975206 | BI10: 14.093688 | BJ10: 121.16509 | BL10: 1801-1802 | BM10: 0.19039309 | BN10: 4.486049 | BO10: -3.0054466 | BP10: 8.5008206 | BQ10: -15.429566 | BR10: 4.215858 | BT10: 1801-1802 | BU10: -2.7457294 | BV10: -4.2378117 | BW10: 0.20584198 | BX10: -1.6355067 | BY10: -9.6560301 | BZ10: -1.612224 | CB10: 1802 | CC10: 1.9532286 | CD10: 0.96621727 | CE10: 0.014835421 | CF10: 0.64641938 | CG10: 0.32308318 | CH10: 0.18124536 | CI10: 0.99015324 | CJ10: 5.0751824 | CL10: 1802 | CM10: 1.9118291 | CN10: 0.39241432 | CO10: 0.013777404 | CP10: 0.54723776 | CQ10: 0.10537096 | CR10: 0.13985094 | CS10: 1.0458131 | CT10: 4.1562936 | CV10: 1802 | CW10: 33.141688 | CX10: 58.118784 | CY10: 5.2863428 | CZ10: 19.00523 | DA10: 17.33489 | DB10: 132.88694 | DC10: 128.93975 | DD10: 19.741995 | DF10: 1802 | DG10: 0.25599633 | DH10: -0.16794503 | DI10: 0.49774489 | DJ10: -0.77105175 | DK10: -0.95177444 | DL10: 2.6785746 | DM10: 0.35936906 | DN10: 0.33841929 | DO10: 4.5163723 | DQ10: 1802 | DR10: 75.4279 | DS10: 134.24628 | DT10: 11.476398 | DU10: 19.00523 | DV10: 17.33489 | DW10: 257.49069 | DX10: 248.57107 | DY10: 29.493088 | EA10: 1802 | EB10: 0.46905091 | EC10: 0.25839648 | ED10: 0.58740967 | EE10: -0.13820485 | EF10: -0.95177444 | EG10: 2.6785746 | EH10: 0.4858655 | EI10: 0.4740072 | EJ10: 3.3581454
A11: 1802-1803 | B11: 0.54520004 | C11: 0.53786318 | D11: 0.59366603 | E11: 0.49675739 | F11: 0.60106744 | G11: -2.036769 | H11: -2.1067364 | J11: 1803 | K11: 115.42132 | L11: 110.11268 | M11: 111.34106 | N11: 106.03243 | O11: 4.0802559 | P11: 5.3086319 | Q11: 79.093535 | R11: 194.51485 | S11: 189.20622 | U11: 1803 | V11: 48.488133 | W11: 8046.0657 | X11: -2.7296029 | Y11: 46.257994 | Z11: 7842.3154 | AA11: -0.16589452 | AB11: 2380403.4 | AC11: 0.71227618 | AE11: 1803 | AF11: 50.48202 | AG11: 13.325406 | AH11: 3.8449263 | AI11: 8.0128928 | AJ11: 5.4958477 | AK11: 12.694969 | AL11: 10.768957 | AM11: 5.4876647 | AN11: 110.11268 | AP11: 1802-1803 | AQ11: 0.54345474 | AR11: -1.8008398 | AS11: -1.7714022 | AT11: 2.3790326 | AU11: -4.4416055 | AV11: 0.41328979 | AW11: 6.159575 | AX11: 0.25205644 | AY11: 0.54520004 | BA11: 1803 | BB11: 91.646348 | BC11: 12.97674 | BD11: 3.4496478 | BE11: 0.65168502 | BF11: 0.14462245 | BG11: 0.42727941 | BH11: 19.550888 | BI11: 13.425896 | BJ11: 115.42132 | BL11: 1802-1803 | BM11: -1.8554296 | BN11: 8.0943768 | BO11: -6.6744678 | BP11: -9.7286425 | BQ11: -5.2639907 | BR11: -2.036769 | BT11: 1802-1803 | BU11: -3.349111 | BV11: -4.6747181 | BW11: -1.3344697 | BX11: 3.2548113 | BY11: 0.55496968 | BZ11: -2.7598984 | CB11: 1803 | CC11: 2.0377381 | CD11: 0.43800253 | CE11: 0.013201321 | CF11: 0.68410895 | CG11: 0.1388221 | CH11: 0.21722182 | CI11: 1.1441398 | CJ11: 4.6732347 | CL11: 1803 | CM11: 1.8602901 | CN11: 0.38608181 | CO11: 0.015778332 | CP11: 0.55939311 | CQ11: 0.099677337 | CR11: 0.14170477 | CS11: 1.0173305 | CT11: 4.0802559 | CV11: 1803 | CW11: 32.05209 | CX11: 56.582815 | CY11: 5.5078367 | CZ11: 18.824343 | DA11: 17.904556 | DB11: 130.87164 | DC11: 126.9768 | DD11: 20.545481 | DF11: 1803 | DG11: 0.11180572 | DH11: 0.39563519 | DI11: -0.048973272 | DJ11: -1.4241483 | DK11: 0.71111816 | DL11: 2.3864284 | DM11: 0.42799843 | DN11: 0.38103634 | DO11: 2.8292946 | DQ11: 1803 | DR11: 73.25959 | DS11: 130.81501 | DT11: 12.023952 | DU11: 18.824343 | DV11: 17.904556 | DW11: 252.82745 | DX11: 244.0489 | DY11: 30.209509 | EA11: 1803 | EB11: 0.39916236 | EC11: 0.50412877 | ED11: 0.34037862 | EE11: -0.50620509 | EF11: 0.71111816 | EG11: 2.3864284 | EH11: 0.51210681 | EI11: 0.48618114 | EJ11: 2.1920761
A12: 1803-1804 | B12: -0.73621898 | C12: -0.79674509 | D12: -0.65777754 | E12: -0.81459847 | F12: -0.71394539 | G12: 1.4880478 | H12: 1.5183574 | J12: 1804 | K12: 113.90068 | L12: 108.6599 | M12: 109.53418 | N12: 104.29341 | O12: 4.3664952 | P12: 5.2407738 | Q12: 77.285617 | R12: 191.18629 | S12: 185.94552 | U12: 1804 | V12: 47.533789 | W12: 8111.948 | X12: 0.81881397 | Y12: 45.346674 | Z12: 7733.2456 | AA12: -1.3907856 | AB12: 2396204.5 | AC12: 0.6637986 | AE12: 1804 | AF12: 49.014837 | AG12: 13.251897 | AH12: 4.5688065 | AI12: 7.7605126 | AJ12: 4.6887319 | AK12: 13.127684 | AL12: 10.586047 | AM12: 5.661387 | AN12: 108.6599 | AP12: 1803-1804 | AQ12: -1.4129765 | AR12: 0.12834235 | AS12: 5.7492289 | AT12: 0.4349827 | AU12: 3.3982293 | AV12: 0.46922564 | AW12: -5.6758731 | AX12: 0.1134485 | AY12: -0.73621898 | BA12: 1804 | BB12: 101.01626 | BC12: 12.529314 | BD12: 4.2006047 | BE12: 0.8687678 | BF12: 0.096287749 | BG12: -0.021057463 | BH12: 17.993398 | BI12: 22.782894 | BJ12: 113.90068 | BL12: 1803-1804 | BM12: 14.736282 | BN12: -6.1538488 | BO12: 4.7053363 | BP12: -9.7067556 | BQ12: 66.811425 | BR12: 1.4880478 | BT12: 1803-1804 | BU12: -3.9327567 | BV12: 2.8833786 | BW12: 5.1393887 | BX12: 1.9275138 | BY12: 1.727837 | BZ12: -2.7643808 | CB12: 1804 | CC12: 2.1174354 | CD12: 0.74143034 | CE12: 0.017680421 | CF12: 0.72025202 | CG12: 0.20006912 | CH12: 0.19605011 | CI12: 1.1516854 | CJ12: 5.1446028 | CL12: 1804 | CM12: 1.9818879 | CN12: 0.42344341 | CO12: 0.016598665 | CP12: 0.59775071 | CQ12: 0.10942079 | CR12: 0.15163646 | CS12: 1.0857573 | CT12: 4.3664952 | CV12: 1804 | CW12: 34.254957 | CX12: 60.203821 | CY12: 5.7328449 | CZ12: 18.958207 | DA12: 17.266884 | DB12: 136.41671 | DC12: 132.19214 | DD12: 20.912827 | DF12: 1804 | DG12: 0.64646844 | DH12: 0.1924632 | DI12: 0.90478975 | DJ12: 1.6148775 | DK12: 20.564132 | DL12: -0.12195288 | DM12: 3.289348 | DN12: 3.3612454 | DO12: -0.76711115 | DQ12: 1804 | DR12: 78.379165 | DS12: 139.72868 | DT12: 12.635333 | DU12: 18.958207 | DV12: 17.266884 | DW12: 266.96827 | DX12: 257.51284 | DY12: 31.283189 | EA12: 1804 | EB12: 0.63222765 | EC12: 0.4109118 | ED12: 0.75637218 | EE12: 0.93464888 | EF12: 20.564132 | EG12: -0.12195288 | EH12: 1.9757539 | EI12: 2.0177076 | EJ12: -0.18497081
A13: 1804-1805 | B13: 4.4854784 | C13: 4.4786817 | D13: 4.3964206 | E13: 4.5746122 | F13: 4.3954423 | G13: 3.9505492 | H13: 4.1040377 | J13: 1805 | K13: 123.81956 | L13: 118.09243 | M13: 119.19893 | N13: 113.47179 | O13: 4.6206345 | P13: 5.7271369 | Q13: 82.128975 | R13: 205.94854 | S13: 200.2214 | U13: 1805 | V13: 51.315466 | W13: 8374.036 | X13: 3.2308881 | Y13: 48.941926 | Z13: 8024.1791 | AA13: 3.7621139 | AB13: 2412909.3 | AC13: 0.6971374 | AE13: 1805 | AF13: 55.788233 | AG13: 14.211373 | AH13: 4.5485506 | AI13: 7.7699051 | AJ13: 5.7796913 | AK13: 13.265296 | AL13: 10.916955 | AM13: 5.8124226 | AN13: 118.09243 | AP13: 1804-1805 | AQ13: 7.7020785 | AR13: 4.7651023 | AS13: -5.7852275 | AT13: -1.9234834 | AU13: 5.1128511 | AV13: 0.80379541 | AW13: 4.6680146 | AX13: 0.29399775 | AY13: 4.4854784 | BA13: 1805 | BB13: 105.32606 | BC13: 12.806465 | BD13: 3.97771 | BE13: 0.74440617 | BF13: 0.34292829 | BG13: 0.34099196 | BH13: 17.216482 | BI13: 16.935476 | BJ13: 123.81956 | BL13: 1804-1805 | BM13: 0.67885697 | BN13: 3.0151388 | BO13: -0.41584769 | BP13: -6.1104551 | BQ13: -21.057375 | BR13: 3.9505492 | BT13: 1804-1805 | BU13: 3.5633966 | BV13: -0.77961176 | BW13: 5.5205096 | BX13: 1.9093386 | BY13: -5.8377194 | BZ13: 4.5769998 | CB13: 1805 | CC13: 2.5425138 | CD13: 0.57332995 | CE13: 0.015673921 | CF13: 0.63140187 | CG13: 0.16265468 | CH13: 0.19854483 | CI13: 1.2819173 | CJ13: 5.4060364 | CL13: 1805 | CM13: 2.0929489 | CN13: 0.44978827 | CO13: 0.017720184 | CP13: 0.62765877 | CQ13: 0.11475511 | CR13: 0.16187644 | CS13: 1.1558868 | CT13: 4.6206345 | CV13: 1805 | CW13: 36.400939 | CX13: 64.430269 | CY13: 6.0589182 | CZ13: 22.856797 | DA13: 18.319924 | DB13: 148.06685 | DC13: 143.53591 | DD13: 22.041614 | DF13: 1805 | DG13: 0.16100987 | DH13: 0.34622857 | DI13: 0.056367523 | DJ13: -1.0187783 | DK13: -14.471073 | DL13: 1.8613175 | DM13: -1.8980907 | DN13: -1.983461 | DO13: -2.4553285 | DQ13: 1805 | DR13: 83.471006 | DS13: 149.31801 | DT13: 13.257894 | DU13: 22.856797 | DV13: 18.319924 | DW13: 287.22363 | DX13: 277.10411 | DY13: 33.162583 | EA13: 1805 | EB13: 0.41544008 | EC13: 0.47560212 | ED13: 0.3818086 | EE13: -0.31905701 | EF13: -14.471073 | EG13: 1.8613175 | EH13: -0.69190956 | EI13: -0.74369292 | EJ13: -1.3252687
A14: 1805-1806 | B14: 0.22097275 | C14: 0.23323719 | D14: 0.39072939 | E14: 0.051503164 | F14: 0.32879509 | G14: 1.8260137 | H14: 1.8835622 | J14: 1806 | K14: 133.09498 | L14: 126.96119 | M14: 128.30897 | N14: 122.17517 | O14: 4.7860178 | P14: 6.1337931 | Q14: 86.999202 | R14: 220.09419 | S14: 213.96039 | U14: 1806 | V14: 54.875835 | W14: 8483.0889 | X14: 1.3022744 | Y14: 52.346837 | Z14: 8000.547 | AA14: -0.29451106 | AB14: 2425384.2 | AC14: 0.51700645 | AE14: 1806 | AF14: 57.752563 | AG14: 14.762946 | AH14: 4.8523967 | AI14: 7.3204265 | AJ14: 7.1579355 | AK14: 16.605811 | AL14: 12.175709 | AM14: 6.333401 | AN14: 126.96119 | AP14: 1805-1806 | AQ14: 2.3905305 | AR14: 1.1883697 | AS14: -0.74151889 | AT14: -1.6657567 | AU14: 4.1275531 | AV14: -0.14326326 | AW14: -10.926473 | AX14: 0.26931641 | AY14: 0.22097275 | BA14: 1806 | BB14: 112.45945 | BC14: 14.228689 | BD14: 4.1236722 | BE14: 0.96032168 | BF14: 0.075861617 | BG14: 0.49781952 | BH14: 19.140004 | BI14: 18.390834 | BJ14: 133.09498 | BL14: 1805-1806 | BM14: 0.80916135 | BN14: -7.7089432 | BO14: 0.94481162 | BP14: 9.6209823 | BQ14: -4.56621 | BR14: 1.8260137 | BT14: 1805-1806 | BU14: 5.9156462 | BV14: 20.386 | BW14: 3.6752354 | BX14: 1.4154079 | BY14: 13.789405 | BZ14: 5.5634735 | CB14: 1806 | CC14: 2.6491551 | CD14: 0.48668427 | CE14: 0.012948422 | CF14: 0.70283536 | CG14: 0.16670867 | CH14: 0.21629477 | CI14: 1.4230484 | CJ14: 5.657675 | CL14: 1806 | CM14: 2.1814311 | CN14: 0.45486739 | CO14: 0.017943038 | CP14: 0.65346131 | CQ14: 0.11472135 | CR14: 0.16770756 | CS14: 1.1958861 | CT14: 4.7860178 | CV14: 1806 | CW14: 37.570597 | CX14: 66.308489 | CY14: 6.3028723 | CZ14: 19.549173 | DA14: 20.038278 | DB14: 149.76941 | DC14: 145.07015 | DD14: 22.670218 | DF14: 1806 | DG14: 0.18460499 | DH14: 0.60462782 | DI14: -0.053381255 | DJ14: 1.6508045 | DK14: 4.1498752 | DL14: 2.4843428 | DM14: 1.0746236 | DN14: 1.0759068 | DO14: -0.56561103 | DQ14: 1806 | DR14: 86.264225 | DS14: 154.17064 | DT14: 13.884994 | DU14: 19.549173 | DV14: 20.038278 | DW14: 293.90731 | DX14: 283.42036 | DY14: 34.221646 | EA14: 1806 | EB14: 0.41966077 | EC14: 0.58845194 | ED14: 0.32521581 | EE14: 0.95121459 | EF14: 4.1498752 | EG14: 2.4843428 | EH14: 0.83550037 | EI14: 0.83565413 | EJ14: -0.095044134
A15: 1806-1807 | B15: -3.1828525 | C15: -3.1532172 | D15: -3.0979268 | E15: -3.2677038 | F15: -3.1571691 | G15: -4.1642941 | H15: -4.3307297 | J15: 1807 | K15: 139.55179 | L15: 133.09089 | M15: 134.74757 | N15: 128.28666 | O15: 4.8042269 | P15: 6.4609074 | Q15: 90.247446 | R15: 229.79924 | S15: 223.33833 | U15: 1807 | V15: 57.330565 | W15: 8100.5164 | X15: -4.5098251 | Y15: 54.6763 | Z15: 7717.9739 | AA15: -3.5319221 | AB15: 2434160.4 | AC15: 0.36184981 | AE15: 1807 | AF15: 64.293654 | AG15: 14.283501 | AH15: 5.3546157 | AI15: 6.8757699 | AJ15: 7.2426229 | AK15: 16.493305 | AL15: 12.183912 | AM15: 6.3635065 | AN15: 133.09089 | AP15: 1806-1807 | AQ15: -4.0958874 | AR15: -6.2882234 | AS15: 7.1576191 | AT15: -11.47493 | AU15: -2.5633516 | AV15: -0.052391245 | AW15: -0.26931135 | AX15: 0.47534513 | AY15: -3.1828525 | BA15: 1807 | BB15: 115.02678 | BC15: 14.126976 | BD15: 4.5276759 | BE15: 0.87061585 | BF15: 0.00026067057 | BG15: -0.0073600777 | BH15: 18.723132 | BI15: 13.71629 | BJ15: 139.55179 | BL15: 1806-1807 | BM15: -7.6549492 | BN15: -0.51042736 | BO15: -4.7709421 | BP15: -3.1392918 | BQ15: -23.165869 | BR15: -4.1642941 | BT15: 1806-1807 | BU15: 10.761645 | BV15: -0.20546131 | BW15: 0.063881068 | BX15: 0.99243281 | BY15: -2.93089 | BZ15: 9.4073232 | CB15: 1807 | CC15: 2.8245608 | CD15: 0.11611579 | CE15: 0.013470019 | CF15: 0.65347018 | CG15: 0.01494128 | CH15: 0.21060313 | CI15: 1.5580311 | CJ15: 5.3911923 | CL15: 1807 | CM15: 2.2073528 | CN15: 0.44100763 | CO15: 0.017294099 | CP15: 0.65275707 | CQ15: 0.11147552 | CR15: 0.16819637 | CS15: 1.2061434 | CT15: 4.8042269 | CV15: 1807 | CW15: 37.79776 | CX15: 66.273093 | CY15: 6.3581318 | CZ15: 20.36044 | DA15: 21.217493 | DB15: 152.00692 | DC15: 147.26269 | DD15: 22.961144 | DF15: 1807 | DG15: 0.55340011 | DH15: 0.93097518 | DI15: 0.33805642 | DJ15: 0.26804565 | DK15: -37.7265 | DL15: -0.034688724 | DM15: -6.0366479 | DN15: -6.2498765 | DO15: -6.8041973 | DQ15: 1807 | DR15: 86.771848 | DS15: 154.67202 | DT15: 13.906691 | DU15: 20.36044 | DV15: 21.217493 | DW15: 296.9285 | DX15: 286.3626 | DY15: 34.593418 | EA15: 1807 | EB15: 0.57768035 | EC15: 0.73442308 | ED15: 0.48974683 | EE15: 0.31184158 | EF15: -37.7265 | EG15: -0.034688724 | EH15: -2.8794724 | EI15: -3.0109072 | EJ15: -4.2611095
A16: 1807-1808 | B16: -3.6381447 | C16: -3.6703096 | D16: -3.265078 | E16: -4.0097726 | F16: -3.5664494 | G16: -2.3922435 | H16: -2.5124802 | J16: 1808 | K16: 155.54693 | L16: 148.4229 | M16: 149.8509 | N16: 142.72687 | O16: 5.6960355 | P16: 7.1240305 | Q16: 95.133185 | R16: 250.68012 | S16: 243.55609 | U16: 1808 | V16: 63.916705 | W16: 7908.5919 | X16: -2.3692876 | Y16: 60.989328 | Z16: 7438.932 | AA16: -3.6154819 | AB16: 2433588.1 | AC16: -0.023512955 | AE16: 1808 | AF16: 69.046519 | AG16: 14.428377 | AH16: 7.3918545 | AI16: 4.6694123 | AJ16: 9.5817332 | AK16: 20.660584 | AL16: 15.106492 | AM16: 7.5379305 | AN16: 148.4229 | AP16: 1807-1808 | AQ16: -3.8337799 | AR16: -3.2653488 | AS16: 8.7339193 | AT16: -26.966392 | AU16: -2.5916916 | AV16: -0.52345618 | AW16: -4.2872078 | AX16: 0.76766939 | AY16: -3.6381447 | BA16: 1808 | BB16: 133.10257 | BC16: 17.744 | BD16: 5.8886895 | BE16: 1.0014946 | BF16: 0.22397474 | BG16: -0.42693092 | BH16: 11.918126 | BI16: 13.904989 | BJ16: 155.54693 | BL16: 1807-1808 | BM16: 4.5655455 | BN16: -0.96498896 | BO16: 4.6553456 | BP16: -44.717499 | BQ16: 1.7067405 | BR16: -2.3922435 | BT16: 1807-1808 | BU16: 10.662087 | BV16: 26.827539 | BW16: 18.522249 | BX16: 15.14412 | BY16: -0.32545469 | BZ16: 14.193582 | CB16: 1808 | CC16: 4.2914451 | CD16: -0.10991862 | CE16: 0.018358239 | CF16: 0.2568059 | CG16: -0.13350885 | CH16: 0.072133467 | CI16: 2.2919127 | CJ16: 6.6872279 | CL16: 1808 | CM16: 2.6564334 | CN16: 0.47684348 | CO16: 0.013460463 | CP16: 0.73028428 | CQ16: 0.13236163 | CR16: 0.19043194 | CS16: 1.4962203 | CT16: 5.6960355 | CV16: 1808 | CW16: 46.627347 | CX16: 81.274274 | CY16: 6.099912 | CZ16: 25.358317 | DA16: 24.351919 | DB16: 183.71177 | DC16: 177.95708 | DD16: 24.857476 | DF16: 1808 | DG16: 0.80104748 | DH16: 1.7064929 | DI16: 0.28159013 | DJ16: 2.8419433 | DK16: 6.6485088 | DL16: -1.7531716 | DM16: 1.4825461 | DN16: 1.5951739 | DO16: 3.0285666 | DQ16: 1808 | DR16: 106.83337 | DS16: 189.96942 | DT16: 13.359007 | DU16: 25.358317 | DV16: 24.351919 | DW16: 359.87203 | DX16: 347.0762 | DY16: 38.744911 | EA16: 1808 | EB16: 0.68618351 | EC16: 1.0856506 | ED16: 0.46153467 | EE16: 1.5834576 | EF16: 6.6485088 | EG16: -1.7531716 | EH16: 1.0528887 | EI16: 1.1124051 | EJ16: 2.1428877
A17: 1808-1809 | B17: -4.1354473 | C17: -4.1767353 | D17: -3.9745721 | E17: -4.296053 | F17: -4.2806174 | G17: 0.7588384 | H17: 0.77953293 | J17: 1809 | K17: 166.61586 | L17: 158.74449 | M17: 160.28759 | N17: 152.41622 | O17: 6.3282705 | P17: 7.8713742 | Q17: 100.38571 | R17: 267.00157 | S17: 259.1302 | U17: 1809 | V17: 69.112604 | W17: 8043.9675 | X17: 1.7117535 | Y17: 65.847542 | Z17: 7198.7423 | AA17: -3.2288194 | AB17: 2410788.3 | AC17: -0.93687802 | AE17: 1809 | AF17: 82.278618 | AG17: 14.966813 | AH17: 7.3202909 | AI17: 9.015166 | AJ17: 7.8741226 | AK17: 17.51847 | AL17: 11.442569 | AM17: 8.3284364 | AN17: 158.74449 | AP17: 1808-1809 | AQ17: -6.5924155 | AR17: -5.5014134 | AS17: -10.508543 | AT17: 26.042963 | AU17: -1.2463791 | AV17: -0.68578139 | AW17: -7.6275635 | AX17: 1.3179921 | AY17: -4.1354473 | BA17: 1809 | BB17: 149.074 | BC17: 13.303649 | BD17: 5.3741267 | BE17: 0.9554115 | BF17: -0.20687607 | BG17: -0.31225504 | BH17: 20.845734 | BI17: 22.417925 | BJ17: 166.61586 | BL17: 1808-1809 | BM17: 1.1910215 | BN17: -15.335023 | BO17: -22.882588 | BP17: 76.546956 | BQ17: 35.1834 | BR17: 0.7588384 | BT17: 1808-1809 | BU17: 10.681103 | BV17: -11.444522 | BW17: 12.669919 | BX17: -0.92843802 | BY17: 19.261808 | BZ17: 6.3094171 | CB17: 1809 | CC17: 3.2492654 | CD17: 0.13245069 | CE17: 0.018643174 | CF17: 0.34507331 | CG17: -0.0081618364 | CH17: 0.064324157 | CI17: 2.0088122 | CJ17: 5.8104071 | CL17: 1809 | CM17: 2.9858766 | CN17: 0.52136856 | CO17: 0.015108656 | CP17: 0.77545469 | CQ17: 0.14546692 | CR17: 0.20814014 | CS17: 1.6768549 | CT17: 6.3282705 | CV17: 1809 | CW17: 52.812021 | CX17: 90.764854 | CY17: 6.7735018 | CZ17: 40.566401 | DA17: 23.582802 | DB17: 214.49958 | DC17: 208.22867 | DD17: 26.583412 | DF17: 1809 | DG17: -0.031527877 | DH17: 0.62856384 | DI17: -0.41560581 | DJ17: 0.70707622 | DK17: 26.191916 | DL17: -1.3240795 | DM17: 4.5641405 | DN17: 4.7751696 | DO17: -0.051230545 | DQ17: 1809 | DR17: 120.26516 | DS17: 212.53326 | DT17: 14.643308 | DU17: 40.566401 | DV17: 23.582802 | DW17: 411.59094 | DX17: 397.43577 | DY17: 42.117928 | EA17: 1809 | EB17: 0.31795871 | EC17: 0.61555495 | ED17: 0.14955938 | EE17: 0.62276405 | EF17: 26.191916 | EG17: -1.3240795 | EH17: 2.6378085 | EI17: 2.7578038 | EJ17: 0.17413016
A18: 1809-1810 | B18: 9.3868345 | C18: 9.2717128 | D18: 9.5883573 | E18: 9.1856822 | F18: 9.0795991 | G18: 12.424375 | H18: 12.939706 | J18: 1810 | K18: 177.75129 | L18: 169.28695 | M18: 170.41503 | N18: 161.95068 | O18: 7.3362629 | P18: 8.4643462 | Q18: 106.89291 | R18: 284.6442 | S18: 276.17986 | U18: 1810 | V18: 74.210664 | W18: 9102.1381 | X18: 13.154835 | Y18: 70.676823 | Z18: 7925.6395 | AA18: 10.097558 | AB18: 2395225.7 | AC18: -0.64554017 | AE18: 1810 | AF18: 87.344633 | AG18: 16.037533 | AH18: 8.7273802 | AI18: 12.101478 | AJ18: 7.9171237 | AK18: 16.691161 | AL18: 10.888376 | AM18: 9.5792602 | AN18: 169.28695 | AP18: 1809-1810 | AQ18: 12.85335 | AR18: 2.7237088 | AS18: -1.6063002 | AT18: 29.74791 | AU18: 7.8963305 | AV18: 1.7288493 | AW18: 4.0170548 | AX18: 1.1660927 | AY18: 9.3868345 | BA18: 1810 | BB18: 161.51459 | BC18: 13.700488 | BD18: 6.8531008 | BE18: 1.2606462 | BF18: 1.360364 | BG18: -0.032214509 | BH18: 21.816153 | BI18: 28.721836 | BJ18: 177.75129 | BL18: 1809-1810 | BM18: 12.765 | BN18: 11.602475 | BO18: 41.355175 | BP18: 0.34814347 | BQ18: 10.912141 | BR18: 12.424375 | BT18: 1809-1810 | BU18: -3.9194359 | BV18: -7.7234272 | BW18: 14.958465 | BX18: 4.2921519 | BY18: 15.51482 | BZ18: -5.1066144 | CB18: 1810 | CC18: 5.0031748 | CD18: 0.29868339 | CE18: 0.015130678 | CF18: 1.6219106 | CG18: 0.073446528 | CH18: 0.28296077 | CI18: 2.1465896 | CJ18: 9.4418964 | CL18: 1810 | CM18: 3.4586019 | CN18: 0.58721514 | CO18: 0.015945672 | CP18: 0.90921555 | CQ18: 0.16641563 | CR18: 0.24128822 | CS18: 1.9575808 | CT18: 7.3362629 | CV18: 1810 | CW18: 61.820546 | CX18: 105.14479 | CY18: 7.3941543 | CZ18: 51.191518 | DA18: 23.429846 | DB18: 248.98086 | DC18: 241.87408 | DD18: 28.456476 | DF18: 1810 | DG18: 0.31556859 | DH18: 0.30573793 | DI18: 0.32134859 | DJ18: 3.3001 | DK18: 2.15517 | DL18: -0.13749347 | DM18: 0.73213783 | DN18: 0.7360018 | DO18: 1.5205125 | DQ18: 1810 | DR18: 140.76145 | DS18: 247.60233 | DT18: 15.957136 | DU18: 51.191518 | DV18: 23.429846 | DW18: 478.94228 | DX18: 462.63508 | DY18: 46.539783 | EA18: 1810 | EB18: 0.4642105 | EC18: 0.47043507 | ED18: 0.46067185 | EE18: 1.9508842 | EF18: 2.15517 | EG18: -0.13749347 | EH18: 0.66060204 | EI18: 0.66297645 | EJ18: 1.1069493
A19: 1810-1811 | B19: 3.2249951 | C19: 3.1163891 | D19: 3.6116735 | E19: 2.8397598 | F19: 3.269166 | G19: 3.9879328 | H19: 4.1369711 | J19: 1811 | K19: 191.78195 | L19: 182.6969 | M19: 183.56561 | N19: 174.48056 | O19: 8.2163411 | P19: 9.0850515 | Q19: 117.0545 | R19: 308.83645 | S19: 299.7514 | U19: 1811 | V19: 79.781006 | W19: 9431.1487 | X19: 3.6146517 | Y19: 76.001638 | Z19: 8151.8731 | AA19: 2.8544527 | AB19: 2403854.8 | AC19: 0.36025898 | AE19: 1811 | AF19: 88.598922 | AG19: 16.777165 | AH19: 10.208412 | AI19: 13.375517 | AJ19: 7.2211592 | AK19: 22.663582 | AL19: 12.682685 | AM19: 11.169457 | AN19: 182.6969 | AP19: 1810-1811 | AQ19: 5.3185348 | AR19: -0.73708943 | AS19: 4.8366987 | AT19: 19.023726 | AU19: 5.2558708 | AV19: 0.62441836 | AW19: -16.000186 | AX19: 0.46702122 | AY19: 3.2249951 | BA19: 1811 | BB19: 158.67604 | BC19: 16.627419 | BD19: 7.9228147 | BE19: 1.2763047 | BF19: 0.77134358 | BG19: 0.41559911 | BH19: 25.712637 | BI19: 19.620204 | BJ19: 191.78195 | BL19: 1810-1811 | BM19: -2.9665258 | BN19: -8.5423783 | BO19: 0.53686441 | BP19: 12.83747 | BQ19: -35.53144 | BR19: 3.9879328 | BT19: 1810-1811 | BU19: 1.2460301 | BV19: 32.699379 | BW19: 9.4123499 | BX19: 4.4516005 | BY19: 5.9603412 | BZ19: 3.7557133 | CB19: 1811 | CC19: 5.072933 | CD19: 0.63573952 | CE19: 0.015626486 | CF19: 1.553787 | CG19: 0.20423459 | CH19: 0.37316353 | CI19: 2.5305779 | CJ19: 10.386062 | CL19: 1811 | CM19: 3.8758663 | CN19: 0.65420328 | CO19: 0.020672797 | CP19: 1.0336726 | CQ19: 0.18116492 | CR19: 0.27577552 | CS19: 2.1749857 | CT19: 8.2163411 | CV19: 1811 | CW19: 68.536877 | CX19: 116.58612 | CY19: 8.8769332 | CZ19: 52.294782 | DA19: 23.023351 | DB19: 269.31806 | DC19: 261.37641 | DD19: 30.138554 | DF19: 1811 | DG19: 0.48439555 | DH19: 0.51883345 | DI19: 0.46415071 | DJ19: 1.0058848 | DK19: -3.5702611 | DL19: 1.80512 | DM19: -0.10698849 | DN19: -0.14772136 | DO19: -9.0074635 | DQ19: 1811 | DR19: 156.31034 | DS19: 274.92643 | DT19: 18.889654 | DU19: 52.294782 | DV19: 23.023351 | DW19: 525.44457 | DX19: 507.22959 | DY19: 50.378509 | EA19: 1811 | EB19: 0.53507963 | EC19: 0.5631611 | ED19: 0.51911382 | EE19: 0.90413067 | EF19: -3.5702611 | EG19: 1.80512 | EH19: 0.23044628 | EI19: 0.20725398 | EJ19: -5.3196914
A20: 1811-1812 | B20: -3.0046987 | C20: -3.0797749 | D20: -2.9976101 | E20: -3.0117867 | F20: -2.9282329 | G20: -6.7785228 | H20: -7.1208914 | J20: 1812 | K20: 228.99697 | L20: 218.19418 | M20: 219.17071 | N20: 208.36792 | O20: 9.8262603 | P20: 10.802791 | Q20: 145.54366 | R20: 374.54063 | S20: 363.73784 | U20: 1812 | V20: 94.819695 | W20: 8750.9984 | X20: -7.2117441 | Y20: 90.346634 | Z20: 7870.1886 | AA20: -3.4554578 | AB20: 2415078.2 | AC20: 0.46689242 | AE20: 1812 | AF20: 102.79209 | AG20: 18.721722 | AH20: 14.741379 | AI20: 10.739608 | AJ20: 13.018032 | AK20: 29.061755 | AL20: 16.034844 | AM20: 13.084751 | AN20: 218.19418 | AP20: 1811-1812 | AQ20: -4.4662862 | AR20: -3.2112784 | AS20: 18.69785 | AT20: -21.346351 | AU20: -3.999364 | AV20: 0.91062181 | AW20: -1.6384877 | AX20: 0.41222916 | AY20: -3.0046987 | BA20: 1812 | BB20: 210.60788 | BC20: 20.520534 | BD20: 11.634482 | BE20: 1.4447159 | BF20: -0.1079829 | BG20: 0.082448824 | BH20: 21.798822 | BI20: 36.983926 | BJ20: 228.99697 | BL20: 1811-1812 | BM20: 2.6944202 | BN20: -0.32185756 | BO20: 5.9738014 | BP20: -26.005903 | BQ20: 61.460411 | BR20: -6.7785228 | BT20: 1811-1812 | BU20: 29.245796 | BV20: 23.812325 | BW20: 18.599533 | BX20: 14.57486 | BY20: 16.746386 | BZ20: 28.087289 | CB20: 1812 | CC20: 6.1391661 | CD20: 0.82835805 | CE20: 0.021593496 | CF20: 1.6200161 | CG20: 0.26421742 | CH20: 0.43433017 | CI20: 3.745982 | CJ20: 13.053663 | CL20: 1812 | CM20: 4.6253751 | CN20: 0.76505873 | CO20: 0.022233035 | CP20: 1.2476281 | CQ20: 0.21636134 | CR20: 0.32868167 | CS20: 2.6209222 | CT20: 9.8262603 | CV20: 1812 | CW20: 82.014844 | CX20: 139.4372 | CY20: 10.111238 | CZ20: 50.427722 | DA20: 32.136044 | DB20: 314.12705 | DC20: 304.5849 | DD20: 35.089589 | DF20: 1812 | DG20: 1.4283267 | DH20: 1.3717757 | DI20: 1.4615891 | DJ20: 0.93347497 | DK20: 5.4700997 | DL20: 0.25656184 | DM20: 1.8977612 | DN20: 1.9229929 | DO20: 2.7585872 | DQ20: 1812 | DR20: 187.13169 | DS20: 328.9924 | DT20: 21.500037 | DU20: 50.427722 | DV20: 32.136044 | DW20: 620.1879 | DX20: 598.37178 | DY20: 59.175317 | EA20: 1812 | EB20: 0.95112633 | EC20: 0.94565578 | ED20: 0.954238 | EE20: 0.8834948 | EF20: 5.4700997 | EG20: 0.25656184 | EH20: 1.2542836 | EI20: 1.2698835 | EJ20: 1.7910065
... A56: 1847-1848 | B56: 4.0057329 | C56: 3.9947129 | D56: 4.0130271 | E56: 3.9984392 | F56: 3.9940458 | G56: 5.5534127 | H56: 5.6703348 | J56: 1848 | K56: 455.42312 | L56: 433.67992 | M56: 437.99683 | N56: 416.25363 | O56: 17.426297 | P56: 21.7432 | Q56: 267.41232 | R56: 722.83544 | S56: 701.09224 | U56: 1848 | V56: 134.75186 | W56: 10540.822 | X56: 4.7029536 | Y56: 128.31842 | Z56: 9556.082 | AA56: 3.1677437 | AB56: 3379716.7 | AC56: 0.81225892 | AE56: 1848 | AF56: 210.52688 | AG56: 53.708588 | AH56: 23.873948 | AI56: 23.53282 | AJ56: 33.980891 | AK56: 39.086055 | AL56: 26.78591 | AM56: 22.184834 | AN56: 433.67992 | AP56: 1847-1848 | AQ56: 3.3233023 | AR56: 3.5328787 | AS56: -5.1212252 | AT56: 16.432876 | AU56: 6.441607 | AV56: 1.4523349 | AW56: 11.720239 | AX56: 2.4348865 | AY56: 4.0057329 | BA56: 1848 | BB56: 398.27469 | BC56: 33.105695 | BD56: 19.366677 | BE56: 5.9971753 | BF56: 1.4007599 | BG56: 3.4930731 | BH56: 45.684134 | BI56: 51.899077 | BJ56: 455.42312 | BL56: 1847-1848 | BM56: 11.01038 | BN56: 5.8157182 | BO56: 2.4576436 | BP56: -18.95744 | BQ56: 15.4715 | BR56: 5.5534127 | BT56: 1847-1848 | BU56: -3.4029711 | BV56: -6.9282809 | BW56: 0.7271988 | BX56: -9.5782927 | BY56: -4.4742683 | BZ56: -4.0420153 | CB56: 1848 | CC56: 12.253255 | CD56: 3.6428624 | CE56: 0.056518529 | CF56: 4.6263103 | CG56: 1.4370888 | CH56: 1.0990201 | CI56: 7.1426296 | CJ56: 30.257685 | CL56: 1848 | CM56: 7.1449982 | CN56: 1.4026873 | CO56: 0.048881301 | CP56: 3.3028614 | CQ56: 0.31235157 | CR56: 0.68941647 | CS56: 4.5251002 | CT56: 17.426297 | CV56: 1848 | CW56: 143.98512 | CX56: 227.10504 | CY56: 25.146034 | CZ56: 105.49682 | DA56: 83.746839 | DB56: 585.47984 | DC56: 564.75177 | DD56: 77.13674 | DF56: 1848 | DG56: 1.4709126 | DH56: 1.8179166 | DI56: 1.2509113 | DJ56: 9.8487047 | DK56: -6.1529636 | DL56: 4.1709911 | DM56: 0.84554064 | DN56: 0.80374975 | DO56: 6.1473028 | DQ56: 1848 | DR56: 312.31696 | DS56: 526.5577 | DT56: 48.869491 | DU56: 105.49682 | DV56: 83.746839 | DW56: 1076.9878 | DX56: 1035.0122 | DY56: 114.2674 | EA56: 1848 | EB56: 1.0281147 | EC56: 1.2763849 | ED56: 0.88085834 | EE56: 7.1075668 | EF56: -6.1529636 | EG56: 4.1709911 | EH56: 0.84565595 | EI56: 0.81510855 | EJ56: 4.3449427
A57: 1848-1849 | B57: 5.3385475 | C57: 5.2790991 | D57: 5.5283989 | E57: 5.1490377 | F57: 5.3250286 | G57: 7.1614753 | H57: 7.3769286 | J57: 1849 | K57: 448.23743 | L57: 426.80545 | M57: 429.96161 | N57: 408.52963 | O57: 18.275817 | P57: 21.431976 | Q57: 261.01103 | R57: 709.24846 | S57: 687.81648 | U57: 1849 | V57: 131.09042 | W57: 11164.937 | X57: 5.9209348 | Y57: 124.82247 | Z57: 9949.7075 | AA57: 4.1191099 | AB57: 3419299.8 | AC57: 1.1711948 | AE57: 1849 | AF57: 201.33332 | AG57: 55.760191 | AH57: 22.955006 | AI57: 27.880122 | AJ57: 31.288645 | AK57: 38.79401 | AL57: 25.735562 | AM57: 23.058591 | AN57: 426.80545 | AP57: 1848-1849 | AQ57: 7.1004072 | AR57: 5.5697528 | AS57: -1.5120573 | AT57: 31.781995 | AU57: -3.8528329 | AV57: 0.89273898 | AW57: -3.6496901 | AX57: 1.9937362 | AY57: 5.3385475 | BA57: 1849 | BB57: 392.44931 | BC57: 32.692519 | BD57: 19.593936 | BE57: 5.0986979 | BF57: 1.8847655 | BG57: 2.6170332 | BH57: 51.703028 | BI57: 57.801862 | BJ57: 448.23743 | BL57: 1848-1849 | BM57: 8.0884808 | BN57: -1.8370505 | BO57: -4.9157213 | BP57: 13.379277 | BQ57: 6.5886343 | BR57: 7.1614753 | BT57: 1848-1849 | BU57: -8.8364032 | BV57: 0.60002204 | BW57: 1.4741994 | BX57: -0.1801539 | BY57: 4.4891726 | BZ57: -8.1552458 | CB57: 1849 | CC57: 12.054294 | CD57: 3.5455525 | CE57: 0.064998502 | CF57: 4.3896818 | CG57: 1.1771374 | CH57: 1.1812113 | CI57: 6.7815576 | CJ57: 29.194433 | CL57: 1849 | CM57: 7.4891416 | CN57: 1.474145 | CO57: 0.050449815 | CP57: 3.495132 | CQ57: 0.32316268 | CR57: 0.72228952 | CS57: 4.7214968 | CT57: 18.275817 | CV57: 1849 | CW57: 151.09048 | CX57: 236.98508 | CY57: 28.066783 | CZ57: 99.005635 | DA57: 84.726648 | DB57: 599.87462 | DC57: 578.10647 | DD57: 81.011832 | DF57: 1849 | DG57: 1.3138997 | DH57: 1.3634617 | DI57: 1.2823013 | DJ57: 4.6981321 | DK57: 9.3107278 | DL57: 3.0887959 | DM57: 2.9547594 | DN57: 2.9870487 | DO57: 1.2588181 | DQ57: 1849 | DR57: 325.98608 | DS57: 547.45702 | DT57: 53.177918 | DU57: 99.005635 | DV57: 84.726648 | DW57: 1110.3533 | DX57: 1066.435 | DY57: 119.4494 | EA57: 1849 | EB57: 0.97034539 | EC57: 1.0766091 | ED57: 0.90707012 | EE57: 4.495075 | EF57: 9.3107278 | EG57: 3.0887959 | EH57: 1.9906862 | EI57: 2.003654 | EJ57: 1.0873896 | HM57: comhn | HV57: nmxhn
A58: 1849-1850 | B58: 2.3544936 | C58: 2.328426 | D58: 2.3322801 | E58: 2.376712 | F58: 2.3994695 | G58: 1.7214554 | H58: 1.681628 | J58: 1850 | K58: 460.80249 | L58: 438.78694 | M58: 441.98067 | N58: 419.96512 | O58: 18.821821 | P58: 22.015543 | Q58: 277.87156 | R58: 738.67405 | S58: 716.65851 | U58: 1850 | V58: 133.10866 | W58: 11217.537 | X58: 0.47111893 | Y58: 126.74919 | Z58: 10058.794 | AA58: 1.096376 | AB58: 3461852 | AC58: 1.2444735 | AE58: 1850 | AF58: 202.50134 | AG58: 57.997172 | AH58: 26.77819 | AI58: 25.69097 | AJ58: 34.252126 | AK58: 41.101905 | AL58: 26.796419 | AM58: 23.668829 | AN58: 438.78694 | AP58: 1849-1850 | AQ58: 1.2362402 | AR58: 4.6196023 | AS58: 13.075992 | AT58: -2.4475549 | AU58: 7.3773764 | AV58: 1.3597724 | AW58: -2.2664705 | AX58: 1.590435 | AY58: 2.3544936 | BA58: 1850 | BB58: 397.12495 | BC58: 33.98621 | BD58: 23.201929 | BE58: 5.9979814 | BF58: 0.69594012 | BG58: 3.0919511 | BH58: 51.843263 | BI58: 55.139733 | BJ58: 460.80249 | BL58: 1849-1850 | BM58: -0.55878781 | BN58: 0.67515237 | BO58: 13.440926 | BP58: -0.43670083 | BQ58: -10.172287 | BR58: 1.7214554 | BT58: 1849-1850 | BU58: 1.7600214 | BV58: 3.2599851 | BW58: -0.39444335 | BX58: 0.71103798 | BY58: 6.1970589 | BZ58: 1.0634529 | CB58: 1850 | CC58: 12.096584 | CD58: 3.8992478 | CE58: 0.072316838 | CF58: 4.9590732 | CG58: 1.314204 | CH58: 1.2221741 | CI58: 9.424202 | CJ58: 32.987802 | CL58: 1850 | CM58: 7.7025119 | CN58: 1.5553393 | CO58: 0.054846415 | CP58: 3.6018115 | CQ58: 0.32424001 | CR58: 0.73959502 | CS58: 4.8434769 | CT58: 18.821821 | CV58: 1850 | CW58: 153.15054 | CX58: 240.02394 | CY58: 29.823884 | CZ58: 90.186483 | DA58: 87.499746 | DB58: 600.6846 | DC58: 578.43485 | DD58: 82.30722 | DF58: 1850 | DG58: 2.1479253 | DH58: 2.9909951 | DI58: 1.6099932 | DJ58: 6.4766976 | DK58: -10.541796 | DL58: 3.5336687 | DM58: 0.65208355 | DN58: 0.5940072 | DO58: 4.0766876 | DQ58: 1850 | DR58: 329.49567 | DS58: 552.42284 | DT58: 56.412345 | DU58: 90.186483 | DV58: 87.499746 | DW58: 1116.0171 | DX58: 1071.3171 | DY58: 121.1486 | EA58: 1850 | EB58: 1.3632329 | EC58: 1.8615463 | ED58: 1.0660111 | EE58: 5.550737 | EF58: -10.541796 | EG58: 3.5336687 | EH58: 0.77935087 | EI58: 0.74002061 | EJ58: 3.0352899 | EL58: 1850 | EM58: 1105486.2 | EN58: 130821.84 | EO58: 12974.907 | EP58: 9055.4971 | EQ58: 15764.214 | ER58: 132871.75 | ES58: 56700.55 | ET58: 845.31983 | EU58: 1464520.3 | EV58: 1407819.7 | EX58: 1850 | EY58: 829430.87 | EZ58: 90105.148 | FA58: 9781.5403 | FB58: 9055.4971 | FC58: 7276.3281 | FD58: 129463.07 | FE58: 56700.55 | FF58: 583.67247 | FG58: 1132396.7 | FH58: 1075696.1 | FJ58: 1850 | FK58: 276055.36 | FL58: 40716.688 | FM58: 3193.3671 | FN58: 0 | FO58: 8487.8862 | FP58: 3408.6779 | FQ58: 261.64736 | FR58: 332123.63 | FS58: 536377.87 | HC58: 1850 | HD58: 136.90466 | HE58: 25.636458 | HF58: 3.7482563 | HG58: 5.267902 | HH58: 39.797908 | HI58: 26.056824 | HJ58: 0.43327739 | HK58: 237.84529 | HL58: 211.78847 | HN58: 1850 | HO58: 57.378371 | HP58: 12.452796 | HQ58: 1.3709441 | HR58: 0 | HS58: 8.2111323 | HT58: 0.22489113 | HU58: 79.638135 | HW58: 1850 | HX58: 24.1973 | HY58: 19.907917 | HZ58: 21.658989 | IA58: 4.4440679 | IB58: 27.34499 | IC58: 0.73959502 | ID58: 23.010661 | IE58: 121.30352 | IF58: 120.56393 | IH58: 1850 | II58: 134.71704 | IJ58: 52.053945 | IK58: 25.411682 | IL58: 138.23614 | IM58: 48.183085 | IN58: 23.522007
A59: 1850-1851 | B59: -0.068891339 | C59: -0.082539223 | D59: 0.030170725 | E59: -0.1678553 | F59: 0.026437468 | G59: -0.84337849 | H59: -1.0481385 | J59: 1851 | K59: 476.45671 | L59: 453.739 | M59: 457.18985 | N59: 434.47214 | O59: 19.266857 | P59: 22.717712 | Q59: 293.43635 | R59: 769.89306 | S59: 747.17535 | U59: 1851 | V59: 136.1479 | W59: 11003.104 | X59: -1.911585 | Y59: 129.65629 | Z59: 9943.5761 | AA59: -1.1454414 | AB59: 3499552.5 | AC59: 1.0890242 | AE59: 1851 | AF59: 201.64608 | AG59: 60.722753 | AH59: 34.830625 | AI59: 26.9978 | AJ59: 34.268419 | AK59: 42.453766 | AL59: 28.608338 | AM59: 24.211213 | AN59: 453.739 | AP59: 1850-1851 | AQ59: -4.8681728 | AR59: 3.9055635 | AS59: 30.082444 | AT59: 4.8975767 | AU59: -3.6209698 | AV59: -1.8557848 | AW59: -1.0840447 | AX59: 2.2915521 | AY59: -0.068891339 | BA59: 1851 | BB59: 405.6582 | BC59: 36.138324 | BD59: 30.941957 | BE59: 6.3209345 | BF59: -0.24748023 | BG59: 3.4017246 | BH59: 56.964652 | BI59: 62.721602 | BJ59: 476.45671 | BL59: 1850-1851 | BM59: -1.7219927 | BN59: 0.013447393 | BO59: 23.976538 | BP59: 9.3919155 | BQ59: 17.996069 | BR59: -0.84337849 | BT59: 1850-1851 | BU59: 3.938572 | BV59: 6.3180179 | BW59: -1.1736717 | BX59: 0.44490017 | BY59: -3.5982447 | BZ59: 4.2766114 | CB59: 1851 | CC59: 16.823828 | CD59: 3.8993054 | CE59: 0.014329891 | CF59: 4.9224407 | CG59: 1.307897 | CH59: 1.3020025 | CI59: 12.147333 | CJ59: 40.417136 | CL59: 1851 | CM59: 7.9695481 | CN59: 1.579527 | CO59: 0.051267634 | CP59: 3.6678285 | CQ59: 0.31758776 | CR59: 0.74210424 | CS59: 4.9389933 | CT59: 19.266857 | CV59: 1851 | CW59: 154.60788 | CX59: 239.05884 | CY59: 31.564149 | CZ59: 80.679208 | DA59: 91.976318 | DB59: 597.88639 | DC59: 575.60293 | DD59: 85.982908 | DF59: 1851 | DG59: 4.0568176 | DH59: 4.6623367 | DI59: 3.6652068 | DJ59: 6.4067441 | DK59: 8.6139339 | DL59: 3.6984788 | DM59: 4.7254254 | DN59: 4.8113958 | DO59: 1.7256697 | DQ59: 1851 | DR59: 328.98326 | DS59: 547.25605 | DT59: 59.187531 | DU59: 80.679208 | DV59: 91.976318 | DW59: 1108.0824 | DX59: 1063.5094 | DY59: 124.36817 | EA59: 1851 | EB59: 2.2721413 | EC59: 2.705679 | ED59: 2.0115199 | EE59: 5.622976 | EF59: 8.6139339 | EG59: 3.6984788 | EH59: 3.0194505 | EI59: 3.065749 | EJ59: 1.4463924 | EL59: 1851 | EM59: 1102721.1 | EN59: 131121.84 | EO59: 16068.24 | EP59: 9145.9775 | EQ59: 15867.955 | ER59: 129716.45 | ES59: 55335.458 | ET59: 858.38249 | EU59: 1460835.4 | EV59: 1405500 | EX59: 1851 | EY59: 825732.05 | EZ59: 90474.133 | FA59: 12654.115 | FB59: 9145.9775 | FC59: 7117.1415 | FD59: 126309.31 | FE59: 55335.458 | FF59: 592.69191 | FG59: 1127360.9 | FH59: 1072025.4 | FJ59: 1851 | FK59: 276989.07 | FL59: 40647.712 | FM59: 3414.125 | FN59: 0 | FO59: 8750.8135 | FP59: 3407.1412 | FQ59: 265.69058 | FR59: 333474.55 | FS59: 540760.61 | HC59: 1851 | HD59: 136.29414 | HE59: 25.741441 | HF59: 4.849018 | HG59: 5.3205377 | HH59: 40.16885 | HI59: 27.866233 | HJ59: 0.44863367 | HK59: 240.68886 | HL59: 212.82262 | HN59: 1851 | HO59: 57.572444 | HP59: 12.4317 | HQ59: 1.4657177 | HR59: 0 | HS59: 8.7687424 | HT59: 0.23286176 | HU59: 80.471466 | HW59: 1851 | HX59: 23.967495 | HY59: 22.549613 | HZ59: 28.515889 | IA59: 5.4892625 | IB59: 27.784593 | IC59: 0.74210424 | ID59: 23.529718 | IE59: 132.57867 | IF59: 131.83657 | IH59: 1851 | II59: 134.41635 | IJ59: 58.856724 | IK59: 27.563755 | IL59: 137.81947 | IM59: 54.934137 | IN59: 25.726731 | IO59: -3.7893266
A60: 1851-1852 | B60: -1.4297059 | C60: -1.460167 | D60: -1.3287676 | E60: -1.5305408 | F60: -1.4091193 | G60: -1.8588224 | H60: -2.099301 | J60: 1852 | K60: 486.94005 | L60: 463.66975 | M60: 466.94457 | N60: 443.67427 | O60: 19.995479 | P60: 23.2703 | Q60: 297.79721 | R60: 784.73726 | S60: 761.46696 | U60: 1852 | V60: 138.00168 | W60: 10709.961 | X60: -2.6641858 | Y60: 131.40674 | Z60: 9720.9801 | AA60: -2.2385907 | AB60: 3528508 | AC60: 0.82740712 | AE60: 1852 | AF60: 207.55766 | AG60: 61.03127 | AH60: 36.4279 | AI60: 25.399685 | AJ60: 35.99025 | AK60: 43.947224 | AL60: 28.198174 | AM60: 25.117581 | AN60: 463.66975 | AP60: 1851-1852 | AQ60: -3.104225 | AR60: 0.41760177 | AS60: 2.292215 | AT60: -13.829674 | AU60: 2.8301345 | AV60: 1.5378039 | AW60: 0.53075922 | AX60: 3.7435879 | AY60: -1.4297059 | BA60: 1852 | BB60: 412.54614 | BC60: 35.974903 | BD60: 31.119744 | BE60: 6.4286803 | BF60: 0.094513769 | BG60: 2.2958774 | BH60: 56.666232 | BI60: 58.18604 | BJ60: 486.94005 | BL60: 1851-1852 | BM60: -2.4554688 | BN60: 1.2866601 | BO60: -1.1015914 | BP60: 0.19633411 | BQ60: -1.6474163 | BR60: -1.8588224 | BT60: 1851-1852 | BU60: 4.2579889 | BV60: -1.7167814 | BW60: -0.082780125 | BX60: -0.71879242 | BY60: -5.6773735 | BZ60: 4.135974 | CB60: 1852 | CC60: 17.957819 | CD60: 3.5125043 | CE60: 0.088130901 | CF60: 5.3432806 | CG60: 1.0788044 | CH60: 1.356399 | CI60: 10.601878 | CJ60: 39.938816 | CL60: 1852 | CM60: 8.3735152 | CN60: 1.6199239 | CO60: 0.05251646 | CP60: 3.7795807 | CQ60: 0.31781936 | CR60: 0.75949926 | CS60: 5.0926239 | CT60: 19.995479 | CV60: 1852 | CW60: 161.81621 | CX60: 247.82084 | CY60: 33.314943 | CZ60: 82.760591 | DA60: 95.715866 | DB60: 621.42846 | DC60: 598.59479 | DD60: 87.586904 | DF60: 1852 | DG60: 3.8161705 | DH60: 3.4046366 | DI60: 4.0848842 | DJ60: 5.7467815 | DK60: 1.1565253 | DL60: 2.3986383 | DM60: 3.3872691 | DN60: 3.4174657 | DO60: 2.6929291 | DQ60: 1852 | DR60: 337.88449 | DS60: 558.26422 | DT60: 62.00023 | DU60: 82.760591 | DV60: 95.715866 | DW60: 1136.6254 | DX60: 1091.2175 | DY60: 126.22576 | EA60: 1852 | EB60: 2.2325517 | EC60: 2.1685253 | ED60: 2.2713032 | EE60: 5.3590886 | EF60: 1.1565253 | EG60: 2.3986383 | EH60: 2.347848 | EI60: 2.3628905 | EJ60: 2.1243859 | EL60: 1852 | EM60: 1103603 | EN60: 133136.59 | EO60: 15616.499 | EP60: 9483.993 | EQ60: 16492.698 | ER60: 130948.11 | ES60: 55977.257 | ET60: 871.647 | EU60: 1466129.8 | EV60: 1410152.6 | EX60: 1852 | EY60: 825677.08 | EZ60: 91382.117 | FA60: 12139.054 | FB60: 9483.993 | FC60: 7348.212 | FD60: 127466.36 | FE60: 55977.257 | FF60: 601.85073 | FG60: 1130075.9 | FH60: 1074098.7 | FJ60: 1852 | FK60: 277925.94 | FL60: 41754.471 | FM60: 3477.445 | FN60: 0 | FO60: 9144.4861 | FP60: 3481.7536 | FQ60: 269.79627 | FR60: 336053.9 | FS60: 545179.15 | HC60: 1852 | HD60: 138.07829 | HE60: 26.34188 | HF60: 4.7128543 | HG60: 5.5897676 | HH60: 41.807848 | HI60: 27.438675 | HJ60: 0.47198317 | HK60: 244.4413 | HL60: 217.00263 | HN60: 1852 | HO60: 58.527268 | HP60: 12.938221 | HQ60: 1.512545 | HR60: 0 | HS60: 9.1203769 | HT60: 0.24498124 | HU60: 82.343392 | HW60: 1852 | HX60: 25.426101 | HY60: 21.751169 | HZ60: 30.202501 | IA60: 5.3359174 | IB60: 29.00925 | IC60: 0.75949926 | ID60: 24.400617 | IE60: 136.88506 | IF60: 136.12556 | IH60: 1852 | II60: 136.23171 | IJ60: 55.159921 | IK60: 26.095516 | IL60: 139.75294 | IM60: 51.250494 | IN60: 24.246011 | IO60: -2.8220374
A61: 1852-1853 | B61: 1.5381043 | C61: 1.4902342 | D61: 1.5812684 | E61: 1.4949585 | F61: 1.6613058 | G61: 1.9883145 | H61: 1.9129096 | J61: 1853 | K61: 511.95801 | L61: 487.54973 | M61: 490.24103 | N61: 465.83275 | O61: 21.716979 | P61: 24.408281 | Q61: 316.669 | R61: 828.62701 | S61: 804.21873 | U61: 1853 | V61: 144.13865 | W61: 10851.144 | X61: 1.3182392 | Y61: 137.26665 | Z61: 9805.6486 | AA61: 0.87098695 | AB61: 3551844 | AC61: 0.66135703 | AE61: 1853 | AF61: 211.5318 | AG61: 63.287916 | AH61: 40.74332 | AI61: 30.84238 | AJ61: 36.48241 | AK61: 46.986753 | AL61: 30.782407 | AM61: 26.892749 | AN61: 487.54973 | AP61: 1852-1853 | AQ61: 1.2602318 | AR61: 1.5591801 | AS61: 6.8258653 | AT61: -2.3216195 | AU61: 6.9133503 | AV61: 0.58604192 | AW61: -6.2647898 | AX61: 3.861819 | AY61: 1.5381043 | BA61: 1853 | BB61: 410.1206 | BC61: 39.615059 | BD61: 35.109642 | BE61: 6.0764248 | BF61: 0.60796504 | BG61: 2.9765262 | BH61: 74.453662 | BI61: 57.001867 | BJ61: 511.95801 | BL61: 1852-1853 | BM61: -0.69761154 | BN61: -2.8441438 | BO61: 8.035752 | BP61: 7.8125824 | BQ61: -9.2944483 | BR61: 1.9883145 | BT61: 1852-1853 | BU61: 0.11043915 | BV61: 13.342214 | BW61: 3.7599673 | BX61: 21.868729 | BY61: 8.0031476 | BZ61: 3.0880766 | CB61: 1853 | CC61: 20.898824 | CD61: 4.0201137 | CE61: 0.10291942 | CF61: 5.1392046 | CG61: 1.3153748 | CH61: 1.5578849 | CI61: 11.736236 | CJ61: 44.770558 | CL61: 1853 | CM61: 9.2033645 | CN61: 1.7307212 | CO61: 0.058851958 | CP61: 4.0501126 | CQ61: 0.33512516 | CR61: 0.81915378 | CS61: 5.5196499 | CT61: 21.716979 | CV61: 1853 | CW61: 175.77625 | CX61: 270.97151 | CY61: 36.468135 | CZ61: 66.974191 | DA61: 96.464812 | DB61: 646.6549 | DC61: 622.05569 | DD61: 90.252599 | DF61: 1853 | DG61: 4.0837247 | DH61: 3.5366476 | DI61: 4.4386077 | DJ61: 3.344775 | DK61: -0.88622704 | DL61: 3.0856083 | DM61: 3.2539416 | DN61: 3.2637425 | DO61: 1.0909901 | DQ61: 1853 | DR61: 362.64653 | DS61: 599.77965 | DT61: 67.614988 | DU61: 66.974191 | DV61: 96.464812 | DW61: 1193.4802 | DX61: 1144.8587 | DY61: 131.09493 | EA61: 1853 | EB61: 2.4268306 | EC61: 2.280175 | ED61: 2.5155035 | EE61: 4.027548 | EF61: -0.88622704 | EG61: 3.0856083 | EH61: 2.3298869 | EI61: 2.334723 | EJ61: 1.0187232 | EL61: 1853 | EM61: 1113419 | EN61: 135097.3 | EO61: 15895.153 | EP61: 9468.2446 | EQ61: 16348.438 | ER61: 132139.93 | ES61: 52841.573 | ET61: 885.11649 | EU61: 1476094.8 | EV61: 1423253.2 | EX61: 1853 | EY61: 834553.04 | EZ61: 93121.839 | FA61: 12320.333 | FB61: 9468.2446 | FC61: 7060.7257 | FD61: 128703.38 | FE61: 52841.573 | FF61: 611.15107 | FG61: 1138680.3 | FH61: 1085838.7 | FJ61: 1853 | FK61: 278865.98 | FL61: 41975.463 | FM61: 3574.8206 | FN61: 0 | FO61: 9287.7125 | FP61: 3436.551 | FQ61: 273.96541 | FR61: 337414.5 | FS61: 549633.79 | HC61: 1853 | HD61: 143.18763 | HE61: 27.540604 | HF61: 4.9074735 | HG61: 5.7254334 | HH61: 43.751107 | HI61: 29.963253 | HJ61: 0.49177956 | HK61: 255.56728 | HL61: 225.60402 | HN61: 1853 | HO61: 60.250558 | HP61: 13.344535 | HQ61: 1.5952864 | HR61: 0 | HS61: 9.8180276 | HT61: 0.25525648 | HU61: 85.263663 | HW61: 1853 | HX61: 20.668613 | HY61: 22.402777 | HZ61: 34.24056 | IA61: 12.541947 | IB61: 29.900029 | IC61: 0.81915378 | ID61: 26.145713 | IE61: 146.71879 | IF61: 145.89964 | IH61: 1853 | II61: 135.37247 | IJ61: 54.573973 | IK61: 26.080677 | IL61: 138.98034 | IM61: 50.561297 | IN61: 24.163035 | IO61: 2.4842199
A62: 1853-1854 | B62: 2.269227 | C62: 2.2450704 | D62: 2.3697857 | E62: 2.1687671 | F62: 2.2204596 | G62: 1.9256451 | H62: 1.8563283 | J62: 1854 | K62: 580.41841 | L62: 552.49405 | M62: 556.08345 | N62: 528.15909 | O62: 24.33496 | P62: 27.924359 | Q62: 349.09493 | R62: 929.51334 | S62: 901.58898 | U62: 1854 | V62: 161.87258 | W62: 10955.822 | X62: 0.96467682 | Y62: 154.08477 | Z62: 9933.6142 | AA62: 1.3050195 | AB62: 3585650 | AC62: 0.95178658 | AE62: 1854 | AF62: 257.19431 | AG62: 70.936994 | AH62: 44.123118 | AI62: 29.210444 | AJ62: 42.654406 | AK62: 47.985526 | AL62: 29.928166 | AM62: 30.461093 | AN62: 552.49405 | AP62: 1853-1854 | AQ62: 3.1049131 | AR62: 3.3079084 | AS62: -1.7575301 | AT62: 2.5173878 | AU62: -0.095170154 | AV62: 0.68231881 | AW62: 3.5259508 | AX62: 3.3655163 | AY62: 2.269227 | BA62: 1854 | BB62: 475.55847 | BC62: 40.097866 | BD62: 37.484764 | BE62: 6.8736708 | BF62: 1.2802434 | BG62: 3.8907582 | BH62: 87.668303 | BI62: 72.435659 | BJ62: 580.41841 | BL62: 1853-1854 | BM62: 1.6056045 | BN62: 5.6811998 | BO62: 0.56514079 | BP62: 20.507991 | BQ62: 24.578862 | BR62: 1.9256451 | BT62: 1853-1854 | BU62: 14.123391 | BV62: -4.2225607 | BW62: 10.007782 | BX62: -2.2896219 | BY62: 2.0044163 | BZ62: 11.230366 | CB62: 1854 | CC62: 22.693123 | CD62: 4.9593026 | CE62: 0.10479898 | CF62: 6.5812355 | CG62: 1.7409812 | CH62: 1.6707201 | CI62: 11.779274 | CJ62: 49.529436 | CL62: 1854 | CM62: 10.396383 | CN62: 1.8909996 | CO62: 0.064170648 | CP62: 4.4916985 | CQ62: 0.37160345 | CR62: 0.91479775 | CS62: 6.2053066 | CT62: 24.33496 | CV62: 1854 | CW62: 199.49215 | CX62: 310.2103 | CY62: 39.016873 | CZ62: 116.16613 | DA62: 111.21146 | DB62: 776.09692 | DC62: 748.37624 | DD62: 100.82807 | DF62: 1854 | DG62: 3.6050289 | DH62: 2.7940788 | DI62: 4.1265403 | DJ62: 4.207499 | DK62: -4.4061663 | DL62: 3.4985226 | DM62: 2.3789358 | DN62: 2.3660481 | DO62: 3.0798301 | DQ62: 1854 | DR62: 406.58046 | DS62: 673.98897 | DT62: 72.856662 | DU62: 116.16613 | DV62: 111.21146 | DW62: 1380.8037 | DX62: 1326.4329 | DY62: 145.60607 | EA62: 1854 | EB62: 2.266637 | EC62: 1.9548245 | ED62: 2.4547364 | EE62: 4.4914066 | EF62: -4.4061663 | EG62: 3.4985226 | EH62: 1.8950091 | EI62: 1.8865991 | EJ62: 2.378118 | EL62: 1854 | EM62: 1126990.5 | EN62: 140235.82 | EO62: 14837.118 | EP62: 9869.0726 | EQ62: 16969.965 | ER62: 131772.29 | ES62: 56524.505 | ET62: 898.79412 | EU62: 1498098 | EV62: 1441573.5 | EX62: 1854 | EY62: 847181.25 | EZ62: 97742.554 | FA62: 11225.274 | FB62: 9869.0726 | FC62: 7385.6896 | FD62: 128274.78 | FE62: 56524.505 | FF62: 620.59514 | FG62: 1158823.7 | FH62: 1102299.2 | FJ62: 1854 | FK62: 279809.2 | FL62: 42493.269 | FM62: 3611.844 | FN62: 0 | FO62: 9584.2757 | FP62: 3497.5074 | FQ62: 278.19898 | FR62: 339274.3 | FS62: 554124.84 | HC62: 1854 | HD62: 154.55394 | HE62: 30.736739 | HF62: 4.754279 | HG62: 6.3455232 | HH62: 45.625701 | HI62: 29.013368 | HJ62: 0.52718944 | HK62: 271.55674 | HL62: 242.54337 | HN62: 1854 | HO62: 64.28057 | HP62: 14.364161 | HQ62: 1.7138215 | HR62: 0 | HS62: 10.255656 | HT62: 0.27363586 | HU62: 90.887845 | HW62: 1854 | HX62: 52.331796 | HY62: 25.836094 | HZ62: 37.655017 | IA62: 8.8929207 | IB62: 34.758575 | IC62: 0.91479775 | ID62: 29.660268 | IE62: 190.04947 | IF62: 189.13467 | IH62: 1854 | II62: 134.92739 | IJ62: 57.066887 | IK62: 26.927711 | IL62: 138.4304 | IM62: 53.092276 | IN62: 25.052241 | IO62: -6.8296927
A63: 1854-1855 | B63: 7.0193989 | C63: 6.870716 | D63: 7.1865323 | E63: 6.8525262 | F63: 7.0751275 | G63: 6.7588972 | H63: 6.8372262 | J63: 1855 | K63: 655.39756 | L63: 623.78447 | M63: 624.88853 | N63: 593.27543 | O63: 30.509037 | P63: 31.613092 | Q63: 391.9988 | R63: 1047.3964 | S63: 1015.7833 | U63: 1855 | V63: 180.82276 | W63: 11570.849 | X63: 5.6136987 | Y63: 172.10078 | Z63: 10516.857 | AA63: 5.8714061 | AB63: 3624530.2 | AC63: 1.0843276 | AE63: 1855 | AF63: 271.17284 | AG63: 87.627311 | AH63: 57.623716 | AI63: 29.395022 | AJ63: 51.934599 | AK63: 57.336374 | AL63: 32.189046 | AM63: 36.505562 | AN63: 623.78447 | AP63: 1854-1855 | AQ63: 7.7030649 | AR63: 12.58604 | AS63: 6.5574239 | AT63: 10.751895 | AU63: 10.827033 | AV63: 3.0815154 | AW63: -8.351183 | AX63: 2.8030325 | AY63: 7.0193989 | BA63: 1855 | BB63: 543.12368 | BC63: 41.82586 | BD63: 49.239252 | BE63: 12.992883 | BF63: 3.0638972 | BG63: 6.4215886 | BH63: 104.60086 | BI63: 105.87046 | BJ63: 655.39756 | BL63: 1854-1855 | BM63: 11.177627 | BN63: -8.2448106 | BO63: 22.4809 | BP63: 5.6110782 | BQ63: 36.59332 | BR63: 6.7588972 | BT63: 1854-1855 | BU63: 2.7252999 | BV63: 13.682336 | BW63: 18.220861 | BX63: 12.975215 | BY63: 7.0022504 | BZ63: 5.7692835 | CB63: 1855 | CC63: 30.301408 | CD63: 8.3411428 | CE63: 0.12872242 | CF63: 8.7032595 | CG63: 2.9255858 | CH63: 1.7089471 | CI63: 19.608556 | CJ63: 71.717621 | CL63: 1855 | CM63: 13.096528 | CN63: 2.3477612 | CO63: 0.076896617 | CP63: 5.5785548 | CQ63: 0.4617808 | CR63: 1.1194303 | CS63: 7.8280849 | CT63: 30.509037 | CV63: 1855 | CW63: 248.23793 | CX63: 391.01363 | CY63: 46.006324 | CZ63: 142.77556 | DA63: 126.58483 | DB63: 954.61827 | DC63: 920.20912 | DD63: 117.28551 | DF63: 1855 | DG63: 3.9579851 | DH63: 4.7456368 | DI63: 3.4579386 | DJ63: 13.941396 | DK63: 1.9517883 | DL63: 5.0729528 | DM63: 4.2742117 | DN63: 4.370018 | DO63: 2.6175622 | DQ63: 1855 | DR63: 501.79753 | DS63: 835.90912 | DT63: 86.188016 | DU63: 142.77556 | DV63: 126.58483 | DW63: 1693.2551 | DX63: 1626.1792 | DY63: 171.49093 | EA63: 1855 | EB63: 2.4967137 | EC63: 2.9759127 | ED63: 2.2090497 | EE63: 10.121902 | EF63: 1.9517883 | EG63: 5.0729528 | EH63: 3.0231663 | EI63: 3.082314 | EJ63: 2.0983201 | EL63: 1855 | EM63: 1150861.6 | EN63: 146014.1 | EO63: 15012.381 | EP63: 10454.284 | EQ63: 17518.054 | ER63: 135458.64 | ES63: 50213.172 | ET63: 912.68311 | EU63: 1526444.9 | EV63: 1476231.7 | EX63: 1855 | EY63: 870105.97 | EZ63: 103020.42 | FA63: 11303.808 | FB63: 10454.284 | FC63: 7611.7259 | FD63: 131899.44 | FE63: 50213.172 | FF63: 630.18515 | FG63: 1185239 | FH63: 1135025.8 | FJ63: 1855 | FK63: 280755.61 | FL63: 42993.689 | FM63: 3708.5724 | FN63: 0 | FO63: 9906.3278 | FP63: 3559.2031 | FQ63: 282.49796 | FR63: 341205.9 | FS63: 558652.58 | HC63: 1855 | HD63: 192.75106 | HE63: 39.338545 | HF63: 5.8134427 | HG63: 8.1621819 | HH63: 53.788814 | HI63: 31.069616 | HJ63: 0.59734172 | HK63: 331.521 | HL63: 300.45139 | HN63: 1855 | HO63: 78.318986 | HP63: 17.647603 | HQ63: 2.1368018 | HR63: 0 | HS63: 13.040579 | HT63: 0.31004816 | HU63: 111.45402 | HW63: 1855 | HX63: 15.333792 | HY63: 30.641163 | HZ63: 49.673471 | IA63: 6.0018396 | IB63: 42.44158 | IC63: 1.1194303 | ID63: 35.598173 | IE63: 180.80945 | IF63: 179.69002 | IH63: 1855 | II63: 127.05633 | IJ63: 53.555053 | IK63: 27.449853 | IL63: 130.37215 | IM63: 49.649613 | IN63: 25.448105 | IO63: 18.207074
A64: 1855-1856 | B64: -1.0581467 | C64: -1.1594328 | D64: -0.81693597 | E64: -1.2987708 | F64: -0.90293447 | G64: 0.43233276 | H64: 0.15878806 | J64: 1856 | K64: 742.28873 | L64: 706.29641 | M64: 707.52567 | N64: 671.53335 | O64: 34.763063 | P64: 35.992317 | Q64: 451.17927 | R64: 1193.468 | S64: 1157.4757 | U64: 1856 | V64: 202.97947 | W64: 11517.806 | X64: -0.45842164 | Y64: 193.13734 | Z64: 10313.284 | AA64: -1.9356818 | AB64: 3656964.5 | AC64: 0.89485662 | AE64: 1856 | AF64: 317.88717 | AG64: 92.951507 | AH64: 63.766059 | AI64: 32.499736 | AJ64: 61.241553 | AK64: 63.327368 | AL64: 32.749831 | AM64: 41.873191 | AN64: 706.29641 | AP64: 1855-1856 | AQ64: -5.6518401 | AR64: 1.7482043 | AS64: 2.0125546 | AT64: -2.2939539 | AU64: 10.449307 | AV64: 2.4199055 | AW64: -1.4864683 | AX64: 3.6868622 | AY64: -1.0581467 | BA64: 1856 | BB64: 672.64349 | BC64: 42.340631 | BD64: 55.547972 | BE64: 17.701274 | BF64: -0.46116051 | BG64: 9.2547155 | BH64: 97.365846 | BI64: 152.10404 | BJ64: 742.28873 | BL64: 1855-1856 | BM64: 8.0413475 | BN64: -2.0393027 | BO64: 7.14697 | BP64: -5.9924013 | BQ64: 38.952661 | BR64: 0.43233276 | BT64: 1855-1856 | BU64: 14.629452 | BV64: 3.3381237 | BW64: 6.7664271 | BX64: -0.98330422 | BY64: 3.394892 | BZ64: 12.770238 | CB64: 1856 | CC64: 27.389627 | CD64: 11.839913 | CE64: 0.12929128 | CF64: 13.19138 | CG64: 3.9883711 | CH64: 1.7285233 | CI64: 23.775695 | CJ64: 82.042801 | CL64: 1856 | CM64: 14.759995 | CN64: 2.8215084 | CO64: 0.086218614 | CP64: 6.5116544 | CQ64: 0.50564472 | CR64: 1.2240059 | CS64: 8.8540357 | CT64: 34.763063 | CV64: 1856 | CW64: 280.7445 | CX64: 436.78015 | CY64: 55.140996 | CZ64: 161.73582 | DA64: 139.03118 | DB64: 1073.4327 | DC64: 1035.6635 | DD64: 126.98055 | DF64: 1856 | DG64: 4.0147708 | DH64: 5.3150317 | DI64: 3.1790161 | DJ64: 17.575535 | DK64: -3.7457931 | DL64: 6.6565755 | DM64: 3.9617281 | DN64: 4.059688 | DO64: 7.0807329 | DQ64: 1856 | DR64: 557.91926 | DS64: 922.4771 | DT64: 99.87099 | DU64: 161.73582 | DV64: 139.03118 | DW64: 1881.0344 | DX64: 1807.4986 | DY64: 185.93427 | EA64: 1856 | EB64: 2.5894594 | EC64: 3.3485518 | ED64: 2.1303561 | EE64: 12.876418 | EF64: -3.7457931 | EG64: 6.6565755 | EH64: 2.9201359 | EI64: 2.9829711 | EJ64: 5.2429438 | EL64: 1856 | EM64: 1143045.2 | EN64: 152931.41 | EO64: 15786.568 | EP64: 11072.601 | EQ64: 18613.688 | ER64: 137338.73 | ES64: 49276.447 | ET64: 937.71419 | EU64: 1529002.4 | EV64: 1479725.9 | EX64: 1856 | EY64: 858004.34 | EZ64: 108703.46 | FA64: 11949.211 | FB64: 11072.601 | FC64: 8250.5717 | FD64: 133669.27 | FE64: 49276.447 | FF64: 647.46849 | FG64: 1181573.4 | FH64: 1132296.9 | FJ64: 1856 | FK64: 285040.87 | FL64: 44227.953 | FM64: 3837.3567 | FN64: 0 | FO64: 10363.116 | FP64: 3669.4642 | FQ64: 290.2457 | FR64: 347429.01 | FS64: 567640.22 | HC64: 1856 | HD64: 204.97771 | HE64: 44.764203 | HF64: 6.6273568 | HG64: 9.3229672 | HH64: 60.370219 | HI64: 31.525825 | HJ64: 0.68310732 | HK64: 358.27138 | HL64: 326.74556 | HN64: 1856 | HO64: 85.750816 | HP64: 19.578092 | HQ64: 2.3844167 | HR64: 0 | HS64: 14.346201 | HT64: 0.35456449 | HU64: 122.41409 | HW64: 1856 | HX64: 44.367649 | HY64: 28.609211 | HZ64: 54.754285 | IA64: 5.9677689 | IB64: 49.852501 | IC64: 1.2240059 | ID64: 40.835519 | IE64: 225.61094 | IF64: 224.38694 | IH64: 1856 | II64: 129.67976 | IJ64: 44.23504 | IK64: 23.649581 | IL64: 133.52733 | IM64: 40.078929 | IN64: 21.427581 | IO64: -5.9202189
A65: 1856-1857 | B65: 2.8375457 | C65: 2.6535647 | D65: 2.8807528 | E65: 2.7943567 | F65: 2.9359095 | G65: 3.6454804 | H65: 3.5998153 | J65: 1857 | K65: 780.28923 | L65: 742.41842 | M65: 740.55144 | N65: 702.68063 | O65: 39.737789 | P65: 37.87081 | Q65: 477.95029 | R65: 1258.2395 | S65: 1220.3687 | U65: 1857 | V65: 212.01857 | W65: 11862.034 | X65: 2.9886588 | Y65: 201.72839 | Z65: 10538.716 | AA65: 2.1858441 | AB65: 3680287.2 | AC65: 0.63776113 | AE65: 1857 | AF65: 333.39951 | AG65: 96.757461 | AH65: 65.075708 | AI65: 36.182755 | AJ65: 64.577072 | AK65: 62.625729 | AL65: 33.718421 | AM65: 50.081767 | AN65: 742.41842 | AP65: 1856-1857 | AQ65: 4.9009956 | AR65: 1.1349494 | AS65: -6.3569181 | AT65: 5.1353534 | AU65: 3.8866102 | AV65: 1.3411485 | AW65: 2.43078 | AX65: 4.671468 | AY65: 2.8375457 | BA65: 1857 | BB65: 691.8291 | BC65: 43.022065 | BD65: 56.994122 | BE65: 15.643965 | BF65: 2.3126513 | BG65: 5.7910635 | BH65: 96.010614 | BI65: 131.31435 | BJ65: 780.28923 | BL65: 1856-1857 | BM65: -0.25959278 | BN65: 0.66414433 | BO65: -8.6889397 | BP65: 0.32301683 | BQ65: -22.319701 | BR65: 3.6454804 | BT65: 1856-1857 | BU65: 3.1199623 | BV65: 0.93902996 | BW65: 7.7791049 | BX65: -1.7093927 | BY65: 11.137483 | BZ65: 1.4220483 | CB65: 1857 | CC65: 27.160518 | CD65: 8.2307419 | CE65: 0.12867673 | CF65: 10.470268 | CG65: 2.357673 | CH65: 1.724885 | CI65: 30.66904 | CJ65: 80.741801 | CL65: 1857 | CM65: 16.595496 | CN65: 3.3631442 | CO65: 0.098248298 | CP65: 7.4074831 | CQ65: 0.55045824 | CR65: 1.367232 | CS65: 10.355727 | CT65: 39.737789 | CV65: 1857 | CW65: 327.41555 | CX65: 499.05907 | CY65: 67.96768 | CZ65: 140.10978 | DA65: 150.91717 | DB65: 1185.4693 | DC65: 1143.1011 | DD65: 142.4061 | DF65: 1857 | DG65: 3.2165013 | DH65: 6.2041379 | DI65: 1.2564153 | DJ65: 9.3127118 | DK65: 6.0584007 | DL65: 3.8372463 | DM65: 4.0003916 | DN65: 4.1159745 | DO65: 4.2834939 | DQ65: 1857 | DR65: 638.51841 | DS65: 1043.2974 | DT65: 118.13938 | DU65: 140.10978 | DV65: 150.91717 | DW65: 2090.9821 | DX65: 2008.4437 | DY65: 208.4669 | EA65: 1857 | EB65: 2.2460733 | EC65: 3.9099755 | ED65: 1.2277326 | EE65: 8.5142624 | EF65: 6.0584007 | EG65: 3.8372463 | EH65: 2.9933582 | EI65: 3.0690809 | EJ65: 3.4601811 | EL65: 1857 | EM65: 1158127.4 | EN65: 154577.9 | EO65: 15247.183 | EP65: 11902.481 | EQ65: 19747.259 | ER65: 138252.02 | ES65: 49908.73 | ET65: 963.43176 | EU65: 1548726.4 | EV65: 1498817.6 | EX65: 1857 | EY65: 868735.81 | EZ65: 109372.31 | FA65: 11343.538 | FB65: 11902.481 | FC65: 8692.9874 | FD65: 134475.53 | FE65: 49908.73 | FF65: 665.22584 | FG65: 1195096.6 | FH65: 1145187.9 | FJ65: 1857 | FK65: 289391.54 | FL65: 45205.586 | FM65: 3903.645 | FN65: 0 | FO65: 11054.272 | FP65: 3776.4905 | FQ65: 298.20592 | FR65: 353629.74 | FS65: 576772.45 | HC65: 1857 | HD65: 222.63538 | HE65: 48.315248 | HF65: 6.7489929 | HG65: 10.750565 | HH65: 61.311009 | HI65: 32.351189 | HJ65: 0.70961873 | HK65: 382.82201 | HL65: 350.47082 | HN65: 1857 | HO65: 93.391268 | HP65: 21.466189 | HQ65: 2.602014 | HR65: 0 | HS65: 15.512698 | HT65: 0.36832515 | HU65: 133.34049 | HW65: 1857 | HX65: 38.363856 | HY65: 26.976023 | HZ65: 55.724701 | IA65: 4.4411899 | IB65: 50.379094 | IC65: 1.367232 | ID65: 49.003823 | IE65: 226.25592 | IF65: 224.88869 | IH65: 1857 | II65: 139.71259 | IJ65: 38.405059 | IK65: 19.860992 | IL65: 144.47975 | IM65: 33.838339 | IN65: 17.499334 | IO65: 4.0271203
A66: 1857-1858 | B66: 5.5604181 | C66: 5.475107 | D66: 5.6119182 | E66: 5.5089431 | F66: 5.4949012 | G66: 4.1748284 | H66: 4.1828538 | J66: 1858 | K66: 717.96488 | L66: 683.37489 | M66: 682.67452 | N66: 648.08453 | O66: 35.290357 | P66: 34.589991 | Q66: 414.82532 | R66: 1132.7902 | S66: 1098.2002 | U66: 1858 | V66: 193.47735 | W66: 12255.488 | X66: 3.3169162 | Y66: 184.15603 | Z66: 11033.098 | AA66: 4.6910952 | AB66: 3710847.2 | AC66: 0.83036948 | AE66: 1858 | AF66: 318.80947 | AG66: 86.519171 | AH66: 54.078849 | AI66: 32.084745 | AJ66: 57.482085 | AK66: 54.477159 | AL66: 36.070893 | AM66: 43.85252 | AN66: 683.37489 | AP66: 1857-1858 | AQ66: 11.175805 | AR66: -3.4955563 | AS66: 1.4531401 | AT66: 2.3436049 | AU66: -4.0276995 | AV66: 1.7729548 | AW66: 13.527995 | AX66: 5.8857017 | AY66: 5.5604181 | BA66: 1858 | BB66: 606.481 | BC66: 44.680363 | BD66: 47.456214 | BE66: 14.719688 | BF66: 3.4475812 | BG66: 2.1412105 | BH66: 78.796465 | BI66: 79.757642 | BJ66: 717.96488 | BL66: 1857-1858 | BM66: 0.034347431 | BN66: 11.211001 | BO66: -2.4970333 | BP66: -7.0531553 | BQ66: -28.138475 | BR66: 4.1748284 | BT66: 1857-1858 | BU66: -12.366687 | BV66: -6.6148798 | BW66: -13.922981 | BX66: -11.701599 | BY66: -15.479182 | BZ66: -11.674766 | CB66: 1858 | CC66: 25.742026 | CD66: 7.0749735 | CE66: 0.11900616 | CF66: 9.9420475 | CG66: 1.4959657 | CH66: 1.6908648 | CI66: 21.699811 | CJ66: 67.764694 | CL66: 1858 | CM66: 14.557172 | CN66: 3.2106026 | CO66: 0.093334877 | CP66: 6.7716967 | CQ66: 0.46909074 | CR66: 1.1686781 | CS66: 9.0197819 | CT66: 35.290357 | CV66: 1858 | CW66: 290.82778 | CX66: 422.63907 | CY66: 67.508273 | CZ66: 132.08728 | DA66: 144.74651 | DB66: 1057.8089 | DC66: 1022.0107 | DD66: 133.58928 | DF66: 1858 | DG66: 2.9929393 | DH66: 4.3599786 | DI66: 2.0522478 | DJ66: 8.1784706 | DK66: -6.8327493 | DL66: 1.4792831 | DM66: 1.9480752 | DN66: 1.9654137 | DO66: 5.1601548 | DQ66: 1858 | DR66: 554.91416 | DS66: 883.28889 | DT66: 116.43141 | DU66: 132.08728 | DV66: 144.74651 | DW66: 1831.4683 | DX66: 1761.5226 | DY66: 190.35974 | EA66: 1858 | EB66: 2.1732796 | EC66: 3.0392733 | ED66: 1.629231 | EE66: 7.9279219 | EF66: -6.8327493 | EG66: 1.4792831 | EH66: 1.8657529 | EI66: 1.8822297 | EJ66: 4.1736952 | EL66: 1858 | EM66: 1185728.5 | EN66: 152900.13 | EO66: 15937.572 | EP66: 12612.179 | EQ66: 20500.306 | ER66: 140449.28 | ES66: 54551.296 | ET66: 989.85466 | EU66: 1583669.1 | EV66: 1529117.8 | EX66: 1858 | EY66: 891919.9 | EZ66: 106745.13 | FA66: 11903.213 | FB66: 12612.179 | FC66: 8952.2054 | FD66: 136622.83 | FE66: 54551.296 | FF66: 683.47019 | FG66: 1223990.2 | FH66: 1169438.9 | FJ66: 1858 | FK66: 293808.61 | FL66: 46154.997 | FM66: 4034.3596 | FN66: 0 | FO66: 11548.101 | FP66: 3826.4499 | FQ66: 306.38446 | FR66: 359678.9 | FS66: 586051.6 | HC66: 1858 | HD66: 201.4576 | HE66: 41.560067 | HF66: 6.2417442 | HG66: 10.040036 | HH66: 54.23857 | HI66: 34.902215 | HJ66: 0.64052561 | HK66: 349.08075 | HL66: 314.17854 | HN66: 1858 | HO66: 83.567286 | HP66: 19.316699 | HQ66: 2.3700922 | HR66: 0 | HS66: 13.84725 | HT66: 0.3324626 | HU66: 119.43379 | HW66: 1858 | HX66: 54.634588 | HY66: 25.642406 | HZ66: 45.467012 | IA66: 1.194709 | IB66: 43.873424 | IC66: 1.1686781 | ID66: 42.879532 | IE66: 214.86035 | IF66: 213.69167 | IH66: 1858 | II66: 146.57188 | IJ66: 41.844531 | IK66: 20.126833 | IL66: 151.92357 | IM66: 36.847889 | IN66: 17.723494 | IO66: 0.57316088
A67: 1858-1859 | B67: 6.3195769 | C67: 6.1918526 | D67: 6.3428607 | E67: 6.2962983 | F67: 6.2596559 | G67: 7.6614373 | H67: 7.8939492 | J67: 1859 | K67: 708.37027 | L67: 674.28455 | M67: 672.6904 | N67: 638.60467 | O67: 35.679872 | P67: 34.085723 | Q67: 399.70736 | R67: 1108.0776 | S67: 1073.9919 | U67: 1859 | V67: 188.35165 | W67: 13018.86 | X67: 6.2288162 | Y67: 179.28844 | Z67: 11574.25 | AA67: 4.9048117 | AB67: 3760892.4 | AC67: 1.3486181 | AE67: 1859 | AF67: 302.87143 | AG67: 90.436404 | AH67: 55.385122 | AI67: 36.23422 | AJ67: 54.887087 | AK67: 52.661916 | AL67: 36.417241 | AM67: 45.391121 | AN67: 674.28455 | AP67: 1858-1859 | AQ67: 6.5893546 | AR67: 9.2344719 | AS67: 5.9080635 | AT67: 19.464623 | AU67: 4.2505811 | AV67: 0.92851131 | AW67: -0.6601747 | AX67: 4.9200612 | AY67: 6.3195769 | BA67: 1859 | BB67: 597.2115 | BC67: 44.909968 | BD67: 49.010352 | BE67: 11.711042 | BF67: 1.975118 | BG67: 2.5680554 | BH67: 98.044585 | BI67: 97.060348 | BJ67: 708.37027 | BL67: 1858-1859 | BM67: 9.3303642 | BN67: -0.68702776 | BO67: -0.96239181 | BP67: 24.563752 | BQ67: 24.670055 | BR67: 7.6614373 | BT67: 1858-1859 | BU67: -9.9320739 | BV67: 1.2092193 | BW67: -2.7535326 | BX67: -0.1092677 | BY67: -2.3870623 | BZ67: -8.3574956 | CB67: 1859 | CC67: 22.675783 | CD67: 8.736785 | CE67: 0.14164372 | CF67: 9.4190074 | CG67: 2.2217862 | CH67: 1.6941473 | CI67: 20.375414 | CJ67: 65.264567 | CL67: 1859 | CM67: 14.60069 | CN67: 3.3256537 | CO67: 0.092115208 | CP67: 6.8003751 | CQ67: 0.49353012 | CR67: 1.1646047 | CS67: 9.2029027 | CT67: 35.679872 | CV67: 1859 | CW67: 299.10914 | CX67: 425.06176 | CY67: 70.045627 | CZ67: 107.67933 | DA67: 138.26618 | DB67: 1040.162 | DC67: 1004.4003 | DD67: 133.71531 | DF67: 1859 | DG67: 3.1158416 | DH67: 3.7352625 | DI67: 2.679965 | DJ67: 3.5257392 | DK67: 17.517568 | DL67: 1.8573273 | DM67: 4.5102173 | DN67: 4.617868 | DO67: 3.9752033 | DQ67: 1859 | DR67: 563.49286 | DS67: 884.66986 | DT67: 120.57595 | DU67: 107.67933 | DV67: 138.26618 | DW67: 1814.6842 | DX67: 1744.816 | DY67: 190.36233 | EA67: 1859 | EB67: 2.2732901 | EC67: 2.7602274 | ED67: 1.963134 | EE67: 5.0419199 | EF67: 17.517568 | EG67: 1.8573273 | EH67: 3.3557693 | EI67: 3.4313435 | EJ67: 3.4036266 | EL67: 1859 | EM67: 1204602.7 | EN67: 161745.38 | EO67: 17418.569 | EP67: 12986.652 | EQ67: 20899.485 | ER67: 142046.06 | ES67: 53937.567 | ET67: 1017.0022 | EU67: 1614653.4 | EV67: 1560715.8 | EX67: 1859 | EY67: 906309.55 | EZ67: 114523.6 | FA67: 13211.783 | FB67: 12986.652 | FC67: 8747.6892 | FD67: 138192.87 | FE67: 53937.567 | FF67: 702.21492 | FG67: 1248611.9 | FH67: 1194674.4 | FJ67: 1859 | FK67: 298293.1 | FL67: 47221.778 | FM67: 4206.7861 | FN67: 0 | FO67: 12151.796 | FP67: 3853.1833 | FQ67: 314.78731 | FR67: 366041.43 | FS67: 595480.03 | HC67: 1859 | HD67: 200.77109 | HE67: 43.731058 | HF67: 6.794696 | HG67: 10.139328 | HH67: 52.184969 | HI67: 35.252636 | HJ67: 0.62320406 | HK67: 349.49699 | HL67: 314.24435 | HN67: 1859 | HO67: 83.211206 | HP67: 19.383105 | HQ67: 2.4238621 | HR67: 0 | HS67: 14.196057 | HT67: 0.32347192 | HU67: 119.5377 | HW67: 1859 | HX67: 40.625133 | HY67: 27.32224 | HZ67: 46.166564 | IA67: 4.3588916 | IB67: 41.167977 | IC67: 1.1646047 | ID67: 44.444445 | IE67: 205.24986 | IF67: 204.08525 | IH67: 1859 | II67: 140.35545 | IJ67: 43.01323 | IK67: 21.428737 | IL67: 145.43219 | IM67: 38.020922 | IN67: 18.941622 | IO67: 8.8921743
A68: 1859-1860 | B68: 3.6101102 | C68: 3.5006384 | D68: 3.619957 | E68: 3.6002644 | F68: 3.5787848 | G68: 4.2946042 | H68: 4.3774718 | J68: 1860 | K68: 743.37093 | L68: 707.588 | M68: 705.95334 | N68: 670.17041 | O68: 37.417589 | P68: 35.782932 | Q68: 420.88205 | R68: 1164.253 | S68: 1128.4701 | U68: 1860 | V68: 194.41843 | W68: 13355.42 | X68: 2.585175 | Y68: 185.0599 | Z68: 11795.538 | AA68: 1.9119001 | AB68: 3823562.1 | AC68: 1.6663512 | AE68: 1860 | AF68: 309.4707 | AG68: 97.086051 | AH68: 59.086318 | AI68: 38.485245 | AJ68: 59.71307 | AK68: 57.581631 | AL68: 37.959761 | AM68: 48.205221 | AN68: 707.588 | AP68: 1859-1860 | AQ68: 2.2848028 | AR68: 6.4287066 | AS68: 4.847772 | AT68: 4.7620707 | AU68: 8.0766007 | AV68: 1.6379183 | AW68: 0.32889933 | AX68: 3.9937439 | AY68: 3.6101102 | BA68: 1860 | BB68: 625.01649 | BC68: 46.631719 | BD68: 53.08044 | BE68: 10.287263 | BF68: 1.3856622 | BG68: 7.7942664 | BH68: 109.23647 | BI68: 110.06139 | BJ68: 743.37093 | BL68: 1859-1860 | BM68: 4.2495604 | BN68: -0.17832331 | BO68: 8.9965768 | BP68: 8.5026152 | BQ68: 9.3143306 | BR68: 4.2946042 | BT68: 1859-1860 | BU68: 0.38968383 | BV68: 4.0192739 | BW68: 1.9842069 | BX68: 2.6842549 | BY68: 3.7327862 | BZ68: 0.6197905 | CB68: 1860 | CC68: 24.226435 | CD68: 10.660089 | CE68: 0.14738565 | CF68: 9.7595767 | CG68: 3.6687567 | CH68: 1.7604088 | CI68: 22.324979 | CJ68: 72.547632 | CL68: 1860 | CM68: 15.220734 | CN68: 3.5166187 | CO68: 0.097666946 | CP68: 7.0900808 | CQ68: 0.52696699 | CR68: 1.2073636 | CS68: 9.7581571 | CT68: 37.417589 | CV68: 1860 | CW68: 317.1261 | CX68: 446.08092 | CY68: 73.742718 | CZ68: 137.00802 | DA68: 141.3786 | DB68: 1115.3364 | DC68: 1078.2554 | DD68: 140.2342 | DF68: 1860 | DG68: 3.3057394 | DH68: 3.9627209 | DI68: 2.8386807 | DJ68: 0.96457826 | DK68: 0.22359909 | DL68: 5.5130454 | DM68: 3.0547323 | DN68: 3.1085067 | DO68: 4.1491765 | DQ68: 1860 | DR68: 591.81963 | DS68: 921.93499 | DT68: 128.81073 | DU68: 137.00802 | DV68: 141.3786 | DW68: 1920.952 | DX68: 1848.5178 | DY68: 199.18896 | EA68: 1860 | EB68: 2.409842 | EC68: 2.9289621 | ED68: 2.0766021 | EE68: 3.3233268 | EF68: 0.22359909 | EG68: 5.5130454 | EH68: 2.5446949 | EI68: 2.5866768 | EJ68: 3.5451549 | EL68: 1860 | EM68: 1214229.4 | EN68: 167373.01 | EO68: 18877.86 | EP68: 12847.76 | EQ68: 21560.845 | ER68: 144123.31 | ES68: 53680.359 | ET68: 1044.8943 | EU68: 1633737.4 | EV68: 1580057.1 | EX68: 1860 | EY68: 911383.34 | EZ68: 119616.91 | FA68: 14498.645 | FB68: 12847.76 | FC68: 8957.9122 | FD68: 140233.33 | FE68: 53680.359 | FF68: 721.47373 | FG68: 1261939.7 | FH68: 1208259.4 | FJ68: 1860 | FK68: 302846.04 | FL68: 47756.099 | FM68: 4379.215 | FN68: 0 | FO68: 12602.933 | FP68: 3889.9798 | FQ68: 323.4206 | FR68: 371797.69 | FS68: 605060.15 | HC68: 1860 | HD68: 211.79189 | HE68: 47.914966 | HF68: 7.8220327 | HG68: 10.522598 | HH68: 56.550127 | HI68: 36.752397 | HJ68: 0.67684412 | HK68: 372.03085 | HL68: 335.27846 | HN68: 1860 | HO68: 88.622524 | HP68: 20.563331 | HQ68: 2.6468989 | HR68: 0 | HS68: 15.613577 | HT68: 0.3513136 | HU68: 127.79764 | HW68: 1860 | HX68: 31.154289 | HY68: 28.607753 | HZ68: 48.617387 | IA68: 5.864647 | IB68: 45.130997 | IC68: 1.2073636 | ID68: 47.177064 | IE68: 207.7595 | IF68: 206.55214 | IH68: 1860 | II68: 137.11613 | IJ68: 41.506605 | IK68: 21.392028 | IL68: 141.99865 | IM68: 36.641003 | IN68: 18.884353 | IO68: 4.4947616
A69: 1860-1861 | B69: 0.71535829 | C69: 0.616189 | D69: 0.73504808 | E69: 0.69567234 | F69: 0.82636976 | G69: 0.70225763 | H69: 0.53286444 | J69: 1861 | K69: 778.46445 | L69: 740.97072 | M69: 739.34398 | N69: 701.85025 | O69: 39.120465 | P69: 37.493732 | Q69: 457.16133 | R69: 1235.6258 | S69: 1198.132 | U69: 1861 | V69: 200.20036 | W69: 13224.856 | X69: -0.97760586 | Y69: 190.55797 | Z69: 11681.744 | AA69: -0.96472374 | AB69: 3888426.8 | AC69: 1.6964481 | AE69: 1861 | AF69: 324.51831 | AG69: 102.11415 | AH69: 54.530366 | AI69: 42.182227 | AJ69: 64.866077 | AK69: 64.097077 | AL69: 39.327211 | AM69: 49.335303 | AN69: 740.97072 | AP69: 1860-1861 | AQ69: -1.5438564 | AR69: 3.6872557 | AS69: -5.9757199 | AT69: 2.5607741 | AU69: 7.3489087 | AV69: 3.4349094 | AW69: 1.6717779 | AX69: 3.8856432 | AY69: 0.71535829 | BA69: 1861 | BB69: 692.17295 | BC69: 48.623507 | BD69: 58.660695 | BE69: 15.00441 | BF69: 0.018 | BG69: 7.6566704 | BH69: 103.05827 | BI69: 146.73006 | BJ69: 778.46445 | BL69: 1860-1861 | BM69: 5.3257837 | BN69: 2.4982526 | BO69: 11.310391 | BP69: -7.250741 | BQ69: 26.791682 | BR69: 0.70225763 | BT69: 1860-1861 | BU69: 5.1449571 | BV69: 1.7298486 | BW69: 0.72656459 | BX69: 1.7196221 | BY69: 5.146144 | BZ69: 3.9905805 | CB69: 1861 | CC69: 24.840634 | CD69: 10.23198 | CE69: 0.14128464 | CF69: 17.440489 | CG69: 3.2524762 | CH69: 2.7530087 | CI69: 22.679903 | CJ69: 81.339776 | CL69: 1861 | CM69: 15.713277 | CN69: 3.714016 | CO69: 0.10340182 | CP69: 7.6097266 | CQ69: 0.5370159 | CR69: 1.2601823 | CS69: 10.182845 | CT69: 39.120465 | CV69: 1861 | CW69: 332.06481 | CX69: 462.04404 | CY69: 74.587875 | CZ69: 137.31437 | DA69: 151.20288 | DB69: 1157.214 | DC69: 1119.3067 | DD69: 147.75144 | DF69: 1861 | DG69: 3.7307642 | DH69: 3.7634393 | DI69: 3.7072809 | DJ69: 6.5932918 | DK69: 4.0492708 | DL69: 5.0638391 | DM69: 4.1265432 | DN69: 4.1329484 | DO69: 5.2505644 | DQ69: 1861 | DR69: 613.5362 | DS69: 947.85027 | DT69: 133.27414 | DU69: 137.31437 | DV69: 151.20288 | DW69: 1983.1779 | DX69: 1909.1424 | DY69: 208.41534 | EA69: 1861 | EB69: 2.6740498 | EC69: 2.8659863 | ED69: 2.54981 | EE69: 6.5665745 | EF69: 4.0492708 | EG69: 5.0638391 | EH69: 3.2064994 | EI69: 3.2238614 | EJ69: 4.3420435 | EL69: 1861 | EM69: 1213013.6 | EN69: 176873.73 | EO69: 18179.142 | EP69: 13709.42 | EQ69: 22795.096 | ER69: 148323.78 | ES69: 54596.927 | ET69: 1067.5044 | EU69: 1648559.2 | EV69: 1593962.2 | EX69: 1861 | EY69: 908411.61 | EZ69: 127538.5 | FA69: 13726.906 | FB69: 13709.42 | FC69: 9842.241 | FD69: 144409.16 | FE69: 54596.927 | FF69: 740.62698 | FG69: 1272975.4 | FH69: 1218378.5 | FJ69: 1861 | FK69: 304601.96 | FL69: 49335.227 | FM69: 4452.2358 | FN69: 0 | FO69: 12952.855 | FP69: 3914.6178 | FQ69: 326.87744 | FR69: 375583.77 | FS69: 611059.25 | HC69: 1861 | HD69: 217.02003 | HE69: 52.520496 | HF69: 7.6133146 | HG69: 11.54313 | HH69: 62.315042 | HI69: 38.067029 | HJ69: 0.72655893 | HK69: 389.8056 | HL69: 351.73857 | HN69: 1861 | HO69: 91.635512 | HP69: 21.838895 | HQ69: 2.7664839 | HR69: 0 | HS69: 16.883307 | HT69: 0.37129184 | HU69: 133.49549 | HW69: 1861 | HX69: 40.033764 | HY69: 27.754758 | HZ69: 44.150567 | IA69: 6.4680975 | IB69: 49.764805 | IC69: 1.2601823 | ID69: 48.237452 | IE69: 217.66963 | IF69: 216.40944 | IH69: 1861 | II69: 137.35271 | IJ69: 37.062733 | IK69: 19.687058 | IL69: 142.26457 | IM69: 32.330472 | IN69: 17.173366 | IO69: -2.2266582
A70: 1861-1862 | B70: -5.4709255 | C70: -5.6423357 | D70: -5.2310069 | E70: -5.7102367 | F70: -5.4358645 | G70: -5.5898304 | H70: -6.1103155 | J70: 1862 | K70: 771.48394 | L70: 734.24219 | M70: 729.63737 | N70: 692.39562 | O70: 41.846574 | P70: 37.241749 | Q70: 442.6918 | R70: 1214.1757 | S70: 1176.934 | U70: 1862 | V70: 195.73139 | W70: 12317.35 | X70: -6.8621297 | Y70: 186.28288 | Z70: 10893.831 | AA70: -6.7448272 | AB70: 3941544.2 | AC70: 1.3660386 | AE70: 1862 | AF70: 321.89057 | AG70: 100.43071 | AH70: 52.435905 | AI70: 39.902033 | AJ70: 62.020022 | AK70: 63.945718 | AL70: 39.495749 | AM70: 54.12148 | AN70: 734.24219 | AP70: 1861-1862 | AQ70: -8.6974281 | AR70: -2.70338 | AS70: -4.3171235 | AT70: -10.319486 | AU70: -7.1072954 | AV70: -0.17289696 | AW70: 1.3008732 | AX70: 3.5922453 | AY70: -5.4709255 | BA70: 1862 | BB70: 654.91863 | BC70: 50.027897 | BD70: 66.118955 | BE70: 15.168552 | BF70: 0.84317995 | BG70: 3.6358342 | BH70: 105.43105 | BI70: 124.66016 | BJ70: 771.48394 | BL70: 1861-1862 | BM70: -9.9072889 | BN70: 3.2131933 | BO70: 2.654675 | BP70: 6.4065404 | BQ70: -10.790144 | BR70: -5.5898304 | BT70: 1861-1862 | BU70: 5.0226715 | BV70: -0.31478478 | BW70: 2.7155254 | BX70: -3.8570691 | BY70: -4.7651876 | BZ70: 4.9709987 | CB70: 1862 | CC70: 24.989118 | CD70: 8.1169596 | CE70: 0.15675711 | CF70: 22.057251 | CG70: 1.8808363 | CH70: 1.8789576 | CI70: 26.686642 | CJ70: 85.766521 | CL70: 1862 | CM70: 16.623904 | CN70: 3.8562499 | CO70: 0.10373809 | CP70: 8.3384608 | CQ70: 0.56330836 | CR70: 1.3240343 | CS70: 11.036878 | CT70: 41.846574 | CV70: 1862 | CW70: 358.84534 | CX70: 499.03031 | CY70: 77.711956 | CZ70: 150.51588 | DA70: 161.64844 | DB70: 1247.7519 | DC70: 1206.7953 | DD70: 157.88337 | DF70: 1862 | DG70: 4.0498358 | DH70: 4.3611444 | DI70: 3.8259732 | DJ70: 6.0406657 | DK70: 0.066247585 | DL70: 2.2492231 | DM70: 3.4761054 | DN70: 3.5483827 | DO70: 3.6783363 | DQ70: 1862 | DR70: 657.28252 | DS70: 1012.2999 | DT70: 138.95984 | DU70: 150.51588 | DV70: 161.64844 | DW70: 2120.7066 | DX70: 2041.6307 | DY70: 221.3621 | EA70: 1862 | EB70: 2.8941513 | EC70: 3.2426114 | ED70: 2.6678924 | EE70: 6.2368112 | EF70: 0.066247585 | EG70: 2.2492231 | EH70: 2.8726693 | EI70: 2.9283742 | EJ70: 3.2563964 | EL70: 1862 | EM70: 1194474.6 | EN70: 173954.7 | EO70: 17947.447 | EP70: 13196.67 | EQ70: 23357.629 | ER70: 146760.59 | ES70: 56953.783 | ET70: 1090.6673 | EU70: 1627736.1 | EV70: 1570782.3 | EX70: 1862 | EY70: 888106.58 | EZ70: 125255.03 | FA70: 13398.385 | FB70: 13196.67 | FC70: 10517.127 | FD70: 142927.55 | FE70: 56953.783 | FF70: 760.29387 | FG70: 1251115.4 | FH70: 1194161.6 | FJ70: 1862 | FK70: 306368.05 | FL70: 48699.664 | FM70: 4549.0613 | FN70: 0 | FO70: 12840.502 | FP70: 3833.0395 | FQ70: 330.37347 | FR70: 376620.69 | FS70: 617117.83 | HC70: 1862 | HD70: 210.24034 | HE70: 51.111251 | HF70: 7.3635528 | HG70: 11.010389 | HH70: 63.43654 | HI70: 38.171715 | HJ70: 0.77325695 | HK70: 382.10704 | HL70: 343.93533 | HN70: 1862 | HO70: 91.32894 | HP70: 21.361576 | HQ70: 2.8009516 | HR70: 0 | HS70: 16.247323 | HT70: 0.38905111 | HU70: 132.12784 | HW70: 1862 | HX70: 43.628297 | HY70: 27.957884 | HZ70: 42.271401 | IA70: 5.5846439 | IB70: 46.281877 | IC70: 1.3240343 | ID70: 52.959172 | IE70: 220.00731 | IF70: 218.68327 | IH70: 1862 | II70: 149.208 | IJ70: 38.296101 | IK70: 18.558913 | IL70: 154.85133 | IM70: 33.256098 | IN70: 16.116445 | IO70: -5.648078
... A157: 1948-1949 | B157: 3.7504101 | C157: 3.6796124 | D157: 3.8430078 | E157: 3.657895 | F157: 4.0945328 | G157: 2.2825844 | H157: 1.9047018 | J157: 1949 | K157: 28941.698 | L157: 26376.083 | M157: 26015.998 | N157: 23450.383 | O157: 2925.6998 | P157: 2565.6149 | Q157: 28644.126 | R157: 57585.824 | S157: 55020.209 | U157: 1949 | V157: 4161 | W157: 69952.975 | X157: 1.2219667 | Y157: 3792.1369 | Z157: 64854.711 | AA157: 2.6745718 | AB157: 6955467 | AC157: 1.0478138 | AE157: 1949 | AF157: 3276.9538 | AG157: 8547.3956 | AH157: 2166.4573 | AI157: 2205.6042 | AJ157: 3345.141 | AK157: 1599.2322 | AL157: 2688.4037 | AM157: 2546.8954 | AN157: 26376.083 | AP157: 1948-1949 | AQ157: 12.80958 | AR157: 1.5459813 | AS157: 4.1731243 | AT157: 3.2559404 | AU157: 2.8433698 | AV157: -0.35937173 | AW157: 3.9851247 | AX157: 4.1043914 | AY157: 3.7504101 | BA157: 1949 | BB157: 18561.043 | BC157: 3924.8761 | BD157: 3578.0972 | BE157: 1941.3381 | BF157: -26.386291 | BG157: 417.54203 | BH157: 5437.8254 | BI157: 4892.638 | BJ157: 28941.698 | BL157: 1948-1949 | BM157: -1.8325056 | BN157: 5.3248256 | BO157: -1.7289173 | BP157: 1.8154312 | BQ157: -14.070839 | BR157: 2.2825844 | BT157: 1948-1949 | BU157: 2.2168424 | BV157: 1.0145372 | BW157: 1.0462593 | BX157: 3.1320601 | BY157: 1.9722081 | BZ157: 2.0265829 | CB157: 1949 | CC157: 386.30817 | CD157: 2051.6472 | CE157: 109.18431 | CF157: 853.43393 | CG157: 335.56346 | CH157: 547.59391 | CI157: 1626.86 | CJ157: 5910.591 | CL157: 1949 | CM157: 238.04041 | CN157: 877.32124 | CO157: 68.520006 | CP157: 513.75889 | CQ157: 152.99127 | CR157: 257.68203 | CS157: 817.38591 | CT157: 2925.6998 | CV157: 1949 | CW157: 26950.267 | CX157: 24091.393 | CY157: 8559.6004 | CZ157: 963.9495 | DA157: 9985.2779 | DB157: 70550.488 | DC157: 63972.813 | DD157: 20164.108 | DF157: 1949 | DG157: 3.5694008 | DH157: 3.0035847 | DI157: 4.202151 | DJ157: 8.9993913 | DK157: -2.7373106 | DL157: 4.1815764 | DM157: 4.2294713 | DN157: 4.2125573 | DO157: 6.1440375 | DQ157: 1949 | DR157: 46429.728 | DS157: 45974.892 | DT157: 14640.93 | DU157: 963.9495 | DV157: 9985.2779 | DW157: 117994.78 | DX157: 107592.67 | DY157: 29189.107 | EA157: 1949 | EB157: 3.0454375 | EC157: 2.868196 | ED157: 3.2243836 | EE157: 8.7366367 | EF157: -2.7373106 | EG157: 4.1815764 | EH157: 3.8040567 | EI157: 3.7477027 | EJ157: 5.9006565 | EL157: 1949 | EM157: 801462.89 | EN157: 1113418.6 | EO157: 247097.66 | EP157: 221750.76 | EQ157: 415837.38 | ER157: 280424.98 | ES157: 301999.29 | ET157: 22301.095 | EU157: 3404292.6 | EV157: 3102293.3 | EX157: 1949 | EY157: 389748.84 | EZ157: 1019353.3 | FA157: 217372.1 | FB157: 200455.27 | FC157: 339106.13 | FD157: 244573.86 | FE157: 301999.29 | FF157: 15647.85 | FG157: 2728256.6 | FH157: 2426257.3 | FJ157: 1949 | FK157: 411714.04 | FL157: 94065.29 | FM157: 29725.568 | FN157: 21295.484 | FO157: 76731.25 | FP157: 35851.125 | FQ157: 6653.2448 | FR157: 676036.01 | FS157: 1311093.6 | HC157: 1949 | HD157: 1339.204 | HE157: 5978.7412 | HF157: 1511.9881 | HG157: 1608.9525 | HH157: 3010.6976 | HI157: 2430.7217 | HJ157: 95.304957 | HK157: 15975.61 | HL157: 13544.888 | HN157: 1949 | HO157: 1752.3993 | HP157: 593.06248 | HQ157: 231.64536 | HR157: 184.08482 | HS157: 797.40916 | HT157: 46.919509 | HU157: 3605.5206 | HW157: 1949 | HX157: 238.04041 | HY157: 1975.5918 | HZ157: 422.82386 | IA157: 359.87681 | IB157: 1136.2665 | IC157: 257.68203 | ID157: 2404.6709 | IE157: 6794.9523 | IF157: 6537.2703 | IH157: 1949 | II157: 212.85504 | IJ157: 28.623872 | IK157: 10.454972 | IL157: 234.57975 | IM157: 16.71186 | IN157: 6.1040667 | IO157: 7.6372072
A158: 1949-1950 | B158: 3.8954662 | C158: 3.9556579 | D158: 4.0148472 | E158: 3.7762221 | F158: 4.2006161 | G158: 6.9969657 | H158: 7.1000016 | J158: 1950 | K158: 31827.346 | L158: 29060.883 | M158: 28653.244 | N158: 25886.781 | O158: 3174.1019 | P158: 2766.4628 | Q158: 30997.787 | R158: 62825.133 | S158: 60058.67 | U158: 1950 | V158: 4537.7208 | W158: 74223.476 | X158: 6.1048172 | Y158: 4143.2978 | Z158: 66819.276 | AA158: 3.0291782 | AB158: 7013949.8 | AC158: 0.84081813 | AE158: 1950 | AF158: 3992.4452 | AG158: 9544.9065 | AH158: 2334.9977 | AI158: 2329.661 | AJ158: 3613.1711 | AK158: 1710.2663 | AL158: 2826.6956 | AM158: 2708.7394 | AN158: 29060.883 | AP158: 1949-1950 | AQ158: 1.4327269 | AR158: 3.840247 | AS158: 6.1406542 | AT158: 3.5956335 | AU158: 6.6125876 | AV158: 2.4715651 | AW158: 3.5518208 | AX158: 3.5820569 | AY158: 3.8954662 | BA158: 1950 | BB158: 21505.443 | BC158: 4164.6367 | BD158: 3851.3542 | BE158: 2304.2749 | BF158: -20.800178 | BG158: -176 | BH158: 7088.5536 | BI158: 6890.117 | BJ158: 31827.346 | BL158: 1949-1950 | BM158: 12.779105 | BN158: 4.2921285 | BO158: -1.3790826 | BP158: 22.288262 | BQ158: 33.653303 | BR158: 6.9969657 | BT158: 1949-1950 | BU158: 2.7347507 | BV158: 1.7418518 | BW158: 2.2259064 | BX158: 6.5976417 | BY158: 5.3668065 | BZ158: 2.7791335 | CB158: 1950 | CC158: 518.09294 | CD158: 1725.851 | CE158: 113.92307 | CF158: 872.33612 | CG158: 276.79174 | CH158: 621.76317 | CI158: 1830.0708 | CJ158: 5958.8289 | CL158: 1950 | CM158: 262.88232 | CN158: 976.02785 | CO158: 72.395066 | CP158: 561.22709 | CQ158: 167.00411 | CR158: 275.55012 | CS158: 859.01536 | CT158: 3174.1019 | CV158: 1950 | CW158: 28194.829 | CX158: 25514.213 | CY158: 9636.6608 | CZ158: 1031.3195 | DA158: 10922.561 | DB158: 75299.584 | DC158: 68278.066 | DD158: 22036.848 | DF158: 1950 | DG158: 3.7353007 | DH158: 3.4440906 | DI158: 4.0592193 | DJ158: 10.179138 | DK158: -2.016851 | DL158: -1.611286 | DM158: 3.6958299 | DN158: 3.5682576 | DO158: 5.6154227 | DQ158: 1950 | DR158: 48510.004 | DS158: 48227.596 | DT158: 16448.878 | DU158: 1031.3195 | DV158: 10922.561 | DW158: 125140.36 | DX158: 114032.2 | DY158: 31717.9 | EA158: 1950 | EB158: 3.1711334 | EC158: 3.1360717 | ED158: 3.2068091 | EE158: 9.564002 | EF158: -2.016851 | EG158: -1.611286 | EH158: 3.5373421 | EI158: 3.4228487 | EJ158: 5.6088953 | EL158: 1950 | EM158: 774965.54 | EN158: 1120004.2 | EO158: 249373.91 | EP158: 223536.35 | EQ158: 423405.94 | ER158: 277944.78 | ES158: 312702.44 | ET158: 23993.746 | EU158: 3405927 | EV158: 3093224.5 | EX158: 1950 | EY158: 365027.77 | EZ158: 1026482.7 | FA158: 219779.88 | FB158: 202240.86 | FC158: 346054.11 | FD158: 242147.59 | FE158: 312702.44 | FF158: 17394.526 | FG158: 2731829.9 | FH158: 2419127.4 | FJ158: 1950 | FK158: 409937.77 | FL158: 93521.56 | FM158: 29594.028 | FN158: 21295.484 | FO158: 77351.83 | FP158: 35797.194 | FQ158: 6599.2203 | FR158: 674097.09 | FS158: 1329434.4 | FU158: 1950 | FV158: 134850.86 | FW158: 225031.36 | FX158: 48926.932 | FY158: 49081.276 | FZ158: 85495.898 | GA158: 47980.967 | GB158: 55024.087 | GC158: 4206.1509 | GD158: 650597.53 | GE158: 595573.44 | GG158: 1950 | GH158: 55857.732 | GI158: 204958.38 | GJ158: 42513.482 | GK158: 44082.232 | GL158: 65949.183 | GM158: 41462.394 | GN158: 55024.087 | GO158: 2922.404 | GP158: 512769.89 | GQ158: 457745.81 | GS158: 1950 | GT158: 78993.128 | GU158: 20072.978 | GV158: 6413.4497 | GW158: 4999.0433 | GX158: 19546.715 | GY158: 6518.5731 | GZ158: 1283.747 | HA158: 137827.63 | HC158: 1950 | HD158: 1304.9248 | HE158: 6287.6491 | HF158: 1577.4844 | HG158: 1683.5439 | HH158: 3204.3559 | HI158: 2551.1455 | HJ158: 110.36606 | HK158: 16719.47 | HL158: 14168.324 | HN158: 1950 | HO158: 1845.4041 | HP158: 615.79254 | HQ158: 237.97431 | HR158: 190.91839 | HS158: 838.20723 | HT158: 48.481349 | HU158: 3776.7779 | HW158: 1950 | HX158: 888.70937 | HY158: 2641.4648 | HZ158: 519.53905 | IA158: 408.60573 | IB158: 1280.8743 | IC158: 275.55012 | ID158: 2549.892 | IE158: 8564.6354 | IF158: 8289.0853 | IH158: 1950 | II158: 208.85154 | IJ158: 36.776845 | IK158: 12.874317 | IL158: 230.1399 | IM158: 24.124734 | IN158: 8.4452454 | IO158: 1.6562921
A159: 1950-1951 | B159: 3.9337823 | C159: 3.8855428 | D159: 3.8515139 | E159: 4.0161159 | F159: 4.2320575 | G159: 3.5367438 | H159: 3.2497879 | J159: 1951 | K159: 39426.043 | L159: 36175.878 | M159: 35323.824 | N159: 32073.659 | O159: 4102.2189 | P159: 3250.1647 | Q159: 39651.947 | R159: 79077.99 | S159: 75827.825 | U159: 1951 | V159: 5576.3474 | W159: 76236.873 | X159: 2.7126144 | Y159: 5116.65 | Z159: 68895.011 | AA159: 3.1064927 | AB159: 7070227.2 | AC159: 0.80236425 | AE159: 1951 | AF159: 5059.1167 | AG159: 13055.648 | AH159: 2793.4052 | AI159: 3124.4575 | AJ159: 4016.6368 | AK159: 1949.0571 | AL159: 3455.0015 | AM159: 2722.5552 | AN159: 36175.878 | AP159: 1950-1951 | AQ159: 1.7994337 | AR159: 7.4922465 | AS159: -2.9755197 | AT159: 8.1295872 | AU159: 1.707721 | AV159: 2.813271 | AW159: 3.4192103 | AX159: 0.32599302 | AY159: 3.9337823 | BA159: 1951 | BB159: 23988.854 | BC159: 5201.7383 | BD159: 4761.7715 | BE159: 2969.267 | BF159: -30.054666 | BG159: 1605 | BH159: 11205.133 | BI159: 10275.666 | BJ159: 39426.043 | BL159: 1950-1951 | BM159: -1.0280819 | BN159: 4.8067074 | BO159: 27.622448 | BP159: 6.7256409 | BQ159: 14.729508 | BR159: 3.5367438 | BT159: 1950-1951 | BU159: 12.706538 | BV159: 19.174214 | BW159: 22.369816 | BX159: 48.112125 | BY159: 29.989492 | BZ159: 19.643268 | CB159: 1951 | CC159: 521.10253 | CD159: 3556.4969 | CE159: 143.47905 | CF159: 1287.0836 | CG159: 783.92994 | CH159: 825.58012 | CI159: 2188.3118 | CJ159: 9305.9838 | CL159: 1951 | CM159: 338.14422 | CN159: 1298.2523 | CO159: 91.67521 | CP159: 690.55749 | CQ159: 220.82663 | CR159: 351.45716 | CS159: 1111.306 | CT159: 4102.2189 | CV159: 1951 | CW159: 36604.586 | CX159: 32902.188 | CY159: 12533.259 | CZ159: 1038.5383 | DA159: 13204.265 | DB159: 96282.836 | DC159: 87192.793 | DD159: 28981.883 | DF159: 1951 | DG159: 3.4256279 | DH159: 2.9422702 | DI159: 3.9546593 | DJ159: 9.9962081 | DK159: -2.8939392 | DL159: 12.155164 | DM159: 5.4083274 | DN159: 5.4292839 | DO159: 6.6489785 | DQ159: 1951 | DR159: 62791.7 | DS159: 61390.666 | DT159: 21259.911 | DU159: 1038.5383 | DV159: 13204.265 | DW159: 159685.08 | DX159: 145339.05 | DY159: 41812.82 | EA159: 1951 | EB159: 3.0211554 | EC159: 2.848253 | ED159: 3.1950047 | EE159: 9.5624278 | EF159: -2.8939392 | EG159: 12.155164 | EH159: 4.6189847 | EI159: 4.5937776 | EJ159: 6.3574963 | EL159: 1951 | EM159: 746021.49 | EN159: 1146530.7 | EO159: 257102.82 | EP159: 227563.29 | EQ159: 426697.39 | ER159: 284073.32 | ES159: 326929.97 | ET159: 23138.125 | EU159: 3438057.1 | EV159: 3111127.1 | EX159: 1951 | EY159: 373177.7 | EZ159: 1055536.4 | FA159: 226704.07 | FB159: 205555.4 | FC159: 350523.18 | FD159: 248714.63 | FE159: 326929.97 | FF159: 17424.766 | FG159: 2804566.1 | FH159: 2477636.1 | FJ159: 1951 | FK159: 372843.78 | FL159: 90994.289 | FM159: 30398.752 | FN159: 22007.886 | FO159: 76174.21 | FP159: 35358.696 | FQ159: 5713.3587 | FR159: 633490.98 | FS159: 1314709 | FU159: 1951 | FV159: 127503.06 | FW159: 227741.27 | FX159: 49874.669 | FY159: 49629.689 | FZ159: 85191.736 | GA159: 48348.497 | GB159: 56882.027 | GC159: 3993.5799 | GD159: 649164.53 | GE159: 592282.5 | GG159: 1951 | GH159: 56464.026 | GI159: 208429.91 | GJ159: 43360.754 | GK159: 44521.388 | GL159: 66164.549 | GM159: 42003.349 | GN159: 56882.027 | GO159: 2894.6321 | GP159: 520720.63 | GQ159: 463838.6 | GS159: 1951 | GT159: 71039.034 | GU159: 19311.365 | GV159: 6513.9156 | GW159: 5108.3008 | GX159: 19027.186 | GY159: 6345.1479 | GZ159: 1098.9478 | HA159: 128443.9 | HC159: 1951 | HD159: 1571.9324 | HE159: 7637.0436 | HF159: 1954.6662 | HG159: 2020.7114 | HH159: 3811.0464 | HI159: 3103.5444 | HJ159: 117.01461 | HK159: 20215.959 | HL159: 17112.415 | HN159: 1951 | HO159: 1977.6939 | HP159: 707.58433 | HQ159: 293.64182 | HR159: 231.85265 | HS159: 959.06022 | HT159: 44.424626 | HU159: 4214.2576 | HW159: 1951 | HX159: 1562.3352 | HY159: 4711.0203 | HZ159: 545.09721 | IA159: 819.04857 | IB159: 1195.5873 | IC159: 351.45716 | ID159: 2561.116 | IE159: 11745.662 | IF159: 11394.205 | IH159: 1951 | II159: 201.92964 | IJ159: 54.910186 | IK159: 17.553869 | IL159: 222.01171 | IM159: 40.897786 | IN159: 13.074339 | IO159: 4.8012049
A160: 1951-1952 | B160: 0.70067598 | C160: 0.53415183 | D160: 0.33793589 | E160: 1.0647274 | F160: 1.2448427 | G160: 1.5152727 | H160: 1.0798323 | J160: 1952 | K160: 43006.043 | L160: 40292.583 | M160: 38109.155 | N160: 35395.695 | O160: 4896.8885 | P160: 2713.4599 | Q160: 43614.673 | R160: 86620.717 | S160: 83907.257 | U160: 1952 | V160: 6036.2529 | W160: 76801.159 | X160: 0.74017447 | Y160: 5655.3965 | Z160: 68848.023 | AA160: -0.068202617 | AB160: 7124625.8 | AC160: 0.76940335 | AE160: 1952 | AF160: 6881.3418 | AG160: 12618.048 | AH160: 3282.7171 | AI160: 3520.213 | AJ160: 4626.2063 | AK160: 2164.4988 | AL160: 4263.3511 | AM160: 2936.208 | AN160: 40292.583 | AP160: 1951-1952 | AQ160: 2.6949414 | AR160: -3.5758183 | AS160: 7.0069888 | AT160: 2.808264 | AU160: 2.0835316 | AV160: 0.21364523 | AW160: 4.5260954 | AX160: 0.65884551 | AY160: 0.70067598 | BA160: 1952 | BB160: 26567.019 | BC160: 6325.5741 | BD160: 5816.6146 | BE160: 3156.9082 | BF160: -35.93603 | BG160: 994 | BH160: 10184.485 | BI160: 10002.622 | BJ160: 43006.043 | BL160: 1951-1952 | BM160: 3.7274255 | BN160: 5.5104872 | BO160: -3.6486922 | BP160: -7.7837707 | BQ160: -5.8400938 | BR160: 1.5152727 | BT160: 1951-1952 | BU160: 6.767661 | BV160: 15.253951 | BW160: 10.764026 | BX160: -1.4368199 | BY160: 3.3803144 | BZ160: 7.452101 | CB160: 1952 | CC160: 540.7838 | CD160: 3816.3601 | CE160: 180.05849 | CF160: 1460.022 | CG160: 197.59849 | CH160: 1187.036 | CI160: 2549.7279 | CJ160: 9931.5868 | CL160: 1952 | CM160: 422.9145 | CN160: 1551.014 | CO160: 116.79477 | CP160: 896.00867 | CQ160: 257.84013 | CR160: 416.97744 | CS160: 1235.3391 | CT160: 4896.8885 | CV160: 1952 | CW160: 40545.497 | CX160: 38030.46 | CY160: 16398.883 | CZ160: 1307.0858 | DA160: 15496.476 | DB160: 111778.4 | DC160: 101054.3 | DD160: 33578.922 | DF160: 1952 | DG160: 3.960215 | DH160: 3.2417629 | DI160: 4.7190733 | DJ160: 5.9122258 | DK160: -2.7493246 | DL160: 6.4143616 | DM160: 4.5070696 | DN160: 4.2214276 | DO160: 5.0376303 | DQ160: 1952 | DR160: 69488.437 | DS160: 70603.798 | DT160: 27713.694 | DU160: 1307.0858 | DV160: 15496.476 | DW160: 184609.49 | DX160: 167732.66 | DY160: 48599.245 | EA160: 1952 | EB160: 3.3375908 | EC160: 3.031035 | ED160: 3.6360957 | EE160: 7.0059768 | EF160: -2.7493246 | EG160: 6.4143616 | EH160: 4.1045358 | EI160: 3.8967453 | EJ160: 5.241737 | EL160: 1952 | EM160: 722972.64 | EN160: 1123431.6 | EO160: 263112.71 | EP160: 227271.83 | EQ160: 425241.74 | ER160: 285728.64 | ES160: 341609.36 | ET160: 21896.284 | EU160: 3411264.7 | EV160: 3069655.4 | EX160: 1952 | EY160: 356141.31 | EZ160: 1038586.4 | FA160: 232118.07 | FB160: 205544.39 | FC160: 350373.33 | FD160: 250107.4 | FE160: 341609.36 | FF160: 17037.479 | FG160: 2791517.7 | FH160: 2449908.4 | FJ160: 1952 | FK160: 366831.32 | FL160: 84845.16 | FM160: 30994.636 | FN160: 21727.439 | FO160: 74868.407 | FP160: 35621.238 | FQ160: 4858.8042 | FR160: 619747.01 | FS160: 1300146.7 | FU160: 1952 | FV160: 123714.79 | FW160: 222987.21 | FX160: 51011.073 | FY160: 49297.253 | FZ160: 84839.281 | GA160: 48570.514 | GB160: 59404.863 | GC160: 3762.8953 | GD160: 643587.88 | GE160: 584183.02 | GG160: 1952 | GH160: 53858.025 | GI160: 204990.31 | GJ160: 44372.957 | GK160: 44256.696 | GL160: 66153.149 | GM160: 42212.999 | GN160: 59404.863 | GO160: 2828.8093 | GP160: 518077.81 | GQ160: 458672.95 | GS160: 1952 | GT160: 69856.764 | GU160: 17996.905 | GV160: 6638.116 | GW160: 5040.5578 | GX160: 18686.132 | GY160: 6357.5156 | GZ160: 934.08602 | HA160: 125510.08 | HC160: 1952 | HD160: 1891.1371 | HE160: 8790.6436 | HF160: 2419.2677 | HG160: 2377.375 | HH160: 4428.6232 | HI160: 3846.3737 | HJ160: 127.65231 | HK160: 23881.073 | HL160: 20034.699 | HN160: 1952 | HO160: 2452.9068 | HP160: 771.76514 | HQ160: 361.91818 | HR160: 270.76798 | HS160: 1097.0663 | HT160: 42.151387 | HU160: 4996.5758 | HW160: 1952 | HX160: 2600.8094 | HY160: 3055.6389 | HZ160: 501.53113 | IA160: 808.55838 | IB160: 1265.0155 | IC160: 416.97744 | ID160: 2766.4043 | IE160: 11414.935 | IF160: 10997.958 | IH160: 1952 | II160: 247.47982 | IJ160: 30.67207 | IK160: 9.4846327 | IL160: 279.42074 | IM160: 15.734789 | IN160: 4.865622 | IO160: 9.5686376
A161: 1952-1953 | B161: 1.6550732 | C161: 1.5145134 | D161: 1.4704303 | E161: 1.840052 | F161: 1.6401525 | G161: 2.3883701 | H161: 2.0450477 | J161: 1953 | K161: 44212.135 | L161: 40470.489 | M161: 39154.106 | N161: 35412.46 | O161: 5058.0289 | P161: 3741.6459 | Q161: 43290.231 | R161: 87502.366 | S161: 83760.72 | U161: 1953 | V161: 6165.037 | W161: 78122.234 | X161: 1.7201248 | Y161: 5643.2937 | Z161: 69530.73 | AA161: 0.9916138 | AB161: 7171430.7 | AC161: 0.656945 | AE161: 1953 | AF161: 5364.9296 | AG161: 12815.377 | AH161: 3727.9682 | AI161: 3529.2752 | AJ161: 4930.497 | AK161: 2318.4126 | AL161: 4526.3315 | AM161: 3257.6979 | AN161: 40470.489 | AP161: 1952-1953 | AQ161: -5.4554175 | AR161: 2.1631326 | AS161: 12.252155 | AT161: -0.89333722 | AU161: 2.613384 | AV161: 1.4647827 | AW161: 4.1885416 | AX161: 0.79911158 | AY161: 1.6550732 | BA161: 1953 | BB161: 27674.162 | BC161: 6970.1877 | BD161: 6490.6016 | BE161: 3281.6586 | BF161: -35.696121 | BG161: -516 | BH161: 9531.7105 | BI161: 9184.489 | BJ161: 44212.135 | BL161: 1952-1953 | BM161: 2.4703376 | BN161: 8.7305182 | BO161: -5.6853379 | BP161: 3.8251672 | BQ161: -0.035561878 | BR161: 2.3883701 | BT161: 1952-1953 | BU161: 1.6561094 | BV161: 1.3428396 | BW161: -1.5627127 | BX161: -9.857599 | BY161: -8.1465173 | BZ161: 0.40639416 | CB161: 1953 | CC161: 664.43182 | CD161: 1902.1945 | CE161: 191.86365 | CF161: 1801.2308 | CG161: 376.65328 | CH161: 1474.1998 | CI161: 2809.9903 | CJ161: 9220.5641 | CL161: 1953 | CM161: 426.25547 | CN161: 1572.7096 | CO161: 119.29713 | CP161: 986.65178 | CQ161: 265.18078 | CR161: 443.32673 | CS161: 1244.6074 | CT161: 5058.0289 | CV161: 1953 | CW161: 40594.187 | CX161: 39347.653 | CY161: 17131.631 | CZ161: 1503.7175 | DA161: 16963.278 | DB161: 115540.47 | DC161: 104069.11 | DD161: 34860.68 | DF161: 1953 | DG161: 4.6610083 | DH161: 3.856175 | DI161: 5.4801388 | DJ161: 5.8097632 | DK161: -2.3738582 | DL161: -3.0418648 | DM161: 3.582965 | DN161: 2.9791211 | DO161: 1.9219351 | DQ161: 1953 | DR161: 69429.88 | DS161: 72513.035 | DT161: 29254.989 | DU161: 1503.7175 | DV161: 16963.278 | DW161: 189664.9 | DX161: 171790.86 | DY161: 50220.417 | EA161: 1953 | EB161: 3.7634807 | EC161: 3.407442 | ED161: 4.0996765 | EE161: 6.8393731 | EF161: -2.3738582 | EG161: -3.0418648 | EH161: 3.5560789 | EI161: 3.1518675 | EJ161: 3.0209076 | EL161: 1953 | EM161: 682120.08 | EN161: 1117247.8 | EO161: 254282.71 | EP161: 228424.68 | EQ161: 444794.51 | ER161: 294119.35 | ES161: 358709.95 | ET161: 23198.254 | EU161: 3402897.4 | EV161: 3044187.4 | EX161: 1953 | EY161: 315758.67 | EZ161: 1036945.6 | FA161: 224438.69 | FB161: 206365.48 | FC161: 367381.63 | FD161: 257676.21 | FE161: 358709.95 | FF161: 18568.155 | FG161: 2785844.4 | FH161: 2427134.5 | FJ161: 1953 | FK161: 366361.41 | FL161: 80302.213 | FM161: 29844.022 | FN161: 22059.208 | FO161: 77412.877 | FP161: 36443.14 | FQ161: 4630.0987 | FR161: 617052.97 | FS161: 1285745.8 | FU161: 1953 | FV161: 116283.23 | FW161: 219382.78 | FX161: 48778.495 | FY161: 49160.866 | FZ161: 87741.252 | GA161: 49543.129 | GB161: 61722.992 | GC161: 3931.3146 | GD161: 636544.06 | GE161: 574821.07 | GG161: 1953 | GH161: 47249.221 | GI161: 202528.53 | GJ161: 42453.984 | GK161: 44097.128 | GL161: 68623.064 | GM161: 43129.369 | GN161: 61722.992 | GO161: 3050.5517 | GP161: 512854.84 | GQ161: 451131.85 | GS161: 1953 | GT161: 69034.006 | GU161: 16854.255 | GV161: 6324.5109 | GW161: 5063.7385 | GX161: 19118.189 | GY161: 6413.7598 | GZ161: 880.76293 | HA161: 123689.22 | HC161: 1953 | HD161: 1722.5007 | HE161: 9004.43 | HF161: 2485.0781 | HG161: 2440.4506 | HH161: 4735.3713 | HI161: 4083.0048 | HJ161: 139.61971 | HK161: 24610.455 | HL161: 20527.45 | HN161: 1953 | HO161: 2516.679 | HP161: 749.34116 | HQ161: 370.21033 | HR161: 280.24055 | HS161: 1170.2696 | HT161: 40.311352 | HU161: 5127.052 | HW161: 1953 | HX161: 1171.3654 | HY161: 3061.606 | HZ161: 872.67973 | IA161: 762.96869 | IB161: 1343.2687 | IC161: 443.32673 | ID161: 3077.7668 | IE161: 10732.982 | IF161: 10289.655 | IH161: 1953 | II161: 246.37554 | IJ161: 29.678636 | IK161: 9.2891913 | IL161: 277.18467 | IM161: 15.264828 | IN161: 4.7777772 | IO161: 0.92266596
A162: 1953-1954 | B162: 4.8116237 | C162: 4.8063954 | D162: 4.8179318 | E162: 4.805316 | F162: 4.8790223 | G162: 6.1919937 | H162: 6.2386755 | J162: 1954 | K162: 47063.756 | L162: 42950.98 | M162: 41901.15 | N162: 37788.373 | O162: 5162.6067 | P162: 4112.7768 | Q162: 45480.339 | R162: 92544.095 | S162: 88431.318 | U162: 1954 | V162: 6524.4367 | W162: 82476.205 | X162: 5.5732804 | Y162: 5954.2835 | Z162: 72451.683 | AA162: 4.2009529 | AB162: 7213458.9 | AC162: 0.58605109 | AE162: 1954 | AF162: 5673.6909 | AG162: 13769.315 | AH162: 3943.3495 | AI162: 3704.2949 | AJ162: 5144.4788 | AK162: 2440.462 | AL162: 4724.6691 | AM162: 3550.7192 | AN162: 42950.98 | AP162: 1953-1954 | AQ162: 4.1185591 | AR162: 5.5125944 | AS162: 6.8764629 | AT162: 5.3597877 | AU162: 6.9493119 | AV162: 3.1127678 | AW162: 2.5780724 | AX162: 1.5115907 | AY162: 4.8116237 | BA162: 1954 | BB162: 29238.07 | BC162: 7302.9233 | BD162: 6990.2078 | BE162: 3545.5935 | BF162: -16.718898 | BG162: 166 | BH162: 10434.399 | BI162: 10596.718 | BJ162: 47063.756 | BL162: 1953-1954 | BM162: 4.0330513 | BN162: 4.9571404 | BO162: 19.585517 | BP162: 10.678354 | BQ162: 16.598752 | BR162: 6.1919937 | BT162: 1953-1954 | BU162: 1.5553682 | BV162: -0.174781 | BW162: -3.0959792 | BX162: -1.091434 | BY162: -1.0484786 | BZ162: 0.24283113 | CB162: 1954 | CC162: 575.46262 | CD162: 3180.48 | CE162: 234.46929 | CF162: 1571.1085 | CG162: 512.3376 | CH162: 1517.6379 | CI162: 3093.5865 | CJ162: 10685.082 | CL162: 1954 | CM162: 405.19984 | CN162: 1616.517 | CO162: 115.13527 | CP162: 1019.1922 | CQ162: 265.01834 | CR162: 471.83035 | CS162: 1269.7137 | CT162: 5162.6067 | CV162: 1954 | CW162: 41170.032 | CX162: 41645.053 | CY162: 16904.65 | CZ162: 1375.1465 | DA162: 16892.592 | DB162: 117987.47 | DC162: 105421.44 | DD162: 35421.23 | DF162: 1954 | DG162: 4.9663707 | DH162: 4.430098 | DI162: 5.4938429 | DJ162: 7.4558953 | DK162: -1.2157902 | DL162: 0.98267928 | DM162: 4.6699014 | DN162: 4.235522 | DO162: 3.7869791 | DQ162: 1954 | DR162: 70110.53 | DS162: 75795.599 | DT162: 29149.164 | DU162: 1375.1465 | DV162: 16892.592 | DW162: 193323.03 | DX162: 174050.98 | DY162: 51318.36 | EA162: 1954 | EB162: 3.9826365 | EC162: 3.7711623 | ED162: 4.1772493 | EE162: 7.7677363 | EF162: -1.2157902 | EG162: 0.98267928 | EH162: 4.2455088 | EI162: 3.9352848 | EJ162: 4.3354918 | EL162: 1954 | EM162: 676037.12 | EN162: 1122304.8 | EO162: 266118.48 | EP162: 224046.9 | EQ162: 454196.75 | ER162: 299545.05 | ES162: 365017.51 | ET162: 23816.482 | EU162: 3431083 | EV162: 3066065.5 | EX162: 1954 | EY162: 321250.11 | EZ162: 1045467.7 | FA162: 235000.51 | FB162: 202138.37 | FC162: 376293.58 | FD162: 262823.45 | FE162: 365017.51 | FF162: 19537.623 | FG162: 2827528.8 | FH162: 2462511.3 | FJ162: 1954 | FK162: 354787.01 | FL162: 76837.099 | FM162: 31117.974 | FN162: 21908.523 | FO162: 77903.169 | FP162: 36721.592 | FQ162: 4278.8583 | FR162: 603554.23 | FS162: 1271504.3 | FU162: 1954 | FV162: 115334.89 | FW162: 221106.57 | FX162: 51228.824 | FY162: 48493.489 | FZ162: 89895.588 | GA162: 50657.52 | GB162: 63032.907 | GC162: 4038.1605 | GD162: 643787.95 | GE162: 580755.04 | GG162: 1954 | GH162: 48242.827 | GI162: 204921.93 | GJ162: 44610.76 | GK162: 43446.359 | GL162: 70591.434 | GM162: 44204.874 | GN162: 63032.907 | GO162: 3221.3021 | GP162: 522272.39 | GQ162: 459239.48 | GS162: 1954 | GT162: 67092.065 | GU162: 16184.642 | GV162: 6618.0645 | GW162: 5047.1307 | GX162: 19304.154 | GY162: 6452.6458 | GZ162: 816.8584 | HA162: 121515.56 | HC162: 1954 | HD162: 1857.0083 | HE162: 9626.739 | HF162: 2724.7457 | HG162: 2504.673 | HH162: 4948.8336 | HI162: 4252.8388 | HJ162: 150.2574 | HK162: 26065.096 | HL162: 21812.257 | HN162: 1954 | HO162: 2582.5709 | HP162: 760.31554 | HQ162: 404.21959 | HR162: 290.96596 | HS162: 1195.8918 | HT162: 38.1023 | HU162: 5272.0661 | HW162: 1954 | HX162: 1277.4663 | HY162: 3382.2607 | HZ162: 814.38419 | IA162: 865.30128 | IB162: 1440.2154 | IC162: 471.83035 | ID162: 3362.3595 | IE162: 11613.818 | IF162: 11141.987 | IH162: 1954 | II162: 232.2588 | IJ162: 30.871276 | IK162: 10.156359 | IL162: 259.79611 | IM162: 16.999464 | IN162: 5.5926639 | IO162: 4.4156194
A163: 1954-1955 | B163: 2.5773832 | C163: 2.4353895 | D163: 2.5703404 | E163: 2.5844265 | F163: 2.6977596 | G163: 3.2688864 | H163: 3.0409501 | J163: 1955 | K163: 50685.195 | L163: 45996.447 | M163: 45066.247 | N163: 40377.499 | O163: 5618.9477 | P163: 4688.7476 | Q163: 49264.867 | R163: 99950.062 | S163: 95261.314 | U163: 1955 | V163: 6979.187 | W163: 84599.042 | X163: 2.5738777 | Y163: 6333.5617 | Z163: 73818.867 | AA163: 1.8870283 | AB163: 7262335.1 | AC163: 0.67756896 | AE163: 1955 | AF163: 5598.7348 | AG163: 14765.864 | AH163: 4172.5114 | AI163: 4081.1626 | AJ163: 5757.155 | AK163: 2564.224 | AL163: 5221.8322 | AM163: 3834.9628 | AN163: 45996.447 | AP163: 1954-1955 | AQ163: -3.7548709 | AR163: 4.4438725 | AS163: 2.106362 | AT163: 6.3051374 | AU163: 4.1048085 | AV163: 0.61128785 | AW163: 2.0133019 | AX163: 1.9501001 | AY163: 2.5773832 | BA163: 1955 | BB163: 31130.979 | BC163: 7934.523 | BD163: 7417.0662 | BE163: 3536.3145 | BF163: -51.841958 | BG163: 1154 | BH163: 11387.07 | BI163: 11822.917 | BJ163: 50685.195 | BL163: 1954-1955 | BM163: 3.2015551 | BN163: 2.1039551 | BO163: 8.5579925 | BP163: 5.2314047 | BQ163: 9.5954623 | BR163: 3.2688864 | BT163: 1954-1955 | BU163: 3.1710484 | BV163: 6.4097744 | BW163: 3.9314403 | BX163: 3.7048796 | BY163: 1.8030251 | BZ163: 4.2857662 | CB163: 1955 | CC163: 451.46369 | CD163: 4027.3542 | CE163: 268.29392 | CF163: 1716.4364 | CG163: 731.08092 | CH163: 1625.7583 | CI163: 3235.1513 | CJ163: 12055.539 | CL163: 1955 | CM163: 425.71595 | CN163: 1796.5984 | CO163: 133.64918 | CP163: 1077.8337 | CQ163: 294.29199 | CR163: 523.68622 | CS163: 1367.1723 | CT163: 5618.9477 | CV163: 1955 | CW163: 44629.079 | CX163: 46069.078 | CY163: 18604.178 | CZ163: 1524.1558 | DA163: 18100.415 | DB163: 128926.91 | DC163: 114762.83 | DD163: 38886.348 | DF163: 1955 | DG163: 4.7245303 | DH163: 4.1855648 | DI163: 5.2449308 | DJ163: 5.6592397 | DK163: -3.4013555 | DL163: 6.3755444 | DM163: 4.9949248 | DN163: 4.6520222 | DO163: 5.3667901 | DQ163: 1955 | DR163: 75521.561 | DS163: 82812.114 | DT163: 32181.675 | DU163: 1524.1558 | DV163: 18100.415 | DW163: 210139.92 | DX163: 188668.37 | DY163: 56607.143 | EA163: 1955 | EB163: 3.8921003 | EC163: 3.6564273 | ED163: 4.1063056 | EE163: 6.5894213 | EF163: -3.4013555 | EG163: 6.3755444 | EH163: 4.4700301 | EI163: 4.2093028 | EJ163: 5.3953551 | EL163: 1955 | EM163: 650392.4 | EN163: 1149347.8 | EO163: 276500.08 | EP163: 225786.37 | EQ163: 463467 | ER163: 303202.68 | ES163: 371383.02 | ET163: 23003.353 | EU163: 3463082.7 | EV163: 3091699.7 | EX163: 1955 | EY163: 301274.4 | EZ163: 1074328.3 | FA163: 244287.37 | FB163: 203692.6 | FC163: 385213.43 | FD163: 266215.79 | FE163: 371383.02 | FF163: 19280.635 | FG163: 2865675.6 | FH163: 2494292.5 | FJ163: 1955 | FK163: 349118 | FL163: 75019.509 | FM163: 32212.709 | FN163: 22093.765 | FO163: 78253.574 | FP163: 36986.882 | FQ163: 3722.7181 | FR163: 597407.16 | FS163: 1257420.6 | FU163: 1955 | FV163: 111021.71 | FW163: 225873.91 | FX163: 53109.145 | FY163: 48741.459 | FZ163: 91504.466 | GA163: 51165.128 | GB163: 63993.021 | GC163: 3881.1816 | GD163: 649290.02 | GE163: 585297 | GG163: 1955 | GH163: 45144.892 | GI163: 210106.39 | GJ163: 46273.116 | GK163: 43662.694 | GL163: 72158.018 | GM163: 44705.16 | GN163: 63993.021 | GO163: 3172.0351 | GP163: 529215.33 | GQ163: 465222.31 | GS163: 1955 | GT163: 65876.818 | GU163: 15767.516 | GV163: 6836.0286 | GW163: 5078.7648 | GX163: 19346.449 | GY163: 6459.9677 | GZ163: 709.14647 | HA163: 120074.69 | HC163: 1955 | HD163: 1932.2924 | HE163: 10609.945 | HF163: 2988.9695 | HG163: 2779.9117 | HH163: 5482.8726 | HI163: 4698.146 | HJ163: 160.89509 | HK163: 28653.032 | HL163: 23954.886 | HN163: 1955 | HO163: 2819.6606 | HP163: 796.22745 | HQ163: 441.56699 | HR163: 323.35425 | HS163: 1307.963 | HT163: 35.970027 | HU163: 5724.7424 | HW163: 1955 | HX163: 885.63939 | HY163: 3359.6918 | HZ163: 741.97492 | IA163: 939.039 | IB163: 1530.5435 | IC163: 523.68622 | ID163: 3638.0976 | IE163: 11618.672 | IF163: 11094.986 | IH163: 1955 | II163: 236.19277 | IJ163: 27.631603 | IK163: 9.1660294 | IL163: 265.1242 | IM163: 13.703926 | IN163: 4.5459031 | IO163: 3.956025
A164: 1955-1956 | B164: 3.741558 | C164: 3.5526436 | D164: 3.7617378 | E164: 3.7213822 | F164: 3.702246 | G164: 3.3268267 | H164: 3.1651793 | J164: 1956 | K164: 55096.753 | L164: 50355.898 | M164: 48878.096 | N164: 44137.242 | O164: 6218.6564 | P164: 4740.8545 | Q164: 53553.672 | R164: 108650.43 | S164: 103909.57 | U164: 1956 | V164: 7532.5275 | W164: 86789.971 | X164: 2.5897798 | Y164: 6884.3837 | Z164: 76034.579 | AA164: 3.0015527 | AB164: 7314510.7 | AC164: 0.71844095 | AE164: 1956 | AF164: 6222.9365 | AG164: 16123.946 | AH164: 4452.9982 | AI164: 4493.0251 | AJ164: 6231.7908 | AK164: 2755.3707 | AL164: 5681.1119 | AM164: 4394.7185 | AN164: 50355.898 | AP164: 1955-1956 | AQ164: 0.49507471 | AR164: 4.7000936 | AS164: 3.6828728 | AT164: 4.3223727 | AU164: 5.7172591 | AV164: 1.8544071 | AW164: 4.1994092 | AX164: 2.1421175 | AY164: 3.741558 | BA164: 1956 | BB164: 33661.354 | BC164: 8771.4654 | BD164: 8026.864 | BE164: 3818.8073 | BF164: -52.130313 | BG164: 1104 | BH164: 12952.53 | BI164: 13186.138 | BJ164: 55096.753 | BL164: 1955-1956 | BM164: 2.9075173 | BN164: 5.07565 | BO164: 1.3582294 | BP164: 9.4048925 | BQ164: 7.2280009 | BR164: 3.3268267 | BT164: 1955-1956 | BU164: 5.0731373 | BV164: 5.2081167 | BW164: 5.5507382 | BX164: 3.9694779 | BY164: 4.0123162 | BZ164: 5.2038887 | CB164: 1956 | CC164: 525.23006 | CD164: 4008.9184 | CE164: 287.92777 | CF164: 1838.3972 | CG164: 958.71897 | CH164: 1734.0667 | CI164: 3544.2819 | CJ164: 12897.541 | CL164: 1956 | CM164: 454.86957 | CN164: 1979.0721 | CO164: 156.71889 | CP164: 1237.6143 | CQ164: 330.61293 | CR164: 582.12823 | CS164: 1477.6404 | CT164: 6218.6564 | CV164: 1956 | CW164: 48421.295 | CX164: 50825.829 | CY164: 21100.332 | CZ164: 1630.6991 | DA164: 20417.955 | DB164: 142396.11 | DC164: 126412.59 | DD164: 43143.187 | DF164: 1956 | DG164: 4.6556425 | DH164: 4.2680427 | DI164: 5.021003 | DJ164: 4.804255 | DK164: -3.1968075 | DL164: 5.4070057 | DM164: 4.6999633 | DN164: 4.3803899 | DO164: 4.592769 | DQ164: 1956 | DR164: 81522.619 | DS164: 90384.943 | DT164: 36808.757 | DU164: 1630.6991 | DV164: 20417.955 | DW164: 230764.97 | DX164: 206762.76 | DY164: 62750.774 | EA164: 1956 | EB164: 3.8959276 | EC164: 3.7341452 | ED164: 4.0403327 | EE164: 5.9479961 | EF164: -3.1968075 | EG164: 5.4070057 | EH164: 4.3124105 | EI164: 4.0636633 | EJ164: 4.8314303 | EL164: 1956 | EM164: 638743.12 | EN164: 1155754.8 | EO164: 280076.6 | EP164: 233813.13 | EQ164: 475494.11 | ER164: 314738.56 | ES164: 392008.66 | ET164: 24302.61 | EU164: 3514931.6 | EV164: 3122922.9 | EX164: 1956 | EY164: 299387.09 | EZ164: 1084010.6 | FA164: 247567.53 | FB164: 210614.41 | FC164: 396565.63 | FD164: 275796.49 | FE164: 392008.66 | FF164: 20757.643 | FG164: 2926708.1 | FH164: 2534699.4 | FJ164: 1956 | FK164: 339356.03 | FL164: 71744.187 | FM164: 32509.069 | FN164: 23198.722 | FO164: 78928.479 | FP164: 38942.072 | FQ164: 3544.9665 | FR164: 588223.53 | FS164: 1243492.9 | FU164: 1956 | FV164: 107274.96 | FW164: 223721.99 | FX164: 52992.171 | FY164: 49886.474 | FZ164: 92470.451 | GA164: 52497.357 | GB164: 66540.98 | GC164: 4029.3965 | GD164: 649413.78 | GE164: 582872.8 | GG164: 1956 | GH164: 44193.91 | GI164: 208867.46 | GJ164: 46196.003 | GK164: 44633.135 | GL164: 73252.923 | GM164: 45826.537 | GN164: 66540.98 | GO164: 3364.1679 | GP164: 532875.12 | GQ164: 466334.14 | GS164: 1956 | GT164: 63081.05 | GU164: 14854.525 | GV164: 6796.1681 | GW164: 5253.3387 | GX164: 19217.529 | GY164: 6670.82 | GZ164: 665.22859 | HA164: 116538.66 | HC164: 1956 | HD164: 2033.675 | HE164: 11317.98 | HF164: 3212.9212 | HG164: 2994.3686 | HH164: 6072.28 | HI164: 5098.9837 | HJ164: 178.18134 | HK164: 30908.39 | HL164: 25809.406 | HN164: 1956 | HO164: 2902.8062 | HP164: 804.92772 | HQ164: 472.6719 | HR164: 352.43844 | HS164: 1451.0036 | HT164: 35.233474 | HU164: 6019.0813 | HW164: 1956 | HX164: 1325.0416 | HY164: 4001.0386 | HZ164: 767.40518 | IA164: 1107.6318 | IB164: 1463.8779 | IC164: 582.12823 | ID164: 4181.3037 | IE164: 13428.427 | IF164: 12846.299 | IH164: 1956 | II164: 241.90171 | IJ164: 31.242266 | IK164: 9.8407878 | IL164: 272.09488 | IM164: 16.67889 | IN164: 5.2535697 | IO164: 0.61612552
A165: 1956-1957 | B165: 3.2274098 | C165: 3.0098413 | D165: 3.2252133 | E165: 3.2296064 | F165: 3.1864016 | G165: 2.134949 | H165: 1.8629514 | J165: 1957 | K165: 58785.252 | L165: 53922.757 | M165: 52021.56 | N165: 47159.066 | O165: 6763.6913 | P165: 4862.4941 | Q165: 57043.282 | R165: 115828.53 | S165: 110966.04 | U165: 1957 | V165: 7983.0491 | W165: 88050.052 | X165: 1.4518745 | Y165: 7322.7215 | Z165: 77963.598 | AA165: 2.537029 | AB165: 7363759.2 | AC165: 0.67329909 | AE165: 1957 | AF165: 5805.7253 | AG165: 17506.998 | AH165: 4654.5905 | AI165: 4957.7268 | AJ165: 6993.191 | AK165: 2936.5575 | AL165: 6378.3151 | AM165: 4689.6532 | AN165: 53922.757 | AP165: 1956-1957 | AQ165: 1.5705048 | AR165: 4.4383789 | AS165: 2.4579613 | AT165: 4.5771861 | AU165: 3.6909215 | AV165: 0.53867986 | AW165: 2.8627672 | AX165: 1.8973867 | AY165: 3.2274098 | BA165: 1957 | BB165: 35465.185 | BC165: 9771.4824 | BD165: 8460.1413 | BE165: 4056.9672 | BF165: -15.209928 | BG165: 1169 | BH165: 14381.037 | BI165: 14503.351 | BJ165: 58785.252 | BL165: 1956-1957 | BM165: 1.5164697 | BN165: 3.0378446 | BO165: 1.1737179 | BP165: 8.9735441 | BQ165: 6.9012722 | BR165: 2.134949 | BT165: 1956-1957 | BU165: 3.7848922 | BV165: 8.1163894 | BW165: 4.7665006 | BX165: 1.8860022 | BY165: 2.8887485 | BZ165: 4.4643248 | CB165: 1957 | CC165: 579.93646 | CD165: 4422.2534 | CE165: 327.79428 | CF165: 1948.4636 | CG165: 623.99876 | CH165: 2013.8954 | CI165: 3754.5567 | CJ165: 13670.899 | CL165: 1957 | CM165: 484.65948 | CN165: 2122.1245 | CO165: 179.36092 | CP165: 1394.784 | CQ165: 360.29086 | CR165: 650.13912 | CS165: 1572.3324 | CT165: 6763.6913 | CV165: 1957 | CW165: 51653.524 | CX165: 55775.716 | CY165: 23279.683 | CZ165: 1550.228 | DA165: 23179.395 | DB165: 155438.55 | DC165: 137377.51 | DD165: 47290.389 | DF165: 1957 | DG165: 4.4536531 | DH165: 4.2247345 | DI165: 4.6653825 | DJ165: 4.1635876 | DK165: -0.98114135 | DL165: 5.0432723 | DM165: 4.4435104 | DN165: 4.0341031 | DO165: 4.6565936 | DQ165: 1957 | DR165: 86519.14 | DS165: 98210.517 | DT165: 41036.044 | DU165: 1550.228 | DV165: 23179.395 | DW165: 250495.32 | DX165: 223587.66 | DY165: 68620.348 | EA165: 1957 | EB165: 3.8137538 | EC165: 3.7340847 | ED165: 3.8838355 | EE165: 5.4238092 | EF165: -0.98114135 | EG165: 5.0432723 | EH165: 4.1620303 | EI165: 3.8529548 | EJ165: 4.8237112 | EL165: 1957 | EM165: 617149.66 | EN165: 1155803.9 | EO165: 279713.54 | EP165: 239696.12 | EQ165: 486556.75 | ER165: 315976.44 | ES165: 401454.34 | ET165: 24533.906 | EU165: 3520884.7 | EV165: 3119430.3 | EX165: 1957 | EY165: 277523.88 | EZ165: 1087523.4 | FA165: 247366.33 | FB165: 215891.77 | FC165: 407167.58 | FD165: 275755.91 | FE165: 401454.34 | FF165: 21306.456 | FG165: 2933989.7 | FH165: 2532535.3 | FJ165: 1957 | FK165: 339625.78 | FL165: 68280.477 | FM165: 32347.213 | FN165: 23804.352 | FO165: 79389.173 | FP165: 40220.538 | FQ165: 3227.4497 | FR165: 586894.98 | FS165: 1229719.4 | FU165: 1957 | FV165: 104144.63 | FW165: 223796.23 | FX165: 52944.612 | FY165: 51115.307 | FZ165: 94641.515 | GA165: 52903.037 | GB165: 68175 | GC165: 4060.5855 | GD165: 651780.92 | GE165: 583605.92 | GG165: 1957 | GH165: 40985.022 | GI165: 209652.5 | GJ165: 46179.236 | GK165: 45722.397 | GL165: 75306.005 | GM165: 46041.533 | GN165: 68175 | GO165: 3454.6678 | GP165: 535516.36 | GQ165: 467341.36 | GS165: 1957 | GT165: 63159.61 | GU165: 14143.732 | GV165: 6765.3754 | GW165: 5392.9099 | GX165: 19335.51 | GY165: 6861.5042 | GZ165: 605.91778 | HA165: 116264.56 | HC165: 1957 | HD165: 2050.7394 | HE165: 12106.45 | HF165: 3430.9794 | HG165: 3247.8177 | HH165: 6552.318 | HI165: 5728.176 | HJ165: 192.80817 | HK165: 33309.288 | HL165: 27581.113 | HN165: 1957 | HO165: 3160.2741 | HP165: 816.73431 | HQ165: 502.6472 | HR165: 383.07677 | HS165: 1566.9602 | HT165: 33.816826 | HU165: 6463.5095 | HW165: 1957 | HX165: 627.40592 | HY165: 4583.814 | HZ165: 720.96387 | IA165: 1294.1382 | IB165: 1810.4702 | IC165: 650.13912 | ID165: 4463.0282 | IE165: 14149.96 | IF165: 13499.82 | IH165: 1957 | II165: 245.05986 | IJ165: 33.757842 | IK165: 10.29872 | IL165: 275.33856 | IM165: 19.04863 | IN165: 5.8112868 | IO165: 2.7326875
A166: 1957-1958 | B166: 2.4942974 | C166: 2.2704539 | D166: 2.512584 | E166: 2.4760141 | F166: 2.3622079 | G166: 2.2199484 | H166: 1.8935442 | J166: 1958 | K166: 62087.929 | L166: 56144.792 | M166: 54954.49 | N166: 49011.353 | O166: 7133.4389 | P166: 5943.137 | Q166: 57790.584 | R166: 119878.51 | S166: 113935.38 | U166: 1958 | V166: 8379.9392 | W166: 89453.749 | X166: 1.5942027 | Y166: 7577.8005 | Z166: 79419.079 | AA166: 1.8668723 | AB166: 7409114.6 | AC166: 0.61592652 | AE166: 1958 | AF166: 5801.6556 | AG166: 18037.244 | AH166: 4986.5515 | AI166: 4867.2843 | AJ166: 7281.8079 | AK166: 3093.6977 | AL166: 6883.9379 | AM166: 5192.6131 | AN166: 56144.792 | AP166: 1957-1958 | AQ166: -1.0438899 | AR166: 2.0835698 | AS166: 6.0194663 | AT166: 1.7841902 | AU166: 4.8848632 | AV166: -1.0054289 | AW166: 4.3222086 | AX166: 1.8608151 | AY166: 2.4942974 | BA166: 1958 | BB166: 37907.761 | BC166: 10397.154 | BD166: 9237.9009 | BE166: 4572.465 | BF166: -16.276397 | BG166: 343 | BH166: 13835.225 | BI166: 14189.3 | BJ166: 62087.929 | BL166: 1957-1958 | BM166: 2.4096572 | BN166: 4.6559807 | BO166: 2.6265091 | BP166: 0.051847051 | BQ166: 2.635065 | BR166: 2.2199484 | BT166: 1957-1958 | BU166: 4.372238 | BV166: 1.6693285 | BW166: 0.76353323 | BX166: -3.84521 | BY166: -4.677186 | BZ166: 3.3244584 | CB166: 1958 | CC166: 640.36384 | CD166: 3964.7911 | CE166: 341.99473 | CF166: 2104.5383 | CG166: 903.04246 | CH166: 2192.2305 | CI166: 3990.1285 | CJ166: 14137.089 | CL166: 1958 | CM166: 506.22312 | CN166: 2228.4398 | CO166: 191.32844 | CP166: 1483.9309 | CQ166: 378.62394 | CR166: 700.83814 | CS166: 1644.0546 | CT166: 7133.4389 | CV166: 1958 | CW166: 54028.402 | CX166: 58736.739 | CY166: 24466.366 | CZ166: 1603.5377 | DA166: 24867.845 | DB166: 163702.89 | DC166: 144054.45 | DD166: 49864.194 | DF166: 1958 | DG166: 4.7746839 | DH166: 4.3422975 | DI166: 5.1719771 | DJ166: 5.2990231 | DK166: -1.0150305 | DL166: 1.3792912 | DM166: 4.2733435 | DN166: 3.819153 | DO166: 3.9322746 | DQ166: 1958 | DR166: 90071.011 | DS166: 102693.88 | DT166: 43648.646 | DU166: 1603.5377 | DV166: 24867.845 | DW166: 262884.92 | DX166: 233844.67 | DY166: 72296.325 | EA166: 1958 | EB166: 4.0413208 | EC166: 3.8302474 | ED166: 4.2263401 | EE166: 5.9817453 | EF166: -1.0150305 | EG166: 1.3792912 | EH166: 4.0747411 | EI166: 3.733581 | EJ166: 4.316491 | EL166: 1958 | EM166: 605832.04 | EN166: 1147941.5 | EO166: 285651.01 | EP166: 235575.61 | EQ166: 494932.55 | ER166: 325836.49 | ES166: 423969.43 | ET166: 26527.221 | EU166: 3546265.9 | EV166: 3122296.5 | EX166: 1958 | EY166: 261379.08 | EZ166: 1083337.1 | FA166: 252738.97 | FB166: 212143.74 | FC166: 415719.41 | FD166: 284328.58 | FE166: 423969.43 | FF166: 23378.484 | FG166: 2956994.8 | FH166: 2533025.4 | FJ166: 1958 | FK166: 344452.96 | FL166: 64604.403 | FM166: 32912.039 | FN166: 23431.874 | FO166: 79213.142 | FP166: 41507.912 | FQ166: 3148.7373 | FR166: 589271.07 | FS166: 1216098.6 | FU166: 1958 | FV166: 101142.52 | FW166: 218944.26 | FX166: 53267.56 | FY166: 49531.462 | FZ166: 94856.307 | GA166: 53811.296 | GB166: 70935.603 | GC166: 4317.0827 | GD166: 646806.09 | GE166: 575870.48 | GG166: 1958 | GH166: 38030.88 | GI166: 205759.56 | GJ166: 46485.673 | GK166: 44301.307 | GL166: 75856.043 | GM166: 46864.817 | GN166: 70935.603 | GO166: 3734.6693 | GP166: 531968.55 | GQ166: 461032.94 | GS166: 1958 | GT166: 63111.638 | GU166: 13184.703 | GV166: 6781.8872 | GW166: 5230.1549 | GX166: 19000.264 | GY166: 6946.4784 | GZ166: 582.41343 | HA166: 114837.54 | HC166: 1958 | HD166: 2012.5955 | HE166: 12727.7 | HF166: 3621.5348 | HG166: 3345.2981 | HH166: 6928.3826 | HI166: 6183.0998 | HJ166: 215.41327 | HK166: 35034.024 | HL166: 28850.925 | HN166: 1958 | HO166: 3312.3063 | HP166: 815.56819 | HQ166: 528.35291 | HR166: 394.94156 | HS166: 1623.589 | HT166: 33.593223 | HU166: 6708.3511 | HW166: 1958 | HX166: 506.22312 | HY166: 4493.9757 | HZ166: 836.66382 | IA166: 1097.5754 | IB166: 1823.5341 | IC166: 700.83814 | ID166: 4943.6066 | IE166: 14402.417 | IF166: 13701.579 | IH166: 1958 | II166: 246.68917 | IJ166: 31.191442 | IK166: 9.6378434 | IL166: 277.25542 | IM166: 16.728132 | IN166: 5.1688254 | IO166: 1.1167584
A167: 1958-1959 | B167: 4.3930271 | C167: 4.2114048 | D167: 4.3829891 | E167: 4.4030661 | F167: 4.2952152 | G167: 5.2879246 | H167: 5.2824403 | J167: 1959 | K167: 66111.252 | L167: 59140.327 | M167: 58620.448 | N167: 51649.523 | O167: 7490.8037 | P167: 6970.9247 | Q167: 61389.388 | R167: 127500.64 | S167: 120529.71 | U167: 1959 | V167: 8878.4857 | W167: 93714.532 | X167: 4.7631131 | Y167: 7942.3175 | Z167: 82494.723 | AA167: 3.8726763 | AB167: 7446230.6 | AC167: 0.5009506 | AE167: 1959 | AF167: 5354.2972 | AG167: 19199.685 | AH167: 5425.6555 | AI167: 5128.4683 | AJ167: 7753.5227 | AK167: 3166.4555 | AL167: 7397.5602 | AM167: 5714.6824 | AN167: 59140.327 | AP167: 1958-1959 | AQ167: -3.0719132 | AR167: 5.8897446 | AS167: 8.451173 | AT167: 4.836672 | AU167: 6.4482927 | AV167: 0.072278209 | AW167: 4.4489396 | AX167: 2.7061823 | AY167: 4.3930271 | BA167: 1959 | BB167: 39804.112 | BC167: 11099.198 | BD167: 10300.233 | BE167: 4934.3444 | BF167: -36.341883 | BG167: 1 | BH167: 14383.036 | BI167: 14374.33 | BJ167: 66111.252 | BL167: 1958-1959 | BM167: 3.6077388 | BN167: 5.0310253 | BO167: 7.4464122 | BP167: 6.0849851 | BQ167: 3.481656 | BR167: 5.2879246 | BT167: 1958-1959 | BU167: 1.3462335 | BV167: 1.6388029 | BW167: 0.062145834 | BX167: -2.0035329 | BY167: -2.104378 | BZ167: 1.1322431 | CB167: 1959 | CC167: 720.67915 | CD167: 4027.4094 | CE167: 420.61 | CF167: 2142.7326 | CG167: 1027.7021 | CH167: 2613.6396 | CI167: 4246.4624 | CJ167: 15199.235 | CL167: 1959 | CM167: 516.39121 | CN167: 2376.1019 | CO167: 211.38291 | CP167: 1488.5914 | CQ167: 411.50085 | CR167: 764.24235 | CS167: 1722.5932 | CT167: 7490.8037 | CV167: 1959 | CW167: 56593.513 | CX167: 62152.932 | CY167: 25444.57 | CZ167: 1672.4643 | DA167: 25871.497 | DB167: 171734.98 | DC167: 150329.34 | DD167: 52501.615 | DF167: 1959 | DG167: 5.2493749 | DH167: 4.4596441 | DI167: 5.9707388 | DJ167: 5.9506973 | DK167: -2.1729541 | DL167: 0.0038652575 | DM167: 4.4985886 | DN167: 3.9094569 | DO167: 4.2438959 | DQ167: 1959 | DR167: 93884.319 | DS167: 107582.14 | DT167: 45705.38 | DU167: 1672.4643 | DV167: 25871.497 | DW167: 274715.81 | DX167: 243314.54 | DY167: 76230.381 | EA167: 1959 | EB167: 4.3731351 | EC167: 3.9275179 | ED167: 4.7634001 | EE167: 6.2913924 | EF167: -2.1729541 | EG167: 0.0038652575 | EH167: 4.2439585 | EI167: 3.811305 | EJ167: 4.5481104 | EL167: 1959 | EM167: 582118.21 | EN167: 1156100.3 | EO167: 297362.5 | EP167: 236191.25 | EQ167: 515457.81 | ER167: 329847.45 | ES167: 447959.26 | ET167: 27054.437 | EU167: 3592091.2 | EV167: 3144131.9 | EX167: 1959 | EY167: 238188.77 | EZ167: 1094135.1 | FA167: 263227.43 | FB167: 212438.09 | FC167: 434352.38 | FD167: 287752.96 | FE167: 447959.26 | FF167: 24155.551 | FG167: 3002209.6 | FH167: 2554250.3 | FJ167: 1959 | FK167: 343929.44 | FL167: 61965.123 | FM167: 34135.074 | FN167: 23753.157 | FO167: 81105.431 | FP167: 42094.489 | FQ167: 2898.8859 | FR167: 589881.6 | FS167: 1202628.5 | FU167: 1959 | FV167: 96202.114 | FW167: 217139.75 | FX167: 54614.021 | FY167: 49058.281 | FZ167: 97341.745 | GA167: 53674.966 | GB167: 73821.192 | GC167: 4328.8449 | GD167: 646180.91 | GE167: 572359.72 | GG167: 1959 | GH167: 34134.979 | GI167: 204684.04 | GJ167: 47685.996 | GK167: 43836.223 | GL167: 78191.352 | GM167: 46774.927 | GN167: 73821.192 | GO167: 3800.7173 | GP167: 532929.43 | GQ167: 459108.23 | GS167: 1959 | GT167: 62067.134 | GU167: 12455.706 | GV167: 6928.0247 | GW167: 5222.058 | GX167: 19150.393 | GY167: 6900.0395 | GZ167: 528.12764 | HA167: 113251.48 | HC167: 1959 | HD167: 1920.247 | HE167: 13225.124 | HF167: 3918.1726 | HG167: 3406.08 | HH167: 7373.262 | HI167: 6633.3179 | HJ167: 224.72125 | HK167: 36700.925 | HL167: 30067.607 | HN167: 1959 | HO167: 2942.6043 | HP167: 804.7929 | HQ167: 569.24881 | HR167: 405.75456 | HS167: 1695.9164 | HT167: 31.22608 | HU167: 6449.543 | HW167: 1959 | HX167: 516.39121 | HY167: 5169.7681 | HZ167: 938.23414 | IA167: 1291.6884 | IB167: 1850.7998 | IC167: 764.24235 | ID167: 5458.7351 | IE167: 15989.859 | IF167: 15225.617 | IH167: 1959 | II167: 240.98434 | IJ167: 34.591262 | IK167: 10.664997 | IL167: 270.48444 | IM167: 19.912208 | IN167: 6.1392276 | IO167: 1.5160872
A168: 1959-1960 | B168: 5.6918631 | C168: 5.4722342 | D168: 5.7124433 | E168: 5.6712869 | F168: 5.605287 | G168: 4.2259586 | H168: 4.0675012 | J168: 1960 | K168: 72271.916 | L168: 64446.46 | M168: 63910.944 | N168: 56085.487 | O168: 8360.9725 | P168: 7825.4564 | Q168: 67005.324 | R168: 139277.24 | S168: 131451.78 | U168: 1960 | V168: 9661.5373 | W168: 97229.037 | X168: 3.7502243 | Y168: 8615.4057 | Z168: 86792.234 | AA168: 5.2094377 | AB168: 7480374.4 | AC168: 0.45853813 | AE168: 1960 | AF168: 5995.1605 | AG168: 21147.586 | AH168: 5747.6508 | AI168: 5641.6303 | AJ168: 8249.0171 | AK168: 3423.1486 | AL168: 8048.424 | AM168: 6193.8428 | AN168: 64446.46 | AP168: 1959-1960 | AQ168: 5.3381343 | AR168: 9.0631517 | AS168: 0.59172298 | AT168: 9.1534356 | AU168: 4.4814725 | AV168: 3.0143676 | AW168: 2.8668503 | AX168: 3.4910941 | AY168: 5.6918631 | BA168: 1960 | BB168: 42125.386 | BC168: 11931.465 | BD168: 11235.256 | BE168: 5565.3136 | BF168: -36.047434 | BG168: 1897 | BH168: 16530.295 | BI168: 16976.752 | BJ168: 72271.916 | BL168: 1959-1960 | BM168: 1.7521849 | BN168: 1.7385 | BO168: 16.062142 | BP168: 12.305983 | BQ168: 16.237397 | BR168: 4.2259586 | BT168: 1959-1960 | BU168: 4.009307 | BV168: 5.6615173 | BW168: 5.7875955 | BX168: 2.3356948 | BY168: 1.6064112 | BZ168: 4.8861852 | CB168: 1960 | CC168: 644.06263 | CD168: 6282.1574 | CE168: 410.78383 | CF168: 2541.3216 | CG168: 1697.1674 | CH168: 2542.1841 | CI168: 4543.8451 | CJ168: 18661.522 | CL168: 1960 | CM168: 553.3163 | CN168: 2708.5764 | CO168: 241.2149 | CP168: 1596.9579 | CQ168: 484.24036 | CR168: 857.30441 | CS168: 1919.3623 | CT168: 8360.9725 | CV168: 1960 | CW168: 63212.216 | CX168: 69985.481 | CY168: 28301.067 | CZ168: 1783.1493 | DA168: 26746.512 | DB168: 190028.42 | DC168: 165447.03 | DD168: 58108.008 | DF168: 1960 | DG168: 5.0216945 | DH168: 4.1518602 | DI168: 5.8080971 | DJ168: 6.1822908 | DK168: -2.02156 | DL168: 7.0925137 | DM168: 5.4217514 | DN168: 5.2103671 | DO168: 5.7404608 | DQ168: 1960 | DR168: 104330.05 | DS168: 119670.14 | DT168: 51011.417 | DU168: 1783.1493 | DV168: 26746.512 | DW168: 303541.28 | DX168: 267827.57 | DY168: 85005.378 | EA168: 1960 | EB168: 4.2867873 | EC168: 3.7616307 | ED168: 4.7449752 | EE168: 6.3812928 | EF168: -2.02156 | EG168: 7.0925137 | EH168: 4.8504948 | EI168: 4.6432106 | EJ168: 5.5741821 | EL168: 1960 | EM168: 585924.7 | EN168: 1204676.5 | EO168: 306900 | EP168: 236966.98 | EQ168: 528720.91 | ER168: 339592.31 | ES168: 462402.88 | ET168: 27902.744 | EU168: 3693087 | EV168: 3230684.2 | EX168: 1960 | EY168: 236924.7 | EZ168: 1143076.5 | FA168: 271800 | FB168: 213466.98 | FC168: 447120.91 | FD168: 297800 | FE168: 462402.88 | FF168: 25202.744 | FG168: 3097794.7 | FH168: 2635391.8 | FJ168: 1960 | FK168: 349000 | FL168: 61600 | FM168: 35100 | FN168: 23500 | FO168: 81600 | FP168: 41792.308 | FQ168: 2700 | FR168: 595292.31 | FS168: 1189307.7 | FU168: 1960 | FV168: 95092.355 | FW168: 224485.4 | FX168: 60873.671 | FY168: 48537.404 | FZ168: 98132.883 | GA168: 55274.693 | GB168: 75657.68 | GC168: 4413.0324 | GD168: 662467.12 | GE168: 586809.44 | GG168: 1960 | GH168: 33468.355 | GI168: 212192.69 | GJ168: 53179.671 | GK168: 43422.404 | GL168: 79207.883 | GM168: 48381.693 | GN168: 75657.68 | GO168: 3926.0324 | GP168: 549436.41 | GQ168: 473778.73 | GS168: 1960 | GT168: 61624 | GU168: 12292.713 | GV168: 7694 | GW168: 5115 | GX168: 18925 | GY168: 6893 | GZ168: 487 | HA168: 113030.71 | HC168: 1960 | HD168: 2148.1069 | HE168: 14838.048 | HF168: 4426.9751 | HG168: 3743.2475 | HH168: 8131.1304 | HI168: 7191.1196 | HJ168: 249.98577 | HK168: 40728.613 | HL168: 33537.493 | HN168: 1960 | HO168: 3318.6736 | HP168: 859.59543 | HQ168: 640.49186 | HR168: 440.94083 | HS168: 1821.9932 | HT168: 31.009186 | HU168: 7112.7042 | HW168: 1960 | HX168: 553.3163 | HY168: 5449.9426 | HZ168: 680.18384 | IA168: 1432.5057 | IB168: 1719.042 | IC168: 857.30441 | ID168: 5912.8479 | IE168: 16605.143 | IF168: 15747.838 | IH168: 1960 | II168: 241.2933 | IJ168: 32.349353 | IK168: 10.129745 | IL168: 271.87166 | IM168: 17.463553 | IN168: 5.4684662 | IO168: 3.2524712
A169: 1960-1961 | B169: 5.6199529 | C169: 5.518415 | D169: 5.6382394 | E169: 5.6016695 | F169: 5.4140387 | G169: 5.8221651 | H169: 5.8362166 | J169: 1961 | K169: 78761.471 | L169: 70631.323 | M169: 69640.323 | N169: 61510.176 | O169: 9121.1475 | P169: 8130.1473 | Q169: 72156.58 | R169: 150918.05 | S169: 142787.9 | U169: 1961 | V169: 10473.648 | W169: 102348.18 | X169: 5.265036 | Y169: 9392.5067 | Z169: 91187.296 | AA169: 5.0638884 | AB169: 7519965.2 | AC169: 0.5292632 | AE169: 1961 | AF169: 6505.5849 | AG169: 22945.119 | AH169: 6367.5762 | AI169: 6058.7539 | AJ169: 9409.9141 | AK169: 3692.8979 | AL169: 8930.3012 | AM169: 6721.1763 | AN169: 70631.323 | AP169: 1960-1961 | AQ169: 2.0397021 | AR169: 7.7435356 | AS169: 6.8022028 | AT169: 4.0102291 | AU169: 7.6515324 | AV169: 2.748699 | AW169: 4.1229389 | AX169: 3.2010203 | AY169: 5.6199529 | BA169: 1961 | BB169: 45534.882 | BC169: 12956.065 | BD169: 12479.457 | BE169: 6194.2209 | BF169: -7.3560043 | BG169: 1237 | BH169: 17462.973 | BI169: 17095.772 | BJ169: 78761.471 | BL169: 1960-1961 | BM169: 5.6989727 | BN169: 3.4483457 | BO169: 3.1253426 | BP169: 5.203123 | BQ169: 0.19851205 | BR169: 5.8221651 | BT169: 1960-1961 | BU169: 2.2655975 | BV169: 4.9677223 | BW169: 3.422041 | BX169: 0.41739461 | BY169: 0.50156451 | BZ169: 2.98349 | CB169: 1961 | CC169: 811.08551 | CD169: 6925.9115 | CE169: 488.06621 | CF169: 2292.3483 | CG169: 1528.3336 | CH169: 2639.0074 | CI169: 5218.5698 | CJ169: 19903.322 | CL169: 1961 | CM169: 585.06938 | CN169: 3000.4732 | CO169: 268.20839 | CP169: 1705.9473 | CQ169: 558.26202 | CR169: 928.36608 | CS169: 2074.8212 | CT169: 9121.1475 | CV169: 1961 | CW169: 67975.589 | CX169: 76308.545 | CY169: 31014.383 | CZ169: 1804.8907 | DA169: 30010.486 | DB169: 207113.89 | DC169: 180263.54 | DD169: 63960.254 | DF169: 1961 | DG169: 5.228924 | DH169: 4.62482 | DI169: 5.7670949 | DJ169: 6.4893565 | DK169: -0.40755955 | DL169: 4.1218926 | DM169: 5.2056237 | DN169: 5.0323957 | DO169: 5.9114153 | DQ169: 1961 | DR169: 111771.52 | DS169: 129221.33 | DT169: 56001.471 | DU169: 1804.8907 | DV169: 30010.486 | DW169: 328809.69 | DX169: 289956.26 | DY169: 93316.875 | EA169: 1961 | EB169: 4.4550577 | EC169: 4.0740187 | ED169: 4.7845107 | EE169: 6.5362197 | EF169: -0.40755955 | EG169: 4.1218926 | EH169: 4.7501261 | EI169: 4.5692773 | EJ169: 5.7321615 | EL169: 1961 | EM169: 557518.94 | EN169: 1233030.2 | EO169: 308100 | EP169: 235782.34 | EQ169: 544231.53 | ER169: 335792.31 | ES169: 478931.58 | ET169: 30093.902 | EU169: 3723480.9 | EV169: 3244549.3 | EX169: 1961 | EY169: 220918.94 | EZ169: 1173830.2 | FA169: 271900 | FB169: 211882.34 | FC169: 464331.53 | FD169: 294900 | FE169: 478931.58 | FF169: 27493.902 | FG169: 3144188.5 | FH169: 2665257 | FJ169: 1961 | FK169: 336600 | FL169: 59200 | FM169: 36200 | FN169: 23900 | FO169: 79900 | FP169: 40892.308 | FQ169: 2600 | FR169: 579292.31 | FS169: 1157310.3 | FU169: 1961 | FV169: 92425.592 | FW169: 227800.34 | FX169: 60589.715 | FY169: 47844.883 | FZ169: 101291.27 | GA169: 55284.909 | GB169: 78623.685 | GC169: 4676.1092 | GD169: 668536.5 | GE169: 589912.82 | GG169: 1961 | GH169: 31753.592 | GI169: 215960.93 | GJ169: 52987.715 | GK169: 42732.883 | GL169: 83073.267 | GM169: 48469.909 | GN169: 78623.685 | GO169: 4196.1092 | GP169: 557798.09 | GQ169: 479174.41 | GS169: 1961 | GT169: 60672 | GU169: 11839.412 | GV169: 7602 | GW169: 5112 | GX169: 18218 | GY169: 6815 | GZ169: 480 | HA169: 110738.41 | HC169: 1961 | HD169: 2310.7206 | HE169: 16543.047 | HF169: 4812.9971 | HG169: 4035.6887 | HH169: 9121.6222 | HI169: 8001.9351 | HJ169: 285.88798 | HK169: 45111.899 | HL169: 37109.964 | HN169: 1961 | HO169: 3634.0557 | HP169: 906.92304 | HQ169: 690.50731 | HR169: 482.77671 | HS169: 1874.8833 | HT169: 32.703207 | HU169: 7621.8493 | HW169: 1961 | HX169: 585.06938 | HY169: 5495.1488 | HZ169: 864.07173 | IA169: 1516.0277 | IB169: 2106.3065 | IC169: 928.36608 | ID169: 6402.5851 | IE169: 17897.575 | IF169: 16969.209 | IH169: 1961 | II169: 246.29915 | IJ169: 29.227447 | IK169: 9.1827594 | IL169: 278.47488 | IM169: 14.296159 | IN169: 4.4916066 | IO169: 6.1644697
... A208: 1999-2000 | B208: 4.1468735 | C208: 4.4151082 | D208: 4.2132136 | E208: 4.0805755 | F208: 4.4561857 | G208: 4.1532475 | H208: 4.3674229 | J208: 2000 | K208: 2013310.6 | L208: 1813900.4 | M208: 1761256.2 | N208: 1561845.9 | O208: 252054.47 | P208: 199410.27 | Q208: 1929457.1 | R208: 3942767.7 | S208: 3743357.5 | U208: 2000 | V208: 226925.99 | W208: 226925.99 | X208: 3.9862042 | Y208: 204449.89 | Z208: 204449.89 | AA208: 3.9798403 | AB208: 8872102.6 | AC208: 0.16063992 | AE208: 2000 | AF208: 28048.859 | AG208: 453831 | AH208: 82547.997 | AI208: 130633.84 | AJ208: 389056.54 | AK208: 148300.16 | AL208: 369860.84 | AM208: 211621.13 | AN208: 1813900.4 | AP208: 1999-2000 | AQ208: 0.45343962 | AR208: 6.2135096 | AS208: 1.683554 | AT208: 5.3260264 | AU208: 7.0616033 | AV208: 7.4108526 | AW208: -1.0415111 | AX208: 2.4609129 | AY208: 4.1468735 | BA208: 2000 | BB208: 1069367.1 | BC208: 541739.11 | BD208: 130593.19 | BE208: 161873.87 | BF208: 692.73255 | BG208: 3514.4259 | BH208: 963286.85 | BI208: 857756.6 | BJ208: 2013310.6 | BL208: 1999-2000 | BM208: 4.9551664 | BN208: -1.2207302 | BO208: 9.6118466 | BP208: 11.300362 | BQ208: 11.525345 | BR208: 4.1532475 | BT208: 1999-2000 | BU208: 0.12359277 | BV208: 6.4243454 | BW208: 1.4213399 | BX208: 2.1737797 | BY208: 4.5285708 | BZ208: 1.1477094 | CB208: 2000 | CC208: 10581.963 | CD208: 81410.975 | CE208: 6206.543 | CF208: 67589.635 | CG208: 56801.17 | CH208: 29745.374 | CI208: 44338.56 | CJ208: 296674.22 | CL208: 2000 | CM208: 9797.0829 | CN208: 70856.919 | CO208: 4609.214 | CP208: 29761.72 | CQ208: 34820.913 | CR208: 29510.291 | CS208: 72698.33 | CT208: 252054.47 | CV208: 2000 | CW208: 2351563.9 | CX208: 1786653.5 | CY208: 824066.18 | CZ208: 31191.278 | DA208: 207551 | DB208: 5201025.8 | DC208: 4451830.9 | DD208: 1030578 | DF208: 2000 | DG208: -0.22481936 | DH208: -1.2059962 | DI208: 1.0937326 | DJ208: 5.9377263 | DK208: 2.2209175 | DL208: 1.6975071 | DM208: 0.81721254 | DN208: 0.94886066 | DO208: 1.0164767 | DQ208: 2000 | DR208: 4476149.7 | DS208: 3355625.2 | DT208: 1620381.4 | DU208: 31191.278 | DV208: 207551 | DW208: 9690898.5 | DX208: 8372488.4 | DY208: 1965472.3 | EA208: 2000 | EB208: 0.84787273 | EC208: 0.24076848 | ED208: 1.6746851 | EE208: 4.7192429 | EF208: 2.2209175 | EG208: 1.6975071 | EH208: 1.5017525 | EI208: 1.5424118 | EJ208: 1.5330235 | EL208: 2000 | EM208: 134052.42 | EN208: 863904.51 | EO208: 227342.93 | EP208: 284978.33 | EQ208: 940600.79 | ER208: 441248.75 | ES208: 1237293.6 | ET208: 56929.758 | EU208: 4186351.1 | EV208: 2949057.5 | EX208: 2000 | EY208: 62024.96 | EZ208: 835325.17 | FA208: 187859.05 | FB208: 263856.22 | FC208: 850681.55 | FD208: 369051.44 | FE208: 1237293.6 | FF208: 51774.338 | FG208: 3857866.4 | FH208: 2620572.7 | FJ208: 2000 | FK208: 72027.46 | FL208: 28579.345 | FM208: 39483.871 | FN208: 21122.105 | FO208: 89919.234 | FP208: 72197.309 | FQ208: 5155.4198 | FR208: 328484.74 | FS208: 224000 | FU208: 2000 | FV208: 18760.963 | FW208: 140366.58 | FX208: 40130.002 | FY208: 49086.945 | FZ208: 143958.38 | GA208: 72349.052 | GB208: 171842.03 | GC208: 8442.9023 | GD208: 644936.85 | GE208: 473094.82 | GG208: 2000 | GH208: 7571.7644 | GI208: 134969.2 | GJ208: 33940.424 | GK208: 45300.279 | GL208: 128527.98 | GM208: 62243.278 | GN208: 171842.03 | GO208: 7443.0855 | GP208: 591838.04 | GQ208: 419996.01 | GS208: 2000 | GT208: 11189.198 | GU208: 5397.3772 | GV208: 6189.5783 | GW208: 3786.6667 | GX208: 15430.402 | GY208: 10105.774 | GZ208: 999.81672 | HA208: 53098.813 | HC208: 2000 | HD208: 10077.829 | HE208: 283970.7 | HF208: 73612.356 | HG208: 81214.032 | HH208: 397116.36 | HI208: 340350.55 | HJ208: 13776.483 | HK208: 1200118.3 | HL208: 859767.76 | HN208: 2000 | HO208: 8173.9473 | HP208: 11355.902 | HQ208: 13424.389 | HR208: 6788.7103 | HS208: 52489.271 | HT208: 1850.571 | HU208: 94082.79 | HW208: 2000 | HX208: 9797.0829 | HY208: 158504.4 | HZ208: -4488.7476 | IA208: 42631.094 | IB208: 87751.076 | IC208: 29510.291 | ID208: 195994.08 | IE208: 519699.27 | IF208: 490188.98 | IH208: 2000 | II208: 199.53053 | IJ208: 50.296817 | IK208: 16.771865 | IL208: 231.25564 | IM208: 29.678153 | IN208: 9.8964109 | IO208: 6.1988359
CV209: 2001 | CW209: 2527611.2 | CX209: 1885064.2 | CY209: 877139.66 | CZ209: 31581.789 | DA209: 210025.03 | DB209: 5531421.8 | DC209: 4754705.3 | DD209: 1072118.7 | DQ209: 2001 | DR209: 4881709 | DS209: 3561092.4 | DT209: 1706767.8 | DU209: 31581.789 | DV209: 210025.03 | DW209: 10391176 | DX209: 9007860.7 | DY209: 2061374
U211: Comments: | AE211: Comments: | AP211: Comments: | BA211: Comment: | BL211: Comment: | BT211: Comment: | CL211: Comments: | CV211: Comment | DF211: Comment: | DQ211: Comment | EA211: Comment: | EL211: Comments: | EX211: Comments: | FJ211: Comments: | FU211: Comments: | GG211: Comments: | GS211: Comments: | IH211: Comments
U212: The per capita and population figures are based on estimates of population during the whole year. | AE212: Circulation includes wholesale and retail trade, banking, insurance and business services. | AP212: Circulation includes wholesale and retail trade, banking, insurance and business services. | BA212: Import and export are recorded on the c.i.f./f.o.b.-basis. | BL212: Import and export are recorded on the c.i.f./f.o.b.-basis. | BT212: Import and export are recorded on the c.i.f./f.o.b.-basis. | CL212: Investment in services of dwellings only consists of investment in residential buildings. | CV212: The gross and net stocks are equal for fixed livestock and the inventory stock. | DF212: The volume change during the year is measured from 1st of January at the beginning of the year | DQ212: The gross and net stocks are equal for fixed livestock and the inventory stock. | EA212: The volume change during the year is measured from 1st of January at the beginning of the year | EL212: Circulation includes wholesale and retail trade, banking, insurance and business services. | EX212: Circulation includes wholesale and retail trade, banking, insurance and business services. | FJ212: Circulation includes wholesale and retail trade, banking, insurance and business services. | FU212: Circulation includes wholesale and retail trade, banking, insurance and business services. | GG212: Circulation includes wholesale and retail trade, banking, insurance and business services. | GS212: Circulation includes wholesale and retail trade, banking, insurance and business services. | IH212: The ratio of net surplus to labour income is the same expressed in purchasers’ proxy values
U213: For this purpose a geometric average is computed of the population at the end of the year and | AE213: Private reproductive services include restaurants, hotels, sanitary services, sewage plants, education, R&D, | AP213: Private reproductive services include restaurants, hotels, sanitary services, sewage plants, education, R&D, | CL213: Investment includes fixed investment and changes in inventories. | DF213: to the 1st of January the next year. | EA213: to the 1st of January the next year. | EL213: Private reproductive services include restaurants, hotels, sanitary services, sewage plants, education, R&D, | EX213: Private reproductive services include restaurants, hotels, sanitary services, sewage plants, education, R&D, | FJ213: Private reproductive services include restaurants, hotels, sanitary services, sewage plants, education, R&D, | FU213: Private reproductive services include restaurants, hotels, sanitary services, sewage plants, education, R&D, | GG213: Private reproductive services include restaurants, hotels, sanitary services, sewage plants, education, R&D, | GS213: Private reproductive services include restaurants, hotels, sanitary services, sewage plants, education, R&D, | IH213: as in basic values. However, this equality does not hold for the ratio of gross surplus to labour income.
U214: at the end of the preceding year. Population figures (at the end of the year) are obtained from | AE214: health services, community services, recreation, other personal services, non-government associations, | AP214: health services, community services, recreation, other personal services, non-government associations, | CL214: Net investment can be obtained by deducting consumption of fixed assets from gross investment. | EL214: health services, community services, recreation, other personal services, non-government associations, | EX214: health services, community services, recreation, other personal services, non-government associations, | FJ214: health services, community services, recreation, other personal services, non-government associations, | FU214: health services, community services, recreation, other personal services, non-government associations, | GG214: health services, community services, recreation, other personal services, non-government associations, | GS214: health services, community services, recreation, other personal services, non-government associations, | IH214: The real wage rate is calculated as wages and salaries (including social benefits) at factor costs
U215: Statistiska databaser, online at http://www.scb.se (030601). | AE215: and paid household services. | AP215: and paid household services. | EL215: and paid household services. | EX215: and paid household services. | FJ215: and paid household services. | FU215: and paid household services. | GG215: and paid household services. | GS215: and paid household services. | IH215: per employed deflated by the price index of private final consumption.
EL216: The calculated figures for the period 1850-1950 of employment in trade (which is included in circulation) and in
EL217: building and construction are not comparable with the estimate of the total value added of these activities
EL218: (for example, if productivity is computed). This partly also pertains to other types of activities, but on the aggregate level
EL219: employment should be comparable with value added. Employment excludes “housewives”. The aggregate employment
EL220: figures also involve certain double counting, as individuals working in two different activities tend to be counted twice
EL221: by Statistics Sweden.

Sheet Explanations
A8: Glossary:
A9: Activity: In the SNA, described to take place when resources are combined leading to the creation of particular goods or services. Not all activities are defined as being productive in an economic sense and counted into aggregate production.
A10: Asset: In the 1993 SNA, defined as an entity over which an institutional unit exercises ownership rights, that functions as a store of value, and from which economic benefits can be derived by their owner through holding it. There are two main types of assets, financial and non-financial. Non-financial assets are either produced or non-produced.
A11: Base period: The period that provides the weights for a volume or price index. The base period is mostly situated earlier than the compared period.
A12: Basic prices: A type of price of a unit of good or services produced as output, which includes the excess of non-commodity related indirect taxes over non-commodity-related subsidies, but excludes the excess of commodity related indirect taxes over commodity-related subsidies. It also excludes transport charges invoiced separately by the producer.
A13: Benchmark series: In Edvinsson, 2005, defined as the data series for a time period which is kept unchanged when linking consecutive series for the same variable(s) to each other, and to which the other data series are adjusted.
A14: Buildings and structures: A type of fixed assets estimated in Edvinsson, 2005. Are subdivided between dwellings (residential buildings), and non-residential buildings and structures.
A15: Capacity stock: The stock of fixed assets that are believed to have been installed at a given point in time and that still have not been scrapped. Some of these objects may be temporarily idle or even be withdrawn from production for an indefinite period and held in reserve to meet unexpected rise in demand. See also utilised stock.
A16: Chain index: Is obtained by linking a price or volume index for consecutive periods. The short-term movements are calculated on the basis of weights pertaining to the relevant period. An annual chain index changes weights for every year.
A17: Changes in fixed livestock: The fixed livestock acquired less the fixed livestock disposed of, in the course of the accounting period. There is no difference between net and gross changes in fixed livestock.
A18: Changes in (the stock of) inventories: Is set equal to the inventories acquired less the inventories disposed of, in the course of the accounting period. Some of these transactions reflect actual purchases and sales, while other are internal to the enterprise. There is no difference between net and gross changes in inventories.
A19: C.i.f. (costs, insurance, freight) price: The c.i.f. prices of imported goods can be regarded as the purchasers’ prices that would be paid by importers if taking delivery of goods at their own frontier. The c.i.f. price is equal to the f.o.b. price plus the costs of transports and insurances between the customs frontier of the exporting and importing country. Exported goods are normally not expressed in c.i.f. prices.
... A109: Volume value: The value expressed in the same price level over time, connected to the construction of a volume index.

Sheet About file
A1: File name (filnamn): Historical national accounts for Sweden 1800-2000 (Historiska nationalräkenskaper för Sverige 1800-2000)
A2: Author (författare): Rodney Edvinsson
A3: Benchmark period: 1980-94
A5: Version 1.0
A6: Is based on methods and data presented in Edvinsson, R., 2005: Growth, Accumulation, Crisis: With New Macroeconomic Data for Sweden. Almqvist & Wiksell International; Stockholm. Online at: http://www.diva-portal.org/su/theses/abstract.xsql?dbid=378 (050320).
A9: Updates:
A11: update: 050404
A12: New headlines were written in Swedish
A13: Some of the headlines in English were inaccurate and therefore corrected
A14: Comments have been inserted below the tables

Sheet Sweden
G5: Wages and Saleries of Goverment services | O5: Mixed income = imputed self-employed labour income / 0.7 | V5: Real Estate Gros Surplus | Y5: gross value added less labour income (of both employees and self-employed). The gross surplus includes consumption of fixed assets. | AB5: Capital Shares
AB6: Total economy | AD6: In Corporations
AB7: NET | AC7: Gross
A8: iso | B8: year | C8: confc | D8: comhn | E8: cfcgo | F8: nsrgo | G8: ceugo | H8: cfcco | I8: nsrco | J8: gsrco | K8: ceuco | L8: ceuhn | M8: cfchn | N8: nmxhn | O8: gmxhn | P8: ccmhn | Q8: nsrhn | R8: ccshn | S8: ptxgo | T8: source | V8: gsrhn | W8: self-employed Imputed labour income | Y8: mios | AA8: check | AB8: cshare_net | AC8: cshare_gross | AG8: check shares
A9: SE | B9: 1800 | C9: =Data!CT8/Data!K8 -> 0.035728484 | S9: =(Data!K8-Data!AN8)/Data!K8 -> 0.045805909
A10: SE | B10: 1801 | C10: =Data!CT9/Data!K9 -> 0.03496984 | S10: =(Data!K9-Data!AN9)/Data!K9 -> 0.046004732
A11: SE | B11: 1802 | C11: =Data!CT10/Data!K10 -> 0.034302731 | S11: =(Data!K10-Data!AN10)/Data!K10 -> 0.046199733
A12: SE | B12: 1803 | C12: =Data!CT11/Data!K11 -> 0.035350974 | S12: =(Data!K11-Data!AN11)/Data!K11 -> 0.045993514
A13: SE | B13: 1804 | C13: =Data!CT12/Data!K12 -> 0.03833599 | S13: =(Data!K12-Data!AN12)/Data!K12 -> 0.046011788
A14: SE | B14: 1805 | C14: =Data!CT13/Data!K13 -> 0.037317483 | S14: =(Data!K13-Data!AN13)/Data!K13 -> 0.046253893
A15: SE | B15: 1806 | C15: =Data!CT14/Data!K14 -> 0.035959416 | S15: =(Data!K14-Data!AN14)/Data!K14 -> 0.046085832
A16: SE | B16: 1807 | C16: =Data!CT15/Data!K15 -> 0.034426121 | S16: =(Data!K15-Data!AN15)/Data!K15 -> 0.046297559
A17: SE | B17: 1808 | C17: =Data!CT16/Data!K16 -> 0.036619401 | S17: =(Data!K16-Data!AN16)/Data!K16 -> 0.045799878
A18: SE | B18: 1809 | C18: =Data!CT17/Data!K17 -> 0.037981201 | S18: =(Data!K17-Data!AN17)/Data!K17 -> 0.047242647
A19: SE | B19: 1810 | C19: =Data!CT18/Data!K18 -> 0.041272628 | S19: =(Data!K18-Data!AN18)/Data!K18 -> 0.047619042
A20: SE | B20: 1811 | C20: =Data!CT19/Data!K19 -> 0.042842098 | S20: =(Data!K19-Data!AN19)/Data!K19 -> 0.047371776
... A58: SE | B58: 1849 | C58: =Data!CT57/Data!K57 -> 0.040772627 | S58: =(Data!K57-Data!AN57)/Data!K57 -> 0.047813893
A59: SE | B59: 1850 | C59: =Data!CT58/Data!K58 -> 0.040845746 | D59: =Data!HK58/Data!K58 -> 0.51615453 | E59: =Data!IC58/Data!K58 -> 0.0016050153 | F59: 0 | G59: =Data!HI58/Data!K58 -> 0.056546621 | I59: =Y59-O59 -> 0.01635138 | O59: =W59/0.7 -> 0.24689269 | S59: =(Data!K58-Data!AN58)/Data!K58 -> 0.047776527 | W59: =Data!HU58/Data!K58 -> 0.17282488 | Y59: =Data!IE58/Data!K58 -> 0.26324407 | AA59: =D59+Y59+W59+S59 -> 1 | AB59: =(Y59-C59)/(1-S59-C59) -> 0.24402431 | AC59: =(Y59)/(1-S59) -> 0.27645198 | AG59: =AC59+D59+W59+S59 -> 1.0132079
A60: SE | B60: 1851 | C60: =Data!CT59/Data!K59 -> 0.040437791 | D60: =Data!HK59/Data!K59 -> 0.50516417 | E60: =Data!IC59/Data!K59 -> 0.0015575481 | F60: 0 | G60: =Data!HI59/Data!K59 -> 0.058486391 | I60: =Y60-O60 -> 0.036980142 | O60: =W60/0.7 -> 0.2412795 | S60: =(Data!K59-Data!AN59)/Data!K59 -> 0.047680537 | W60: =Data!HU59/Data!K59 -> 0.16889565 | Y60: =Data!IE59/Data!K59 -> 0.27825964 | AA60: =D60+Y60+W60+S60 -> 1 | AB60: =(Y60-C60)/(1-S60-C60) -> 0.26080341 | AC60: =(Y60)/(1-S60) -> 0.29219149 | AG60: =AC60+D60+W60+S60 -> 1.0139318
A61: SE | B61: 1852 | C61: =Data!CT60/Data!K60 -> 0.041063533 | D61: =Data!HK60/Data!K60 -> 0.50199465 | E61: =Data!IC60/Data!K60 -> 0.0015597387 | F61: 0 | G61: =Data!HI60/Data!K60 -> 0.056349185 | I61: =Y61-O61 -> 0.039535952 | O61: =W61/0.7 -> 0.2415768 | S61: =(Data!K60-Data!AN60)/Data!K60 -> 0.047788839 | W61: =Data!HU60/Data!K60 -> 0.16910376 | Y61: =Data!IE60/Data!K60 -> 0.28111275 | AA61: =D61+Y61+W61+S61 -> 1 | AB61: =(Y61-C61)/(1-S61-C61) -> 0.26345809 | AC61: =(Y61)/(1-S61) -> 0.29522102 | AG61: =AC61+D61+W61+S61 -> 1.0141083
A62: SE | B62: 1853 | C62: =Data!CT61/Data!K61 -> 0.042419454 | D62: =Data!HK61/Data!K61 -> 0.49919578 | E62: =Data!IC61/Data!K61 -> 0.0016000409 | F62: 0 | G62: =Data!HI61/Data!K61 -> 0.058526779 | I62: =Y62-O62 -> 0.048663287 | O62: =W62/0.7 -> 0.23792036 | S62: =(Data!K61-Data!AN61)/Data!K61 -> 0.047676333 | W62: =Data!HU61/Data!K61 -> 0.16654425 | Y62: =Data!IE61/Data!K61 -> 0.28658364 | AA62: =D62+Y62+W62+S62 -> 1 | AB62: =(Y62-C62)/(1-S62-C62) -> 0.26834054 | AC62: =(Y62)/(1-S62) -> 0.30093093 | AG62: =AC62+D62+W62+S62 -> 1.0143473
A63: SE | B63: 1854 | C63: =Data!CT62/Data!K62 -> 0.041926581 | D63: =Data!HK62/Data!K62 -> 0.46786376 | E63: =Data!IC62/Data!K62 -> 0.0015761005 | F63: 0 | G63: =Data!HI62/Data!K62 -> 0.049986988 | I63: =Y63-O63 -> 0.10373498 | O63: =W63/0.7 -> 0.22370031 | S63: =(Data!K62-Data!AN62)/Data!K62 -> 0.04811074 | W63: =Data!HU62/Data!K62 -> 0.15659022 | Y63: =Data!IE62/Data!K62 -> 0.32743529 | AA63: =D63+Y63+W63+S63 -> 1 | AB63: =(Y63-C63)/(1-S63-C63) -> 0.3137587 | AC63: =(Y63)/(1-S63) -> 0.34398464 | AG63: =AC63+D63+W63+S63 -> 1.0165494
A64: SE | B64: 1855 | C64: =Data!CT63/Data!K63 -> 0.046550427 | D64: =Data!HK63/Data!K63 -> 0.50583191 | E64: =Data!IC63/Data!K63 -> 0.0017080172 | F64: 0 | G64: =Data!HI63/Data!K63 -> 0.047405755 | I64: =Y64-O64 -> 0.032940956 | O64: =W64/0.7 -> 0.24293656 | S64: =(Data!K63-Data!AN63)/Data!K63 -> 0.048234985 | W64: =Data!HU63/Data!K63 -> 0.17005559 | Y64: =Data!IE63/Data!K63 -> 0.27587751 | AA64: =D64+Y64+W64+S64 -> 1 | AB64: =(Y64-C64)/(1-S64-C64) -> 0.25334002 | AC64: =(Y64)/(1-S64) -> 0.28985885 | AG64: =AC64+D64+W64+S64 -> 1.0139813
A65: SE | B65: 1856 | C65: =Data!CT64/Data!K64 -> 0.046832265 | D65: =Data!HK64/Data!K64 -> 0.48265772 | E65: =Data!IC64/Data!K64 -> 0.001648962 | F65: 0 | G65: =Data!HI64/Data!K64 -> 0.042471109 | I65: =Y65-O65 -> 0.068347622 | O65: =W65/0.7 -> 0.23559198 | S65: =(Data!K64-Data!AN64)/Data!K64 -> 0.048488297 | W65: =Data!HU64/Data!K64 -> 0.16491439 | Y65: =Data!IE64/Data!K64 -> 0.3039396 | AA65: =D65+Y65+W65+S65 -> 1 | AB65: =(Y65-C65)/(1-S65-C65) -> 0.28419717 | AC65: =(Y65)/(1-S65) -> 0.31942813 | AG65: =AC65+D65+W65+S65 -> 1.0154885
A66: SE | B66: 1857 | C66: =Data!CT65/Data!K65 -> 0.050926999 | D66: =Data!HK65/Data!K65 -> 0.49061552 | E66: =Data!IC65/Data!K65 -> 0.0017522117 | F66: 0 | G66: =Data!HI65/Data!K65 -> 0.04146051 | I66: =Y66-O66 -> 0.045841332 | O66: =W66/0.7 -> 0.24412284 | S66: =(Data!K65-Data!AN65)/Data!K65 -> 0.048534324 | W66: =Data!HU65/Data!K65 -> 0.17088599 | Y66: =Data!IE65/Data!K65 -> 0.28996417 | AA66: =D66+Y66+W66+S66 -> 1 | AB66: =(Y66-C66)/(1-S66-C66) -> 0.26543798 | AC66: =(Y66)/(1-S66) -> 0.30475526 | AG66: =AC66+D66+W66+S66 -> 1.0147911
A67: SE | B67: 1858 | C67: =Data!CT66/Data!K66 -> 0.049153319 | D67: =Data!HK66/Data!K66 -> 0.48620867 | E67: =Data!IC66/Data!K66 -> 0.001627765 | F67: 0 | G67: =Data!HI66/Data!K66 -> 0.048612705 | I67: =Y67-O67 -> 0.061619518 | O67: =W67/0.7 -> 0.23764351 | S67: =(Data!K66-Data!AN66)/Data!K66 -> 0.048177832 | W67: =Data!HU66/Data!K66 -> 0.16635046 | Y67: =Data!IE66/Data!K66 -> 0.29926303 | AA67: =D67+Y67+W67+S67 -> 1 | AB67: =(Y67-C67)/(1-S67-C67) -> 0.27707804 | AC67: =(Y67)/(1-S67) -> 0.31441066 | AG67: =AC67+D67+W67+S67 -> 1.0151476
A68: SE | B68: 1859 | C68: =Data!CT67/Data!K67 -> 0.050368957 | D68: =Data!HK67/Data!K67 -> 0.49338178 | E68: =Data!IC67/Data!K67 -> 0.0016440621 | F68: 0 | G68: =Data!HI67/Data!K67 -> 0.049765833 | I68: =Y68-O68 -> 0.048677524 | O68: =W68/0.7 -> 0.24107187 | S68: =(Data!K67-Data!AN67)/Data!K67 -> 0.048118511 | W68: =Data!HU67/Data!K67 -> 0.16875031 | Y68: =Data!IE67/Data!K67 -> 0.28974939 | AA68: =D68+Y68+W68+S68 -> 1 | AB68: =(Y68-C68)/(1-S68-C68) -> 0.26553201 | AC68: =(Y68)/(1-S68) -> 0.3043965 | AG68: =AC68+D68+W68+S68 -> 1.0146471
A69: SE | B69: 1860 | C69: =Data!CT68/Data!K68 -> 0.050335017 | D69: =Data!HK68/Data!K68 -> 0.50046462 | E69: =Data!IC68/Data!K68 -> 0.0016241738 | F69: 0 | G69: =Data!HI68/Data!K68 -> 0.049440186 | I69: =Y69-O69 -> 0.033888112 | O69: =W69/0.7 -> 0.24559484 | S69: =(Data!K68-Data!AN68)/Data!K68 -> 0.048136039 | W69: =Data!HU68/Data!K68 -> 0.17191639 | Y69: =Data!IE68/Data!K68 -> 0.27948295 | AA69: =D69+Y69+W69+S69 -> 1 | AB69: =(Y69-C69)/(1-S69-C69) -> 0.25417701 | AC69: =(Y69)/(1-S69) -> 0.29361649 | AG69: =AC69+D69+W69+S69 -> 1.0141335
A70: SE | B70: 1861 | C70: =Data!CT69/Data!K69 -> 0.050253374 | D70: =Data!HK69/Data!K69 -> 0.50073655 | E70: =Data!IC69/Data!K69 -> 0.0016188052 | F70: 0 | G70: =Data!HI69/Data!K69 -> 0.048900151 | I70: =Y70-O70 -> 0.034634573 | O70: =W70/0.7 -> 0.24497951 | S70: =(Data!K69-Data!AN69)/Data!K69 -> 0.048163705 | W70: =Data!HU69/Data!K69 -> 0.17148566 | Y70: =Data!IE69/Data!K69 -> 0.27961409 | AA70: =D70+Y70+W70+S70 -> 1 | AB70: =(Y70-C70)/(1-S70-C70) -> 0.2543978 | AC70: =(Y70)/(1-S70) -> 0.29376279 | AG70: =AC70+D70+W70+S70 -> 1.0141487
... A209: SE | B209: 2000 | C209: =Data!CT208/Data!K208 -> 0.12519403 | D209: =Data!HK208/Data!K208 -> 0.59609197 | E209: =Data!IC208/Data!K208 -> 0.014657594 | F209: 0 | G209: =Data!HI208/Data!K208 -> 0.16905019 | I209: =Y209-O209 -> 0.19137399 | O209: =W209/0.7 -> 0.066757699 | S209: =(Data!K208-Data!AN208)/Data!K208 -> 0.099045951 | W209: =Data!HU208/Data!K208 -> 0.046730389 | Y209: =Data!IE208/Data!K208 -> 0.25813169 | AA209: =D209+Y209+W209+S209 -> 1 | AB209: =(Y209-C209)/(1-S209-C209) -> 0.17136441 | AC209: =(Y209)/(1-S209) -> 0.28650927 | AG209: =AC209+D209+W209+S209 -> 1.0283776
